Workbook
Name IQ_CH: 110000
Name IQ_CQ: 5000
Name IQ_CY: 10000
Name IQ_DAILY: 500000
Name IQ_FH: 100000
Name IQ_FQ: 500
Name IQ_FY: 1000
Name IQ_LTM: 2000
Name IQ_MONTH: 15000
Name IQ_NTM: 6000
Name IQ_WEEK: 50000
Name IQ_YTD: 3000

Sheet Buenaventura
Q5: Remuneración Directores
R6: 2024 | S6: 2023
Q7: USD (000) | R7: 4415 | S7: 2223

Sheet Cerro Verde
C4: No tiene

Sheet Minsur

Sheet Volcan
D8: No tiene

Sheet Nexa Pe

Sheet Nexa US

Sheet HOC

Sheet Orygen

Sheet Pluzen

Sheet Engie

Sheet Ferrey

Sheet Aenza

Sheet Unacem

Sheet Pacasmayo

Sheet Inretail

Sheet Alicorp
C4: No tiene

Sheet BAP
D7: No tiene

Sheet IFS
B4: Individual

Sheet BBVA

Sheet El Comercio

Sheet Consolidado
G3: Remuneracion Directorio (000) | I3: # Directores | K3: Prom. Por Director
E4: Empresa | F4: Moneda | G4: 2024 | H4: 2023 | I4: 2024 | J4: 2023 | K4: 2024 | L4: 2023 | O4: No separan Key Management y Directores
E5: Mineras | O5: 1
E6: Buenaventura | F6: USD | G6: 3383 | H6: 999 | I6: 9 | J6: 7 | K6: =IFERROR(G6/I6,"-") -> 375.88889 | L6: =IFERROR(H6/J6,"-") -> 142.71429
E7: Cerro Verde | F7: - | G7: - | H7: - | I7: 5 | J7: 5 | K7: =IFERROR(G7/I7,"-") -> - | L7: =IFERROR(H7/J7,"-") -> -
E8: Minsur | F8: USD | G8: 540 | H8: 538 | I8: 8 | J8: 8 | K8: =IFERROR(G8/I8,"-") -> 67.5 | L8: =IFERROR(H8/J8,"-") -> 67.25
E9: Volcan | F9: USD | G9: 14433 | H9: 10571 | I9: 7 | J9: 7 | K9: =IFERROR(G9/I9,"-") -> 2061.8571 | L9: =IFERROR(H9/J9,"-") -> 1510.1429
E10: Nexa Perú | F10: USD | G10: 11342 | H10: 13951 | I10: 5 | J10: 5 | K10: =IFERROR(G10/I10,"-") -> 2268.4 | L10: =IFERROR(H10/J10,"-") -> 2790.2
E11: Nexa US | F11: USD | G11: 7829 | H11: 7353 | I11: 9 | J11: 9 | K11: =IFERROR(G11/I11,"-") -> 869.88889 | L11: =IFERROR(H11/J11,"-") -> 817
E12: Hochschild | F12: USD | G12: 8284 | H12: 7416 | I12: 9 | J12: 9 | K12: =IFERROR(G12/I12,"-") -> 920.44444 | L12: =IFERROR(H12/J12,"-") -> 824
E13: Utilities
E14: Orygen | F14: PEN | G14: 9339 | H14: 9008 | I14: 7 | J14: 7 | K14: =IFERROR(G14/I14,"-") -> 1334.1429 | L14: =IFERROR(H14/J14,"-") -> 1286.8571
E15: Pluzen | F15: PEN | G15: 9514 | H15: 7315 | I15: 7 | J15: 7 | K15: =IFERROR(G15/I15,"-") -> 1359.1429 | L15: =IFERROR(H15/J15,"-") -> 1045
E16: Engie | F16: USD | G16: 1974 | H16: 869 | I16: 7 | J16: 7 | K16: =IFERROR(G16/I16,"-") -> 282 | L16: =IFERROR(H16/J16,"-") -> 124.14286
E17: Construccion
E18: Ferreycorp | F18: PEN | G18: 44340 | H18: 42031 | I18: 9 | J18: 9 | K18: =IFERROR(G18/I18,"-") -> 4926.6667 | L18: =IFERROR(H18/J18,"-") -> 4670.1111
E19: Aenza | F19: PEN | G19: 32000 | H19: 36500 | I19: 9 | J19: 9 | K19: =IFERROR(G19/I19,"-") -> 3555.5556 | L19: =IFERROR(H19/J19,"-") -> 4055.5556
E20: UNACEM | F20: PEN | G20: 6724 | H20: 6323 | I20: 11 | J20: 11 | K20: =IFERROR(G20/I20,"-") -> 611.27273 | L20: =IFERROR(H20/J20,"-") -> 574.81818
E21: Pacasmayo | F21: PEN | G21: 6032 | H21: 5941 | I21: 7 | J21: 7 | K21: =IFERROR(G21/I21,"-") -> 861.71429 | L21: =IFERROR(H21/J21,"-") -> 848.71429
E22: Consumo
E23: Inretail | F23: PEN | G23: 72200 | H23: 65609 | I23: 6 | J23: 6 | K23: =IFERROR(G23/I23,"-") -> 12033.333 | L23: =IFERROR(H23/J23,"-") -> 10934.833
E24: Alicorp | F24: - | G24: - | H24: - | I24: 9 | J24: 9 | K24: =IFERROR(G24/I24,"-") -> - | L24: =IFERROR(H24/J24,"-") -> -
E25: Financieras
E26: BAP | F26: PEN | G26: - | H26: - | I26: 9 | J26: 9 | K26: =IFERROR(G26/I26,"-") -> - | L26: =IFERROR(H26/J26,"-") -> -
E27: IFS | F27: PEN | G27: =2160/O5 -> 2160 | H27: =2104/O5 -> 2104 | I27: 7 | J27: 7 | K27: =IFERROR(G27/I27,"-") -> 308.57143 | L27: =IFERROR(H27/J27,"-") -> 300.57143
E28: BBVA | F28: PEN | G28: =16000/O5 -> 16000 | H28: =15000/O5 -> 15000 | I28: 11 | J28: 11 | K28: =IFERROR(G28/I28,"-") -> 1454.5455 | L28: =IFERROR(H28/J28,"-") -> 1363.6364
E29: Otros
E30: El Comercio | F30: PEN

Sheet _CIQHiddenCacheSheet
A1: 39 | B1: BAABTAVMT0NBTAFI/////wFQoQAAACdDSVEuSVEzOTI4MjQuSVFfVE9UQUxfUkVWLkZZMjAyNC4uLi5VU0QBAAAAeP4FAAIAAAAIMTE1NC42MDUBCAAAAAUAAAABMQEAAAALLTE5NTg4MDE2OTMDAAAAAzE2MAIAAAACMjgEAAAAATAHAAAACTMvMjcvMjAyNQgAAAAKMTIvMzEvMjAyNAkAAAABMPwPA4ZVbd0IPLThVFdt3QgnQ0lRLklRMzkyODI0LklRX1RPVEFMX1JFVi5GWTIwMjMuLi4uVVNEAQAAAHj+BQACAAAABzgyMy44NDUBCAAAAAUAAAABMQEAAAALLTIwMDY4NzQ2MjEDAAAAAzE2MAIAAAACMjgEAAAAATAHAAAACTMvMjcvMjAyNQgAAAAKMTIvMzEvMjAyMwkAAAABMPwPA4ZVbd0IPLThVFdt3QgnQ0lRLklRMzkyODI0LklRX1RPVEFMX1JFVi5GWTIwMjIuLi4uVVNEAQAAAHj+BQACAAAABzgyNC44MDIBCAAAAAUAAAABMQEAAAALLTIwMDY4NzQ2MTEDAAAAAzE2MAIAAAACMjgEAAAAATAHAAAACTMvMjcvMjAyNQgAAAAKMTIvMzEvMjAyMgkAAAABMPwPA4ZVbd0I37PgVFdt3QgkQ0lRLklRMzkyODI0LklRX0VCSVREQS5GWTIwMjQuLi4uVVNEAQAAAHj+BQACAAAABzQwMy4yNzUBCAAAAAUAAAABMQEAAAALLTE5NTg4MDE2OTMDAAAAAzE2MAIAAAAENDA1MQQAAAABMAcAAAAJMy8yNy8yMDI1CAAAAAoxMi8zMS8yMDI0CQAAAAEw/A8DhlVt3Qjfs+BUV23dCCRDSVEuSVEzOTI4MjQuSVFfRUJJVERB | C1: LkZZMjAyMy4uLi5VU0QBAAAAeP4FAAIAAAAHMTU4LjY2MwEIAAAABQAAAAExAQAAAAstMjAwNjg3NDYyMQMAAAADMTYwAgAAAAQ0MDUxBAAAAAEwBwAAAAkzLzI3LzIwMjUIAAAACjEyLzMxLzIwMjMJAAAAATD8DwOGVW3dCDy04VRXbd0IJENJUS5JUTM5MjgyNC5JUV9FQklUREEuRlkyMDIyLi4uLlVTRAEAAAB4/gUAAgAAAAcxMzIuMzYzAQgAAAAFAAAAATEBAAAACy0yMDA2ODc0NjExAwAAAAMxNjACAAAABDQwNTEEAAAAATAHAAAACTMvMjcvMjAyNQgAAAAKMTIvMzEvMjAyMgkAAAABMPwPA4ZVbd0IPLThVFdt3QggQ0lRLklRMzkyODI0LklRX05JLkZZMjAyNC4uLi5VU0QBAAAAeP4FAAIAAAAHNDAyLjY4OQEIAAAABQAAAAExAQAAAAstMTk1ODgwMTY5MwMAAAADMTYwAgAAAAIxNQQAAAABMAcAAAAJMy8yNy8yMDI1CAAAAAoxMi8zMS8yMDI0CQAAAAEw/A8DhlVt3Qg8tOFUV23dCCBDSVEuSVEzOTI4MjQuSVFfTkkuRlkyMDIzLi4uLlVTRAEAAAB4/gUAAgAAAAYxOS44NTUBCAAAAAUAAAABMQEAAAALLTIwMDY4NzQ2MjEDAAAAAzE2MAIAAAACMTUEAAAAATAHAAAACTMvMjcvMjAyNQgAAAAKMTIvMzEvMjAyMwkAAAABMPwPA4ZVbd0IPLThVFdt3QggQ0lRLklRMzkyODI0LklRX05JLkZZMjAyMi4uLi5VU0QBAAAAeP4FAAIAAAAGNjAyLjU1AQgAAAAFAAAAATEBAAAACy0yMDA2ODc0NjExAwAAAAMx | D1: NjACAAAAAjE1BAAAAAEwBwAAAAkzLzI3LzIwMjUIAAAACjEyLzMxLzIwMjIJAAAAATD8DwOGVW3dCDy04VRXbd0IJ0NJUS5JUTg4MDEyMC5JUV9UT1RBTF9SRVYuRlkyMDI0Li4uLlVTRAEAAAD4bQ0AAgAAAAgyMTcwLjQwMwEIAAAABQAAAAExAQAAAAstMTk1NTkwMzY1NAMAAAADMTYwAgAAAAIyOAQAAAABMAcAAAAJMy8yNy8yMDI1CAAAAAoxMi8zMS8yMDI0CQAAAAEw/A8DhlVt3Qg8tOFUV23dCCdDSVEuSVE4ODAxMjAuSVFfVE9UQUxfUkVWLkZZMjAyMy4uLi5VU0QBAAAA+G0NAAIAAAAHMjAxMC43NQEIAAAABQAAAAExAQAAAAstMTk1NTkwMzY1MgMAAAADMTYwAgAAAAIyOAQAAAABMAcAAAAJMy8yNy8yMDI1CAAAAAoxMi8zMS8yMDIzCQAAAAEw/A8DhlVt3Qg8tOFUV23dCCdDSVEuSVE4ODAxMjAuSVFfVE9UQUxfUkVWLkZZMjAyMi4uLi5VU0QBAAAA+G0NAAIAAAAIMjI3NC45NzkBCAAAAAUAAAABMQEAAAALLTIwMDIyNDA1NzYDAAAAAzE2MAIAAAACMjgEAAAAATAHAAAACTMvMjcvMjAyNQgAAAAKMTIvMzEvMjAyMgkAAAABMPwPA4ZVbd0IPLThVFdt3QgkQ0lRLklRODgwMTIwLklRX0VCSVREQS5GWTIwMjQuLi4uVVNEAQAAAPhtDQACAAAACDE0NDQuMDUzAQgAAAAFAAAAATEBAAAACy0xOTU1OTAzNjU0AwAAAAMxNjACAAAABDQwNTEEAAAAATAHAAAACTMvMjcvMjAyNQgAAAAKMTIvMzEvMjAy | E1: NAkAAAABMPwPA4ZVbd0I37PgVFdt3QgkQ0lRLklRODgwMTIwLklRX0VCSVREQS5GWTIwMjMuLi4uVVNEAQAAAPhtDQACAAAACDEyMTEuNjIxAQgAAAAFAAAAATEBAAAACy0xOTU1OTAzNjUyAwAAAAMxNjACAAAABDQwNTEEAAAAATAHAAAACTMvMjcvMjAyNQgAAAAKMTIvMzEvMjAyMwkAAAABMPwPA4ZVbd0IPLThVFdt3QgkQ0lRLklRODgwMTIwLklRX0VCSVREQS5GWTIwMjIuLi4uVVNEAQAAAPhtDQACAAAACDEzMDYuMTI4AQgAAAAFAAAAATEBAAAACy0yMDAyMjQwNTc2AwAAAAMxNjACAAAABDQwNTEEAAAAATAHAAAACTMvMjcvMjAyNQgAAAAKMTIvMzEvMjAyMgkAAAABMPwPA4ZVbd0IPLThVFdt3QggQ0lRLklRODgwMTIwLklRX05JLkZZMjAyNC4uLi5VU0QBAAAA+G0NAAIAAAAHNDYzLjU0NgEIAAAABQAAAAExAQAAAAstMTk1NTkwMzY1NAMAAAADMTYwAgAAAAIxNQQAAAABMAcAAAAJMy8yNy8yMDI1CAAAAAoxMi8zMS8yMDI0CQAAAAEw/A8DhlVt3Qjfs+BUV23dCCBDSVEuSVE4ODAxMjAuSVFfTkkuRlkyMDIzLi4uLlVTRAEAAAD4bQ0AAgAAAAczOTUuMzAzAQgAAAAFAAAAATEBAAAACy0xOTU1OTAzNjUyAwAAAAMxNjACAAAAAjE1BAAAAAEwBwAAAAkzLzI3LzIwMjUIAAAACjEyLzMxLzIwMjMJAAAAATD8DwOGVW3dCDy04VRXbd0IIENJUS5JUTg4MDEyMC5JUV9OSS5GWTIwMjIuLi4uVVNEAQAA | F1: APhtDQACAAAABzQ5Ni4yMzkBCAAAAAUAAAABMQEAAAALLTIwMDIyNDA1NzYDAAAAAzE2MAIAAAACMTUEAAAAATAHAAAACTMvMjcvMjAyNQgAAAAKMTIvMzEvMjAyMgkAAAABMPwPA4ZVbd0IPLThVFdt3QgnQ0lRLklRODc3NTE1LklRX1RPVEFMX1JFVi5GWTIwMjQuLi4uVVNEAQAAAMtjDQACAAAABzk2MC41MjEBCAAAAAUAAAABMQEAAAALLTE5NTUxNzM0MTIDAAAAAzE2MAIAAAACMjgEAAAAATAHAAAACTMvMjcvMjAyNQgAAAAKMTIvMzEvMjAyNAkAAAABMPwPA4ZVbd0IPLThVFdt3QgnQ0lRLklRODc3NTE1LklRX1RPVEFMX1JFVi5GWTIwMjMuLi4uVVNEAQAAAMtjDQACAAAABzg4My4wODYBCAAAAAUAAAABMQEAAAALLTE5NTUxNzM0MTYDAAAAAzE2MAIAAAACMjgEAAAAATAHAAAACTMvMjcvMjAyNQgAAAAKMTIvMzEvMjAyMwkAAAABMPwPA4ZVbd0I37PgVFdt3QgnQ0lRLklRODc3NTE1LklRX1RPVEFMX1JFVi5GWTIwMjIuLi4uVVNEAQAAAMtjDQACAAAABzk1MS4yNjYBCAAAAAUAAAABMQEAAAALLTIwMDQwNDY4MTcDAAAAAzE2MAIAAAACMjgEAAAAATAHAAAACTMvMjcvMjAyNQgAAAAKMTIvMzEvMjAyMgkAAAABMPwPA4ZVbd0IPLThVFdt3QgkQ0lRLklRODc3NTE1LklRX0VCSVREQS5GWTIwMjQuLi4uVVNEAQAAAMtjDQACAAAABzM4MS40NzYBCAAAAAUAAAABMQEAAAALLTE5NTUxNzM0MTIDAAAA | G1: AzE2MAIAAAAENDA1MQQAAAABMAcAAAAJMy8yNy8yMDI1CAAAAAoxMi8zMS8yMDI0CQAAAAEw/A8DhlVt3Qg8tOFUV23dCCRDSVEuSVE4Nzc1MTUuSVFfRUJJVERBLkZZMjAyMy4uLi5VU0QBAAAAy2MNAAIAAAAHMjU1LjA2NQEIAAAABQAAAAExAQAAAAstMTk1NTE3MzQxNgMAAAADMTYwAgAAAAQ0MDUxBAAAAAEwBwAAAAkzLzI3LzIwMjUIAAAACjEyLzMxLzIwMjMJAAAAATD8DwOGVW3dCDy04VRXbd0IJENJUS5JUTg3NzUxNS5JUV9FQklUREEuRlkyMDIyLi4uLlVTRAEAAADLYw0AAgAAAAcyODUuMzA0AQgAAAAFAAAAATEBAAAACy0yMDA0MDQ2ODE3AwAAAAMxNjACAAAABDQwNTEEAAAAATAHAAAACTMvMjcvMjAyNQgAAAAKMTIvMzEvMjAyMgkAAAABMPwPA4ZVbd0I37PgVFdt3QggQ0lRLklRODc3NTE1LklRX05JLkZZMjAyNC4uLi5VU0QBAAAAy2MNAAIAAAAHMTM3LjEzMwEIAAAABQAAAAExAQAAAAstMTk1NTE3MzQxMgMAAAADMTYwAgAAAAIxNQQAAAABMAcAAAAJMy8yNy8yMDI1CAAAAAoxMi8zMS8yMDI0CQAAAAEw/A8DhlVt3Qg8tOFUV23dCCBDSVEuSVE4Nzc1MTUuSVFfTkkuRlkyMDIzLi4uLlVTRAEAAADLYw0AAgAAAAYtOS45ODMBCAAAAAUAAAABMQEAAAALLTE5NTUxNzM0MTYDAAAAAzE2MAIAAAACMTUEAAAAATAHAAAACTMvMjcvMjAyNQgAAAAKMTIvMzEvMjAyMwkAAAABMPwPA4ZVbd0I | H1: PLThVFdt3QggQ0lRLklRODc3NTE1LklRX05JLkZZMjAyMi4uLi5VU0QBAAAAy2MNAAIAAAAHLTgxLjM4MgEIAAAABQAAAAExAQAAAAstMjAwNDA0NjgxNwMAAAADMTYwAgAAAAIxNQQAAAABMAcAAAAJMy8yNy8yMDI1CAAAAAoxMi8zMS8yMDIyCQAAAAEw/A8DhlVt3Qg8tOFUV23dCCdDSVEuSVE4Nzc2ODcuSVFfVE9UQUxfUkVWLkZZMjAyNC4uLi5VU0QBAAAAd2QNAAIAAAAHODgxLjEyMgEIAAAABQAAAAExAQAAAAstMTk1NzIyODM0OQMAAAADMTYwAgAAAAIyOAQAAAABMAcAAAAJMy8yNy8yMDI1CAAAAAoxMi8zMS8yMDI0CQAAAAEw/A8DhlVt3Qjfs+BUV23dCCdDSVEuSVE4Nzc2ODcuSVFfVE9UQUxfUkVWLkZZMjAyMy4uLi5VU0QBAAAAd2QNAAIAAAAHNzM1LjMzNwEIAAAABQAAAAExAQAAAAstMTk1NzIyODM1NAMAAAADMTYwAgAAAAIyOAQAAAABMAcAAAAJMy8yNy8yMDI1CAAAAAoxMi8zMS8yMDIzCQAAAAEw/A8DhlVt3Qg8tOFUV23dCCdDSVEuSVE4Nzc2ODcuSVFfVE9UQUxfUkVWLkZZMjAyMi4uLi5VU0QBAAAAd2QNAAIAAAAHODkyLjM4OQEIAAAABQAAAAExAQAAAAstMjAwODgxNjUzNAMAAAADMTYwAgAAAAIyOAQAAAABMAcAAAAJMy8yNy8yMDI1CAAAAAoxMi8zMS8yMDIyCQAAAAEw/A8DhlVt3Qg8tOFUV23dCCRDSVEuSVE4Nzc2ODcuSVFfRUJJVERBLkZZMjAyNC4uLi5VU0QBAAAAd2QN | I1: AAIAAAAHMzMzLjcwNQEIAAAABQAAAAExAQAAAAstMTk1NzIyODM0OQMAAAADMTYwAgAAAAQ0MDUxBAAAAAEwBwAAAAkzLzI3LzIwMjUIAAAACjEyLzMxLzIwMjQJAAAAATD8DwOGVW3dCDy04VRXbd0IJENJUS5JUTg3NzY4Ny5JUV9FQklUREEuRlkyMDIzLi4uLlVTRAEAAAB3ZA0AAgAAAAcxODcuODk2AQgAAAAFAAAAATEBAAAACy0xOTU3MjI4MzU0AwAAAAMxNjACAAAABDQwNTEEAAAAATAHAAAACTMvMjcvMjAyNQgAAAAKMTIvMzEvMjAyMwkAAAABMPwPA4ZVbd0IPLThVFdt3QgkQ0lRLklRODc3Njg3LklRX0VCSVREQS5GWTIwMjIuLi4uVVNEAQAAAHdkDQACAAAABzMxNi45NzQBCAAAAAUAAAABMQEAAAALLTIwMDg4MTY1MzQDAAAAAzE2MAIAAAAENDA1MQQAAAABMAcAAAAJMy8yNy8yMDI1CAAAAAoxMi8zMS8yMDIyCQAAAAEw/A8DhlVt3Qg8tOFUV23dCCBDSVEuSVE4Nzc2ODcuSVFfTkkuRlkyMDI0Li4uLlVTRAEAAAB3ZA0AAgAAAAU0LjIwNwEIAAAABQAAAAExAQAAAAstMTk1NzIyODM0OQMAAAADMTYwAgAAAAIxNQQAAAABMAcAAAAJMy8yNy8yMDI1CAAAAAoxMi8zMS8yMDI0CQAAAAEw/A8DhlVt3Qjfs+BUV23dCCBDSVEuSVE4Nzc2ODcuSVFfTkkuRlkyMDIzLi4uLlVTRAEAAAB3ZA0AAgAAAAY0Ni45MzEBCAAAAAUAAAABMQEAAAALLTE5NTcyMjgzNTQDAAAAAzE2MAIAAAACMTUEAAAAATAH | J1: AAAACTMvMjcvMjAyNQgAAAAKMTIvMzEvMjAyMwkAAAABMPwPA4ZVbd0IPLThVFdt3QggQ0lRLklRODc3Njg3LklRX05JLkZZMjAyMi4uLi5VU0QBAAAAd2QNAAIAAAAGOTQuODQ1AQgAAAAFAAAAATEBAAAACy0yMDA4ODE2NTM0AwAAAAMxNjACAAAAAjE1BAAAAAEwBwAAAAkzLzI3LzIwMjUIAAAACjEyLzMxLzIwMjIJAAAAATD8DwOGVW3dCDy04VRXbd0IKkNJUS5JUTI4NDgzOTkyOS5JUV9UT1RBTF9SRVYuRlkyMDI0Li4uLlVTRAEAAAD5T/oQAgAAAAgyNzY2LjQ4MQEIAAAABQAAAAExAQAAAAstMTk1ODQwNzA4MwMAAAADMTYwAgAAAAIyOAQAAAABMAcAAAAJMy8yNy8yMDI1CAAAAAoxMi8zMS8yMDI0CQAAAAEw/A8DhlVt3Qg8tOFUV23dCCpDSVEuSVEyODQ4Mzk5MjkuSVFfVE9UQUxfUkVWLkZZMjAyMy4uLi5VU0QBAAAA+U/6EAIAAAAIMjU3My4yMzMBCAAAAAUAAAABMQEAAAALLTE5NTg0MDcwNzcDAAAAAzE2MAIAAAACMjgEAAAAATAHAAAACTMvMjcvMjAyNQgAAAAKMTIvMzEvMjAyMwkAAAABMPwPA4ZVbd0IPLThVFdt3QgqQ0lRLklRMjg0ODM5OTI5LklRX1RPVEFMX1JFVi5GWTIwMjIuLi4uVVNEAQAAAPlP+hACAAAABzMwMzMuOTkBCAAAAAUAAAABMQEAAAALLTE5NTg0MDcwOTADAAAAAzE2MAIAAAACMjgEAAAAATAHAAAACTMvMjcvMjAyNQgAAAAKMTIvMzEvMjAyMgkAAAABMPwPA4ZVbd0I | K1: 37PgVFdt3QgnQ0lRLklRMjg0ODM5OTI5LklRX0VCSVREQS5GWTIwMjQuLi4uVVNEAQAAAPlP+hACAAAABzYwOC41MTIBCAAAAAUAAAABMQEAAAALLTE5NTg0MDcwODMDAAAAAzE2MAIAAAAENDA1MQQAAAABMAcAAAAJMy8yNy8yMDI1CAAAAAoxMi8zMS8yMDI0CQAAAAEw/A8DhlVt3Qg8tOFUV23dCCdDSVEuSVEyODQ4Mzk5MjkuSVFfRUJJVERBLkZZMjAyMy4uLi5VU0QBAAAA+U/6EAIAAAAHMjczLjI0NwEIAAAABQAAAAExAQAAAAstMTk1ODQwNzA3NwMAAAADMTYwAgAAAAQ0MDUxBAAAAAEwBwAAAAkzLzI3LzIwMjUIAAAACjEyLzMxLzIwMjMJAAAAATD8DwOGVW3dCN+z4FRXbd0IJ0NJUS5JUTI4NDgzOTkyOS5JUV9FQklUREEuRlkyMDIyLi4uLlVTRAEAAAD5T/oQAgAAAAc2OTMuOTExAQgAAAAFAAAAATEBAAAACy0xOTU4NDA3MDkwAwAAAAMxNjACAAAABDQwNTEEAAAAATAHAAAACTMvMjcvMjAyNQgAAAAKMTIvMzEvMjAyMgkAAAABMPwPA4ZVbd0IPLThVFdt3QgjQ0lRLklRMjg0ODM5OTI5LklRX05JLkZZMjAyNC4uLi5VU0QBAAAA+U/6EAIAAAAHLTIwNS4wMwEIAAAABQAAAAExAQAAAAstMTk1ODQwNzA4MwMAAAADMTYwAgAAAAIxNQQAAAABMAcAAAAJMy8yNy8yMDI1CAAAAAoxMi8zMS8yMDI0CQAAAAEw/A8DhlVt3Qg8tOFUV23dCCNDSVEuSVEyODQ4Mzk5MjkuSVFfTkkuRlkyMDIzLi4uLlVT | L1: RAEAAAD5T/oQAgAAAAgtMjkxLjk2OAEIAAAABQAAAAExAQAAAAstMTk1ODQwNzA3NwMAAAADMTYwAgAAAAIxNQQAAAABMAcAAAAJMy8yNy8yMDI1CAAAAAoxMi8zMS8yMDIzCQAAAAEw/A8DhlVt3Qg8tOFUV23dCCNDSVEuSVEyODQ4Mzk5MjkuSVFfTkkuRlkyMDIyLi4uLlVTRAEAAAD5T/oQAgAAAAY0OS42OTUBCAAAAAUAAAABMQEAAAALLTE5NTg0MDcwOTADAAAAAzE2MAIAAAACMTUEAAAAATAHAAAACTMvMjcvMjAyNQgAAAAKMTIvMzEvMjAyMgkAAAABMPwPA4ZVbd0I37PgVFdt3QgpQ0lRLklRMjk2NjY1NjkuSVFfVE9UQUxfUkVWLkZZMjAyNC4uLi5VU0QBAAAACa3EAQIAAAAHOTQ3LjY5NgEIAAAABQAAAAExAQAAAAstMTk1NjI4OTcwMwMAAAADMTYwAgAAAAIyOAQAAAABMAcAAAAJMy8yNy8yMDI1CAAAAAoxMi8zMS8yMDI0CQAAAAEw/A8DhlVt3Qg8tOFUV23dCClDSVEuSVEyOTY2NjU2OS5JUV9UT1RBTF9SRVYuRlkyMDIzLi4uLlVTRAEAAAAJrcQBAgAAAAc2OTMuNzE2AQgAAAAFAAAAATEBAAAACy0xOTk0OTU3NTgyAwAAAAMxNjACAAAAAjI4BAAAAAEwBwAAAAkzLzI3LzIwMjUIAAAACjEyLzMxLzIwMjMJAAAAATD8DwOGVW3dCDy04VRXbd0IKUNJUS5JUTI5NjY2NTY5LklRX1RPVEFMX1JFVi5GWTIwMjIuLi4uVVNEAQAAAAmtxAECAAAABzczNS42NDMBCAAAAAUAAAABMQEAAAALLTE5OTQ5 | M1: NTc1ODEDAAAAAzE2MAIAAAACMjgEAAAAATAHAAAACTMvMjcvMjAyNQgAAAAKMTIvMzEvMjAyMgkAAAABMPwPA4ZVbd0IPLThVFdt3QgmQ0lRLklRMjk2NjY1NjkuSVFfRUJJVERBLkZZMjAyNC4uLi5VU0QBAAAACa3EAQIAAAAHMzgwLjgzNgEIAAAABQAAAAExAQAAAAstMTk1NjI4OTcwMwMAAAADMTYwAgAAAAQ0MDUxBAAAAAEwBwAAAAkzLzI3LzIwMjUIAAAACjEyLzMxLzIwMjQJAAAAATD8DwOGVW3dCN+z4FRXbd0IJkNJUS5JUTI5NjY2NTY5LklRX0VCSVREQS5GWTIwMjMuLi4uVVNEAQAAAAmtxAECAAAABzIyNy4zMTIBCAAAAAUAAAABMQEAAAALLTE5OTQ5NTc1ODIDAAAAAzE2MAIAAAAENDA1MQQAAAABMAcAAAAJMy8yNy8yMDI1CAAAAAoxMi8zMS8yMDIzCQAAAAEw/A8DhlVt3Qg8tOFUV23dCCZDSVEuSVEyOTY2NjU2OS5JUV9FQklUREEuRlkyMDIyLi4uLlVTRAEAAAAJrcQBAgAAAAcxOTIuODU1AQgAAAAFAAAAATEBAAAACy0xOTk0OTU3NTgxAwAAAAMxNjACAAAABDQwNTEEAAAAATAHAAAACTMvMjcvMjAyNQgAAAAKMTIvMzEvMjAyMgkAAAABMPwPA4ZVbd0IPLThVFdt3QgiQ0lRLklRMjk2NjY1NjkuSVFfTkkuRlkyMDI0Li4uLlVTRAEAAAAJrcQBAgAAAAY5Ny4wMDUBCAAAAAUAAAABMQEAAAALLTE5NTYyODk3MDMDAAAAAzE2MAIAAAACMTUEAAAAATAHAAAACTMvMjcvMjAyNQgAAAAKMTIv | N1: MzEvMjAyNAkAAAABMPwPA4ZVbd0IPLThVFdt3QgiQ0lRLklRMjk2NjY1NjkuSVFfTkkuRlkyMDIzLi4uLlVTRAEAAAAJrcQBAgAAAActNTUuMDA2AQgAAAAFAAAAATEBAAAACy0xOTk0OTU3NTgyAwAAAAMxNjACAAAAAjE1BAAAAAEwBwAAAAkzLzI3LzIwMjUIAAAACjEyLzMxLzIwMjMJAAAAATD8DwOGVW3dCDy04VRXbd0IIkNJUS5JUTI5NjY2NTY5LklRX05JLkZZMjAyMi4uLi5VU0QBAAAACa3EAQIAAAAFMi45NjEBCAAAAAUAAAABMQEAAAALLTE5OTQ5NTc1ODEDAAAAAzE2MAIAAAACMTUEAAAAATAHAAAACTMvMjcvMjAyNQgAAAAKMTIvMzEvMjAyMgkAAAABMPwPA4ZVbd0IPLThVFdt3QgnQ0lRLklRODc3NDgyLklRX1RPVEFMX1JFVi5GWTIwMjQuLi4uVVNEAQAAAKpjDQACAAAACzI4MTAuMDM0OTk1AQgAAAAFAAAAATEBAAAACy0xOTU5MjA1NTgxAwAAAAMxNjACAAAAAjI4BAAAAAEwBwAAAAkzLzI3LzIwMjUIAAAACjEyLzMxLzIwMjQJAAAAATD8DwOGVW3dCDy04VRXbd0IIENJUS5JUTg3NzQ4Mi5JUV9UT1RBTF9SRVYuRlkyMDI0AQAAAKpjDQACAAAACTEwNTk4LjMyOAEIAAAABQAAAAExAQAAAAstMTk1OTIwNTU4MQMAAAADMTIyAgAAAAIyOAQAAAABMAcAAAAJMy8yNy8yMDI1CAAAAAoxMi8zMS8yMDI0CQAAAAEw/A8DhlVt3Qg8tOFUV23dCCdDSVEuSVE4Nzc0ODIuSVFfVE9UQUxfUkVWLkZZ | O1: MjAyMy4uLi5VU0QBAAAAqmMNAAIAAAALMzY3Ny4zMjk3NDQBCAAAAAUAAAABMQEAAAALLTE5OTM1OTgxNzUDAAAAAzE2MAIAAAACMjgEAAAAATAHAAAACTMvMjcvMjAyNQgAAAAKMTIvMzEvMjAyMwkAAAABMPwPA4ZVbd0IwhfkVFdt3QggQ0lRLklRODc3NDgyLklRX1RPVEFMX1JFVi5GWTIwMjMBAAAAqmMNAAIAAAAJMTM2NTUuNzY0AQgAAAAFAAAAATEBAAAACy0xOTkzNTk4MTc1AwAAAAMxMjICAAAAAjI4BAAAAAEwBwAAAAkzLzI3LzIwMjUIAAAACjEyLzMxLzIwMjMJAAAAATD8DwOGVW3dCDy04VRXbd0IJ0NJUS5JUTg4MzExMC5JUV9UT1RBTF9SRVYuRlkyMDI0Li4uLlVTRAEAAACmeQ0AAgAAAAo3NDEuOTUzODEyAQgAAAAFAAAAATEBAAAACy0xOTU2NDIxNDc2AwAAAAMxNjACAAAAAjI4BAAAAAEwBwAAAAkzLzI3LzIwMjUIAAAACjEyLzMxLzIwMjQJAAAAATD8DwOGVW3dCDy04VRXbd0IJ0NJUS5JUTg4MzExMC5JUV9UT1RBTF9SRVYuRlkyMDIzLi4uLlVTRAEAAACmeQ0AAgAAAAo3MDYuMjIzNTA5AQgAAAAFAAAAATEBAAAACy0yMDAwMzk3Mzk0AwAAAAMxNjACAAAAAjI4BAAAAAEwBwAAAAkzLzI3LzIwMjUIAAAACjEyLzMxLzIwMjMJAAAAATD8DwOGVW3dCC/vMctebd0IJ0NJUS5JUTg4MzExMC5JUV9UT1RBTF9SRVYuRlkyMDIyLi4uLlVTRAEAAACmeQ0AAgAAAAo2MjMuNTI2MjkxAQgAAAAF | P1: AAAAATEBAAAACy0yMDAwMzk3MzcxAwAAAAMxNjACAAAAAjI4BAAAAAEwBwAAAAkzLzI3LzIwMjUIAAAACjEyLzMxLzIwMjIJAAAAATD8DwOGVW3dCIl7qdZebd0IJENJUS5JUTg4MzExMC5JUV9FQklUREEuRlkyMDI0Li4uLlVTRAEAAACmeQ0AAgAAAAo0MjguMjYyNTQxAQgAAAAFAAAAATEBAAAACy0xOTU2NDIxNDc2AwAAAAMxNjACAAAABDQwNTEEAAAAATAHAAAACTMvMjcvMjAyNQgAAAAKMTIvMzEvMjAyNAkAAAABMPwPA4ZVbd0IwhfkVFdt3QgkQ0lRLklRODgzMTEwLklRX0VCSVREQS5GWTIwMjMuLi4uVVNEAQAAAKZ5DQACAAAACjM1My4xMTU5MjgBCAAAAAUAAAABMQEAAAALLTIwMDAzOTczOTQDAAAAAzE2MAIAAAAENDA1MQQAAAABMAcAAAAJMy8yNy8yMDI1CAAAAAoxMi8zMS8yMDIzCQAAAAEw/A8DhlVt3Qgv7zHLXm3dCCRDSVEuSVE4ODMxMTAuSVFfRUJJVERBLkZZMjAyMi4uLi5VU0QBAAAApnkNAAIAAAAKMzI5Ljg0MTY5NAEIAAAABQAAAAExAQAAAAstMjAwMDM5NzM3MQMAAAADMTYwAgAAAAQ0MDUxBAAAAAEwBwAAAAkzLzI3LzIwMjUIAAAACjEyLzMxLzIwMjIJAAAAATD8DwOGVW3dCIl7qdZebd0IIENJUS5JUTg4MzExMC5JUV9OSS5GWTIwMjQuLi4uVVNEAQAAAKZ5DQACAAAACjI0Ni4zMDc5MzMBCAAAAAUAAAABMQEAAAALLTE5NTY0MjE0NzYDAAAAAzE2MAIAAAACMTUEAAAAATAH | Q1: AAAACTMvMjcvMjAyNQgAAAAKMTIvMzEvMjAyNAkAAAABMPwPA4ZVbd0IwhfkVFdt3QggQ0lRLklRODgzMTEwLklRX05JLkZZMjAyMy4uLi5VU0QBAAAApnkNAAIAAAAKMjE0LjczODY1NgEIAAAABQAAAAExAQAAAAstMjAwMDM5NzM5NAMAAAADMTYwAgAAAAIxNQQAAAABMAcAAAAJMy8yNy8yMDI1CAAAAAoxMi8zMS8yMDIzCQAAAAEw/A8DhlVt3Qgv7zHLXm3dCCBDSVEuSVE4ODMxMTAuSVFfTkkuRlkyMDIyLi4uLlVTRAEAAACmeQ0AAgAAAAoyMDcuMDg5NjAxAQgAAAAFAAAAATEBAAAACy0yMDAwMzk3MzcxAwAAAAMxNjACAAAAAjE1BAAAAAEwBwAAAAkzLzI3LzIwMjUIAAAACjEyLzMxLzIwMjIJAAAAATD8DwOGVW3dCIl7qdZebd0IKENJUS5JUTU4ODU5NjUuSVFfVE9UQUxfUkVWLkZZMjAyNC4uLi5VU0QBAAAADdBZAAIAAAALMTA4Ni45Mzc2MzgBCAAAAAUAAAABMQEAAAALLTE5NTYxODA1MjgDAAAAAzE2MAIAAAACMjgEAAAAATAHAAAACTMvMjcvMjAyNQgAAAAKMTIvMzEvMjAyNAkAAAABMPwPA4ZVbd0IwhfkVFdt3QgoQ0lRLklRNTg4NTk2NS5JUV9UT1RBTF9SRVYuRlkyMDIzLi4uLlVTRAEAAAAN0FkAAgAAAAsxMTE2LjgxODA5NgEIAAAABQAAAAExAQAAAAstMjAwMjc3NjA1OAMAAAADMTYwAgAAAAIyOAQAAAABMAcAAAAJMy8yNy8yMDI1CAAAAAoxMi8zMS8yMDIzCQAAAAEw/A8DhlVt3QiF | R1: 7l3YWW3dCChDSVEuSVE1ODg1OTY1LklRX1RPVEFMX1JFVi5GWTIwMjIuLi4uVVNEAQAAAA3QWQACAAAACzEwMjkuNDIxNjQ3AQgAAAAFAAAAATEBAAAACy0yMDAyNzc2MDQ2AwAAAAMxNjACAAAAAjI4BAAAAAEwBwAAAAkzLzI3LzIwMjUIAAAACjEyLzMxLzIwMjIJAAAAATD8DwOGVW3dCBzbYyZabd0IJUNJUS5JUTU4ODU5NjUuSVFfRUJJVERBLkZZMjAyNC4uLi5VU0QBAAAADdBZAAIAAAAKMjY1LjMwOTk0OAEIAAAABQAAAAExAQAAAAstMTk1NjE4MDUyOAMAAAADMTYwAgAAAAQ0MDUxBAAAAAEwBwAAAAkzLzI3LzIwMjUIAAAACjEyLzMxLzIwMjQJAAAAATD8DwOGVW3dCMIX5FRXbd0IJUNJUS5JUTU4ODU5NjUuSVFfRUJJVERBLkZZMjAyMy4uLi5VU0QBAAAADdBZAAIAAAAKMjU1LjY2NjA4MwEIAAAABQAAAAExAQAAAAstMjAwMjc3NjA1OAMAAAADMTYwAgAAAAQ0MDUxBAAAAAEwBwAAAAkzLzI3LzIwMjUIAAAACjEyLzMxLzIwMjMJAAAAATD8DwOGVW3dCIXuXdhZbd0IJUNJUS5JUTU4ODU5NjUuSVFfRUJJVERBLkZZMjAyMi4uLi5VU0QBAAAADdBZAAIAAAAKMjU0Ljg1NDQyNwEIAAAABQAAAAExAQAAAAstMjAwMjc3NjA0NgMAAAADMTYwAgAAAAQ0MDUxBAAAAAEwBwAAAAkzLzI3LzIwMjUIAAAACjEyLzMxLzIwMjIJAAAAATD8DwOGVW3dCBzbYyZabd0IIUNJUS5JUTU4ODU5NjUuSVFfTkkuRlky | S1: MDI0Li4uLlVTRAEAAAAN0FkAAgAAAAoxMDEuNzE4ODk5AQgAAAAFAAAAATEBAAAACy0xOTU2MTgwNTI4AwAAAAMxNjACAAAAAjE1BAAAAAEwBwAAAAkzLzI3LzIwMjUIAAAACjEyLzMxLzIwMjQJAAAAATD8DwOGVW3dCMIX5FRXbd0IIUNJUS5JUTU4ODU5NjUuSVFfTkkuRlkyMDIzLi4uLlVTRAEAAAAN0FkAAgAAAAoxMTYuNzEwMTEyAQgAAAAFAAAAATEBAAAACy0yMDAyNzc2MDU4AwAAAAMxNjACAAAAAjE1BAAAAAEwBwAAAAkzLzI3LzIwMjUIAAAACjEyLzMxLzIwMjMJAAAAATD8DwOGVW3dCPdQYNhZbd0IIUNJUS5JUTU4ODU5NjUuSVFfTkkuRlkyMDIyLi4uLlVTRAEAAAAN0FkAAgAAAAoxMjUuNzYyNzc4AQgAAAAFAAAAATEBAAAACy0yMDAyNzc2MDQ2AwAAAAMxNjACAAAAAjE1BAAAAAEwBwAAAAkzLzI3LzIwMjUIAAAACjEyLzMxLzIwMjIJAAAAATD8DwOGVW3dCBzbYyZabd0IKENJUS5JUTU3MDQ2ODguSVFfVE9UQUxfUkVWLkZZMjAyNC4uLi5VU0QBAAAA8AtXAAIAAAAHNzI0LjIxNwEIAAAABQAAAAExAQAAAAstMTk1ODg4MjY5MwMAAAADMTYwAgAAAAIyOAQAAAABMAcAAAAJMy8yNy8yMDI1CAAAAAoxMi8zMS8yMDI0CQAAAAEw/A8DhlVt3Qjfs+BUV23dCChDSVEuSVE1NzA0Njg4LklRX1RPVEFMX1JFVi5GWTIwMjMuLi4uVVNEAQAAAPALVwACAAAABzY3MS44MDMBCAAAAAUAAAABMQEAAAAL | T1: LTIwMDUyNDY3OTgDAAAAAzE2MAIAAAACMjgEAAAAATAHAAAACTMvMjcvMjAyNQgAAAAKMTIvMzEvMjAyMwkAAAABMPwPA4ZVbd0I3pi0GVtt3QgoQ0lRLklRNTcwNDY4OC5JUV9UT1RBTF9SRVYuRlkyMDIyLi4uLlVTRAEAAADwC1cAAgAAAAc1NTQuOTA3AQgAAAAFAAAAATEBAAAACy0yMDA1MjQ2NzgzAwAAAAMxNjACAAAAAjI4BAAAAAEwBwAAAAkzLzI3LzIwMjUIAAAACjEyLzMxLzIwMjIJAAAAATD8DwOGVW3dCFtChFhbbd0IJUNJUS5JUTU3MDQ2ODguSVFfRUJJVERBLkZZMjAyNC4uLi5VU0QBAAAA8AtXAAIAAAAHMjU3LjQ3NwEIAAAABQAAAAExAQAAAAstMTk1ODg4MjY5MwMAAAADMTYwAgAAAAQ0MDUxBAAAAAEwBwAAAAkzLzI3LzIwMjUIAAAACjEyLzMxLzIwMjQJAAAAATD8DwOGVW3dCDy04VRXbd0IJUNJUS5JUTU3MDQ2ODguSVFfRUJJVERBLkZZMjAyMy4uLi5VU0QBAAAA8AtXAAIAAAAGMTYxLjE4AQgAAAAFAAAAATEBAAAACy0yMDA1MjQ2Nzk4AwAAAAMxNjACAAAABDQwNTEEAAAAATAHAAAACTMvMjcvMjAyNQgAAAAKMTIvMzEvMjAyMwkAAAABMPwPA4ZVbd0I3pi0GVtt3QglQ0lRLklRNTcwNDY4OC5JUV9FQklUREEuRlkyMDIyLi4uLlVTRAEAAADwC1cAAgAAAAcxODguNTYyAQgAAAAFAAAAATEBAAAACy0yMDA1MjQ2NzgzAwAAAAMxNjACAAAABDQwNTEEAAAAATAHAAAACTMvMjcvMjAy | U1: NQgAAAAKMTIvMzEvMjAyMgkAAAABMPwPA4ZVbd0IW0KEWFtt3QghQ0lRLklRNTcwNDY4OC5JUV9OSS5GWTIwMjQuLi4uVVNEAQAAAPALVwACAAAABjk4LjU3OQEIAAAABQAAAAExAQAAAAstMTk1ODg4MjY5MwMAAAADMTYwAgAAAAIxNQQAAAABMAcAAAAJMy8yNy8yMDI1CAAAAAoxMi8zMS8yMDI0CQAAAAEw/A8DhlVt3Qjfs+BUV23dCCFDSVEuSVE1NzA0Njg4LklRX05JLkZZMjAyMy4uLi5VU0QBAAAA8AtXAAIAAAABNgEIAAAABQAAAAExAQAAAAstMjAwNTI0Njc5OAMAAAADMTYwAgAAAAIxNQQAAAABMAcAAAAJMy8yNy8yMDI1CAAAAAoxMi8zMS8yMDIzCQAAAAEw/A8DhlVt3QjemLQZW23dCCFDSVEuSVE1NzA0Njg4LklRX05JLkZZMjAyMi4uLi5VU0QBAAAA8AtXAAIAAAAFNjUuMTUBCAAAAAUAAAABMQEAAAALLTIwMDUyNDY3ODMDAAAAAzE2MAIAAAACMTUEAAAAATAHAAAACTMvMjcvMjAyNQgAAAAKMTIvMzEvMjAyMgkAAAABMPwPA4ZVbd0IW0KEWFtt3QgnQ0lRLklRODc3NDE0LklRX1RPVEFMX1JFVi5GWTIwMjQuLi4uVVNEAQAAAGZjDQACAAAACzIwMTAuNTQ3MjQ1AQgAAAAFAAAAATEBAAAACy0xOTU5ODIyMTAzAwAAAAMxNjACAAAAAjI4BAAAAAEwBwAAAAkzLzI3LzIwMjUIAAAACjEyLzMxLzIwMjQJAAAAATD8DwOGVW3dCMIX5FRXbd0IJ0NJUS5JUTg3NzQxNC5JUV9UT1RBTF9SRVYuRlky | V1: MDIzLi4uLlVTRAEAAABmYw0AAgAAAAsxODY5LjM1NjQwMwEIAAAABQAAAAExAQAAAAstMjAwMjI5NDQ4MAMAAAADMTYwAgAAAAIyOAQAAAABMAcAAAAJMy8yNy8yMDI1CAAAAAoxMi8zMS8yMDIzCQAAAAEw/A8DhlVt3QjCF+RUV23dCCdDSVEuSVE4Nzc0MTQuSVFfVE9UQUxfUkVWLkZZMjAyMi4uLi5VU0QBAAAAZmMNAAIAAAALMTcyNi40OTIwODIBCAAAAAUAAAABMQEAAAALLTIwMDIyOTQ0NzcDAAAAAzE2MAIAAAACMjgEAAAAATAHAAAACTMvMjcvMjAyNQgAAAAKMTIvMzEvMjAyMgkAAAABMPwPA4ZVbd0IPLThVFdt3QgkQ0lRLklRODc3NDE0LklRX0VCSVREQS5GWTIwMjQuLi4uVVNEAQAAAGZjDQACAAAACjI3Mi40MDEzNjgBCAAAAAUAAAABMQEAAAALLTE5NTk4MjIxMDMDAAAAAzE2MAIAAAAENDA1MQQAAAABMAcAAAAJMy8yNy8yMDI1CAAAAAoxMi8zMS8yMDI0CQAAAAEw/A8DhlVt3QjCF+RUV23dCCRDSVEuSVE4Nzc0MTQuSVFfRUJJVERBLkZZMjAyMy4uLi5VU0QBAAAAZmMNAAIAAAAKMjE5LjcyODU1OAEIAAAABQAAAAExAQAAAAstMjAwMjI5NDQ4MAMAAAADMTYwAgAAAAQ0MDUxBAAAAAEwBwAAAAkzLzI3LzIwMjUIAAAACjEyLzMxLzIwMjMJAAAAATD8DwOGVW3dCMIX5FRXbd0IJENJUS5JUTg3NzQxNC5JUV9FQklUREEuRlkyMDIyLi4uLlVTRAEAAABmYw0AAgAAAAoxOTUuMjE1MTQyAQgA | W1: AAAFAAAAATEBAAAACy0yMDAyMjk0NDc3AwAAAAMxNjACAAAABDQwNTEEAAAAATAHAAAACTMvMjcvMjAyNQgAAAAKMTIvMzEvMjAyMgkAAAABMPwPA4ZVbd0IPLThVFdt3QggQ0lRLklRODc3NDE0LklRX05JLkZZMjAyNC4uLi5VU0QBAAAAZmMNAAIAAAAKMTI5LjYwMDk2NQEIAAAABQAAAAExAQAAAAstMTk1OTgyMjEwMwMAAAADMTYwAgAAAAIxNQQAAAABMAcAAAAJMy8yNy8yMDI1CAAAAAoxMi8zMS8yMDI0CQAAAAEw/A8DhlVt3QjCF+RUV23dCCBDSVEuSVE4Nzc0MTQuSVFfTkkuRlkyMDIzLi4uLlVTRAEAAABmYw0AAgAAAAoxMTYuODMwNzUzAQgAAAAFAAAAATEBAAAACy0yMDAyMjk0NDgwAwAAAAMxNjACAAAAAjE1BAAAAAEwBwAAAAkzLzI3LzIwMjUIAAAACjEyLzMxLzIwMjMJAAAAATD8DwOGVW3dCMIX5FRXbd0IIENJUS5JUTg3NzQxNC5JUV9OSS5GWTIwMjIuLi4uVVNEAQAAAGZjDQACAAAACjEwOS45Njc5NzEBCAAAAAUAAAABMQEAAAALLTIwMDIyOTQ0NzcDAAAAAzE2MAIAAAACMTUEAAAAATAHAAAACTMvMjcvMjAyNQgAAAAKMTIvMzEvMjAyMgkAAAABMPwPA4ZVbd0IPLThVFdt3QgnQ0lRLklRODgyOTE3LklRX1RPVEFMX1JFVi5GWTIwMjQuLi4uVVNEAQAAAOV4DQACAAAACzEwNTEuODk1NDgxAQgAAAAFAAAAATEBAAAACy0xOTU2OTcyOTMzAwAAAAMxNjACAAAAAjI4BAAAAAEwBwAAAAkz | X1: LzI3LzIwMjUIAAAACjEyLzMxLzIwMjQJAAAAATD8DwOGVW3dCDy04VRXbd0IJ0NJUS5JUTg4MjkxNy5JUV9UT1RBTF9SRVYuRlkyMDIzLi4uLlVTRAEAAADleA0AAgAAAAsxMTU4LjMzNDQ1NgEIAAAABQAAAAExAQAAAAstMjAwNzU3NTgzMgMAAAADMTYwAgAAAAIyOAQAAAABMAcAAAAJMy8yNy8yMDI1CAAAAAoxMi8zMS8yMDIzCQAAAAEw/A8DhlVt3QjCF+RUV23dCCdDSVEuSVE4ODI5MTcuSVFfVE9UQUxfUkVWLkZZMjAyMi4uLi5VU0QBAAAA5XgNAAIAAAALMTE1Ni40NzM3MDYBCAAAAAUAAAABMQEAAAALLTIwMDc1NzU4MzgDAAAAAzE2MAIAAAACMjgEAAAAATAHAAAACTMvMjcvMjAyNQgAAAAKMTIvMzEvMjAyMgkAAAABMPwPA4ZVbd0IPLThVFdt3QgkQ0lRLklRODgyOTE3LklRX0VCSVREQS5GWTIwMjQuLi4uVVNEAQAAAOV4DQACAAAACTgyLjI1NTAxMQEIAAAABQAAAAExAQAAAAstMTk1Njk3MjkzMwMAAAADMTYwAgAAAAQ0MDUxBAAAAAEwBwAAAAkzLzI3LzIwMjUIAAAACjEyLzMxLzIwMjQJAAAAATD8DwOGVW3dCMIX5FRXbd0IJENJUS5JUTg4MjkxNy5JUV9FQklUREEuRlkyMDIzLi4uLlVTRAEAAADleA0AAgAAAAkxNjEuMTA3NTgBCAAAAAUAAAABMQEAAAALLTIwMDc1NzU4MzIDAAAAAzE2MAIAAAAENDA1MQQAAAABMAcAAAAJMy8yNy8yMDI1CAAAAAoxMi8zMS8yMDIzCQAAAAEw/A8DhlVt | Y1: 3QjCF+RUV23dCCRDSVEuSVE4ODI5MTcuSVFfRUJJVERBLkZZMjAyMi4uLi5VU0QBAAAA5XgNAAIAAAAJMTAzLjQ2NTkxAQgAAAAFAAAAATEBAAAACy0yMDA3NTc1ODM4AwAAAAMxNjACAAAABDQwNTEEAAAAATAHAAAACTMvMjcvMjAyNQgAAAAKMTIvMzEvMjAyMgkAAAABMPwPA4ZVbd0IPLThVFdt3QggQ0lRLklRODgyOTE3LklRX05JLkZZMjAyNC4uLi5VU0QBAAAA5XgNAAIAAAAKLTY1LjYxODgzNQEIAAAABQAAAAExAQAAAAstMTk1Njk3MjkzMwMAAAADMTYwAgAAAAIxNQQAAAABMAcAAAAJMy8yNy8yMDI1CAAAAAoxMi8zMS8yMDI0CQAAAAEw/A8DhlVt3QjCF+RUV23dCCBDSVEuSVE4ODI5MTcuSVFfTkkuRlkyMDIzLi4uLlVTRAEAAADleA0AAgAAAAkyMi43ODE0NzMBCAAAAAUAAAABMQEAAAALLTIwMDc1NzU4MzIDAAAAAzE2MAIAAAACMTUEAAAAATAHAAAACTMvMjcvMjAyNQgAAAAKMTIvMzEvMjAyMwkAAAABMPwPA4ZVbd0IPLThVFdt3QggQ0lRLklRODgyOTE3LklRX05JLkZZMjAyMi4uLi5VU0QBAAAA5XgNAAIAAAALLTExOC40NDAzMTQBCAAAAAUAAAABMQEAAAALLTIwMDc1NzU4MzgDAAAAAzE2MAIAAAACMTUEAAAAATAHAAAACTMvMjcvMjAyNQgAAAAKMTIvMzEvMjAyMgkAAAABMPwPA4ZVbd0IPLThVFdt3QgnQ0lRLklRODc0MDA4LklRX1RPVEFMX1JFVi5GWTIwMjQuLi4uVVNEAQAAABhW | Z1: DQACAAAACzE4MTcuNTMwMjIzAQgAAAAFAAAAATEBAAAACy0xOTU3NjA1MDIyAwAAAAMxNjACAAAAAjI4BAAAAAEwBwAAAAkzLzI3LzIwMjUIAAAACjEyLzMxLzIwMjQJAAAAATD8DwOGVW3dCMIX5FRXbd0IJ0NJUS5JUTg3NDAwOC5JUV9UT1RBTF9SRVYuRlkyMDIzLi4uLlVTRAEAAAAYVg0AAgAAAAsxNzE3LjA1MjM3NwEIAAAABQAAAAExAQAAAAstMjAwMTkwNTg2MgMAAAADMTYwAgAAAAIyOAQAAAABMAcAAAAJMy8yNy8yMDI1CAAAAAoxMi8zMS8yMDIzCQAAAAEw/A8DhlVt3QjCF+RUV23dCCdDSVEuSVE4NzQwMDguSVFfVE9UQUxfUkVWLkZZMjAyMi4uLi5VU0QBAAAAGFYNAAIAAAALMTU2OS42MjA5MDYBCAAAAAUAAAABMQEAAAALLTIwMDE5MDU4NzEDAAAAAzE2MAIAAAACMjgEAAAAATAHAAAACTMvMjcvMjAyNQgAAAAKMTIvMzEvMjAyMgkAAAABMPwPA4ZVbd0I37PgVFdt3QgkQ0lRLklRODc0MDA4LklRX0VCSVREQS5GWTIwMjQuLi4uVVNEAQAAABhWDQACAAAACjQyOS4zNDY5NjEBCAAAAAUAAAABMQEAAAALLTE5NTc2MDUwMjIDAAAAAzE2MAIAAAAENDA1MQQAAAABMAcAAAAJMy8yNy8yMDI1CAAAAAoxMi8zMS8yMDI0CQAAAAEw/A8DhlVt3Qg8tOFUV23dCCRDSVEuSVE4NzQwMDguSVFfRUJJVERBLkZZMjAyMy4uLi5VU0QBAAAAGFYNAAIAAAAKMzkyLjc0Mzc3MwEIAAAABQAAAAExAQAAAAst | AA1: MjAwMTkwNTg2MgMAAAADMTYwAgAAAAQ0MDUxBAAAAAEwBwAAAAkzLzI3LzIwMjUIAAAACjEyLzMxLzIwMjMJAAAAATD8DwOGVW3dCMIX5FRXbd0IJENJUS5JUTg3NDAwOC5JUV9FQklUREEuRlkyMDIyLi4uLlVTRAEAAAAYVg0AAgAAAAo0MDEuMzM0Njk4AQgAAAAFAAAAATEBAAAACy0yMDAxOTA1ODcxAwAAAAMxNjACAAAABDQwNTEEAAAAATAHAAAACTMvMjcvMjAyNQgAAAAKMTIvMzEvMjAyMgkAAAABMPwPA4ZVbd0IPLThVFdt3QggQ0lRLklRODc0MDA4LklRX05JLkZZMjAyNC4uLi5VU0QBAAAAGFYNAAIAAAAKMTE5LjM0ODI4NwEIAAAABQAAAAExAQAAAAstMTk1NzYwNTAyMgMAAAADMTYwAgAAAAIxNQQAAAABMAcAAAAJMy8yNy8yMDI1CAAAAAoxMi8zMS8yMDI0CQAAAAEw/A8DhlVt3QjCF+RUV23dCCBDSVEuSVE4NzQwMDguSVFfTkkuRlkyMDIzLi4uLlVTRAEAAAAYVg0AAgAAAAkxMzcuMjA2MTQBCAAAAAUAAAABMQEAAAALLTIwMDE5MDU4NjIDAAAAAzE2MAIAAAACMTUEAAAAATAHAAAACTMvMjcvMjAyNQgAAAAKMTIvMzEvMjAyMwkAAAABMPwPA4ZVbd0IwhfkVFdt3QggQ0lRLklRODc0MDA4LklRX05JLkZZMjAyMi4uLi5VU0QBAAAAGFYNAAIAAAAKMTQ1LjYxMjYxMgEIAAAABQAAAAExAQAAAAstMjAwMTkwNTg3MQMAAAADMTYwAgAAAAIxNQQAAAABMAcAAAAJMy8yNy8yMDI1CAAAAAoxMi8z | AB1: MS8yMDIyCQAAAAEw/A8DhlVt3Qjfs+BUV23dCCdDSVEuSVE4Nzc0NzAuSVFfVE9UQUxfUkVWLkZZMjAyNC4uLi5VU0QBAAAAnmMNAAIAAAAKNTI0LjQ2NDY4MwEIAAAABQAAAAExAQAAAAstMTk1OTY5NjE0NQMAAAADMTYwAgAAAAIyOAQAAAABMAcAAAAJMy8yNy8yMDI1CAAAAAoxMi8zMS8yMDI0CQAAAAEw/A8DhlVt3QjCF+RUV23dCCdDSVEuSVE4Nzc0NzAuSVFfVE9UQUxfUkVWLkZZMjAyMy4uLi5VU0QBAAAAnmMNAAIAAAAKNTI1LjEzMTI3OAEIAAAABQAAAAExAQAAAAstMTk1OTY5NjE0NwMAAAADMTYwAgAAAAIyOAQAAAABMAcAAAAJMy8yNy8yMDI1CAAAAAoxMi8zMS8yMDIzCQAAAAEw/A8DhlVt3QjCF+RUV23dCCdDSVEuSVE4Nzc0NzAuSVFfVE9UQUxfUkVWLkZZMjAyMi4uLi5VU0QBAAAAnmMNAAIAAAAKNTU1LjQ0NTExNwEIAAAABQAAAAExAQAAAAstMTk1OTY5NjEyNQMAAAADMTYwAgAAAAIyOAQAAAABMAcAAAAJMy8yNy8yMDI1CAAAAAoxMi8zMS8yMDIyCQAAAAEw/A8DhlVt3Qjfs+BUV23dCCRDSVEuSVE4Nzc0NzAuSVFfRUJJVERBLkZZMjAyNC4uLi5VU0QBAAAAnmMNAAIAAAAKMTQyLjE3NTIwNAEIAAAABQAAAAExAQAAAAstMTk1OTY5NjE0NQMAAAADMTYwAgAAAAQ0MDUxBAAAAAEwBwAAAAkzLzI3LzIwMjUIAAAACjEyLzMxLzIwMjQJAAAAATD8DwOGVW3dCMIX5FRXbd0IJENJUS5J | AC1: UTg3NzQ3MC5JUV9FQklUREEuRlkyMDIzLi4uLlVTRAEAAACeYw0AAgAAAAoxMzcuMjQ4MTQ5AQgAAAAFAAAAATEBAAAACy0xOTU5Njk2MTQ3AwAAAAMxNjACAAAABDQwNTEEAAAAATAHAAAACTMvMjcvMjAyNQgAAAAKMTIvMzEvMjAyMwkAAAABMPwPA4ZVbd0IwhfkVFdt3QgkQ0lRLklRODc3NDcwLklRX0VCSVREQS5GWTIwMjIuLi4uVVNEAQAAAJ5jDQACAAAACjEyOS42NTE4ODYBCAAAAAUAAAABMQEAAAALLTE5NTk2OTYxMjUDAAAAAzE2MAIAAAAENDA1MQQAAAABMAcAAAAJMy8yNy8yMDI1CAAAAAoxMi8zMS8yMDIyCQAAAAEw/A8DhlVt3Qjfs+BUV23dCCBDSVEuSVE4Nzc0NzAuSVFfTkkuRlkyMDI0Li4uLlVTRAEAAACeYw0AAgAAAAk1Mi43Mjk2MTEBCAAAAAUAAAABMQEAAAALLTE5NTk2OTYxNDUDAAAAAzE2MAIAAAACMTUEAAAAATAHAAAACTMvMjcvMjAyNQgAAAAKMTIvMzEvMjAyNAkAAAABMPwPA4ZVbd0IwhfkVFdt3QggQ0lRLklRODc3NDcwLklRX05JLkZZMjAyMy4uLi5VU0QBAAAAnmMNAAIAAAAJNDUuNDgyNjk4AQgAAAAFAAAAATEBAAAACy0xOTU5Njk2MTQ3AwAAAAMxNjACAAAAAjE1BAAAAAEwBwAAAAkzLzI3LzIwMjUIAAAACjEyLzMxLzIwMjMJAAAAATD8DwOGVW3dCMIX5FRXbd0IIENJUS5JUTg3NzQ3MC5JUV9OSS5GWTIwMjIuLi4uVVNEAQAAAJ5jDQACAAAACTQ2LjQyMjUxNAEI | AD1: AAAABQAAAAExAQAAAAstMTk1OTY5NjEyNQMAAAADMTYwAgAAAAIxNQQAAAABMAcAAAAJMy8yNy8yMDI1CAAAAAoxMi8zMS8yMDIyCQAAAAEw/A8DhlVt3Qjfs+BUV23dCCpDSVEuSVEyMTY0MDE5ODguSVFfVE9UQUxfUkVWLkZZMjAyNC4uLi5VU0QBAAAARAjmDAIAAAALNTc0OS4xMTQ5NTcBCAAAAAUAAAABMQEAAAALLTE5NTgyNzQwODcDAAAAAzE2MAIAAAACMjgEAAAAATAHAAAACTMvMjcvMjAyNQgAAAAKMTIvMzEvMjAyNAkAAAABMPwPA4ZVbd0IwhfkVFdt3QgqQ0lRLklRMjE2NDAxOTg4LklRX1RPVEFMX1JFVi5GWTIwMjMuLi4uVVNEAQAAAEQI5gwCAAAACzU2MTguMDc0MzI1AQgAAAAFAAAAATEBAAAACy0xOTk0Mzc2MjM2AwAAAAMxNjACAAAAAjI4BAAAAAEwBwAAAAkzLzI3LzIwMjUIAAAACjEyLzMxLzIwMjMJAAAAATD8DwOGVW3dCMIX5FRXbd0IKkNJUS5JUTIxNjQwMTk4OC5JUV9UT1RBTF9SRVYuRlkyMDIyLi4uLlVTRAEAAABECOYMAgAAAAs1MTkzLjM4NDI1NwEIAAAABQAAAAExAQAAAAstMTk5NDM3NjI0MwMAAAADMTYwAgAAAAIyOAQAAAABMAcAAAAJMy8yNy8yMDI1CAAAAAoxMi8zMS8yMDIyCQAAAAEw/A8DhlVt3Qjfs+BUV23dCCdDSVEuSVEyMTY0MDE5ODguSVFfRUJJVERBLkZZMjAyNC4uLi5VU0QBAAAARAjmDAIAAAAJNzQ5Ljg2Nzk2AQgAAAAFAAAAATEBAAAACy0xOTU4Mjc0 | AE1: MDg3AwAAAAMxNjACAAAABDQwNTEEAAAAATAHAAAACTMvMjcvMjAyNQgAAAAKMTIvMzEvMjAyNAkAAAABMPwPA4ZVbd0IPLThVFdt3QgnQ0lRLklRMjE2NDAxOTg4LklRX0VCSVREQS5GWTIwMjMuLi4uVVNEAQAAAEQI5gwCAAAACjcwMS42MTg0MTkBCAAAAAUAAAABMQEAAAALLTE5OTQzNzYyMzYDAAAAAzE2MAIAAAAENDA1MQQAAAABMAcAAAAJMy8yNy8yMDI1CAAAAAoxMi8zMS8yMDIzCQAAAAEw/A8DhlVt3QjCF+RUV23dCCdDSVEuSVEyMTY0MDE5ODguSVFfRUJJVERBLkZZMjAyMi4uLi5VU0QBAAAARAjmDAIAAAAKNTQzLjA3NzM2NwEIAAAABQAAAAExAQAAAAstMTk5NDM3NjI0MwMAAAADMTYwAgAAAAQ0MDUxBAAAAAEwBwAAAAkzLzI3LzIwMjUIAAAACjEyLzMxLzIwMjIJAAAAATD8DwOGVW3dCDy04VRXbd0II0NJUS5JUTIxNjQwMTk4OC5JUV9OSS5GWTIwMjQuLi4uVVNEAQAAAEQI5gwCAAAACjI1Ny41NDQyNzgBCAAAAAUAAAABMQEAAAALLTE5NTgyNzQwODcDAAAAAzE2MAIAAAACMTUEAAAAATAHAAAACTMvMjcvMjAyNQgAAAAKMTIvMzEvMjAyNAkAAAABMPwPA4ZVbd0IwhfkVFdt3QgjQ0lRLklRMjE2NDAxOTg4LklRX05JLkZZMjAyMy4uLi5VU0QBAAAARAjmDAIAAAAKMjUxLjk5MDAzNgEIAAAABQAAAAExAQAAAAstMTk5NDM3NjIzNgMAAAADMTYwAgAAAAIxNQQAAAABMAcAAAAJMy8yNy8y | AF1: MDI1CAAAAAoxMi8zMS8yMDIzCQAAAAEw/A8DhlVt3QjCF+RUV23dCCNDSVEuSVEyMTY0MDE5ODguSVFfTkkuRlkyMDIyLi4uLlVTRAEAAABECOYMAgAAAAoxOTMuMjk5OTkyAQgAAAAFAAAAATEBAAAACy0xOTk0Mzc2MjQzAwAAAAMxNjACAAAAAjE1BAAAAAEwBwAAAAkzLzI3LzIwMjUIAAAACjEyLzMxLzIwMjIJAAAAATD8DwOGVW3dCN+z4FRXbd0IJ0NJUS5JUTg3NzQ4Mi5JUV9UT1RBTF9SRVYuRlkyMDIyLi4uLlVTRAEAAACqYw0AAgAAAAs0MDQwLjk1NTA3NQEIAAAABQAAAAExAQAAAAstMTk5MzU5ODE3MwMAAAADMTYwAgAAAAIyOAQAAAABMAcAAAAJMy8yNy8yMDI1CAAAAAoxMi8zMS8yMDIyCQAAAAEw/A8DhlVt3QjCF+RUV23dCCRDSVEuSVE4Nzc0ODIuSVFfRUJJVERBLkZZMjAyMy4uLi5VU0QBAAAAqmMNAAIAAAAKMjkyLjc4MzM1OAEIAAAABQAAAAExAQAAAAstMTk5MzU5ODE3NQMAAAADMTYwAgAAAAQ0MDUxBAAAAAEwBwAAAAkzLzI3LzIwMjUIAAAACjEyLzMxLzIwMjMJAAAAATD8DwOGVW3dCMIX5FRXbd0IJENJUS5JUTg3NzQ4Mi5JUV9FQklUREEuRlkyMDIyLi4uLlVTRAEAAACqYw0AAgAAAAo0MTAuNzcxMDQ4AQgAAAAFAAAAATEBAAAACy0xOTkzNTk4MTczAwAAAAMxNjACAAAABDQwNTEEAAAAATAHAAAACTMvMjcvMjAyNQgAAAAKMTIvMzEvMjAyMgkAAAABMPwPA4ZVbd0IwhfkVFdt | AG1: 3QggQ0lRLklRODc3NDgyLklRX05JLkZZMjAyMy4uLi5VU0QBAAAAqmMNAAIAAAAJNTAuNzI1NDYxAQgAAAAFAAAAATEBAAAACy0xOTkzNTk4MTc1AwAAAAMxNjACAAAAAjE1BAAAAAEwBwAAAAkzLzI3LzIwMjUIAAAACjEyLzMxLzIwMjMJAAAAATD8DwOGVW3dCDy04VRXbd0IIENJUS5JUTg3NzQ4Mi5JUV9OSS5GWTIwMjIuLi4uVVNEAQAAAKpjDQACAAAACjEzNy42MDI4NDYBCAAAAAUAAAABMQEAAAALLTE5OTM1OTgxNzMDAAAAAzE2MAIAAAACMTUEAAAAATAHAAAACTMvMjcvMjAyNQgAAAAKMTIvMzEvMjAyMgkAAAABMPwPA4ZVbd0IwhfkVFdt3QgrQ0lRLklRMzk2ODEyLklRX0lOVF9JTkNfTE9BTlMuRlkyMDIzLi4uLlVTRAEAAAAMDgYAAgAAAAs1MDYyLjIwNDEyMQEIAAAABQAAAAExAQAAAAstMTk1NzA5OTkxNgMAAAADMTYwAgAAAAMyMTIEAAAAATAHAAAACTMvMjcvMjAyNQgAAAAKMTIvMzEvMjAyMwkAAAABMPwPA4ZVbd0IPLThVFdt3QgrQ0lRLklRMzk2ODEyLklRX0lOVF9JTkNfTE9BTlMuRlkyMDIyLi4uLlVTRAEAAAAMDgYAAgAAAAszOTQwLjg5OTk0NQEIAAAABQAAAAExAQAAAAstMTk1NzA5OTkxNwMAAAADMTYwAgAAAAMyMTIEAAAAATAHAAAACTMvMjcvMjAyNQgAAAAKMTIvMzEvMjAyMgkAAAABMPwPA4ZVbd0I37PgVFdt3QggQ0lRLklRMzk2ODEyLklRX05JLkZZMjAyMy4uLi5VU0QB | AH1: AAAADA4GAAIAAAALMTMxMC4yMzAyNDEBCAAAAAUAAAABMQEAAAALLTE5NTcwOTk5MTYDAAAAAzE2MAIAAAACMTUEAAAAATAHAAAACTMvMjcvMjAyNQgAAAAKMTIvMzEvMjAyMwkAAAABMPwPA4ZVbd0IwhfkVFdt3QggQ0lRLklRMzk2ODEyLklRX05JLkZZMjAyMi4uLi5VU0QBAAAADA4GAAIAAAALMTIyMC4xODc5NjkBCAAAAAUAAAABMQEAAAALLTE5NTcwOTk5MTcDAAAAAzE2MAIAAAACMTUEAAAAATAHAAAACTMvMjcvMjAyNQgAAAAKMTIvMzEvMjAyMgkAAAABMPwPA4ZVbd0IPLThVFdt3QgtQ0lRLklRMzUxOTYyNjcuSVFfSU5UX0lOQ19MT0FOUy5GWTIwMjQuLi4uVVNEAQAAAGsNGQICAAAACzE4NjMuNzY4OTU1AQgAAAAFAAAAATEBAAAACy0xOTU1MzEyNzg0AwAAAAMxNjACAAAAAzIxMgQAAAABMAcAAAAJMy8yNy8yMDI1CAAAAAoxMi8zMS8yMDI0CQAAAAEw/A8DhlVt3Qg8tOFUV23dCC1DSVEuSVEzNTE5NjI2Ny5JUV9JTlRfSU5DX0xPQU5TLkZZMjAyMy4uLi5VU0QBAAAAaw0ZAgIAAAALMTkxNy40MzkzNDMBCAAAAAUAAAABMQEAAAALLTE5NTUzMTI3OTMDAAAAAzE2MAIAAAADMjEyBAAAAAEwBwAAAAkzLzI3LzIwMjUIAAAACjEyLzMxLzIwMjMJAAAAATD8DwOGVW3dCMIX5FRXbd0ILUNJUS5JUTM1MTk2MjY3LklRX0lOVF9JTkNfTE9BTlMuRlkyMDIyLi4uLlVTRAEAAABrDRkCAgAAAAsxNTQx | AI1: LjM4ODI1MgEIAAAABQAAAAExAQAAAAstMTk1NTMxMjc4OAMAAAADMTYwAgAAAAMyMTIEAAAAATAHAAAACTMvMjcvMjAyNQgAAAAKMTIvMzEvMjAyMgkAAAABMPwPA4ZVbd0IPLThVFdt3QgiQ0lRLklRMzUxOTYyNjcuSVFfTkkuRlkyMDI0Li4uLlVTRAEAAABrDRkCAgAAAAozNDQuNzAxOTgzAQgAAAAFAAAAATEBAAAACy0xOTU1MzEyNzg0AwAAAAMxNjACAAAAAjE1BAAAAAEwBwAAAAkzLzI3LzIwMjUIAAAACjEyLzMxLzIwMjQJAAAAATD8DwOGVW3dCMIX5FRXbd0IIkNJUS5JUTM1MTk2MjY3LklRX05JLkZZMjAyMy4uLi5VU0QBAAAAaw0ZAgIAAAAKMjg4Ljg3MjQ5MgEIAAAABQAAAAExAQAAAAstMTk1NTMxMjc5MwMAAAADMTYwAgAAAAIxNQQAAAABMAcAAAAJMy8yNy8yMDI1CAAAAAoxMi8zMS8yMDIzCQAAAAEw/A8DhlVt3QjCF+RUV23dCCJDSVEuSVEzNTE5NjI2Ny5JUV9OSS5GWTIwMjIuLi4uVVNEAQAAAGsNGQICAAAACjQzNy45MDU1NDEBCAAAAAUAAAABMQEAAAALLTE5NTUzMTI3ODgDAAAAAzE2MAIAAAACMTUEAAAAATAHAAAACTMvMjcvMjAyNQgAAAAKMTIvMzEvMjAyMgkAAAABMPwPA4ZVbd0IPLThVFdt3QgrQ0lRLklRODczODA1LklRX0lOVF9JTkNfTE9BTlMuRlkyMDI0Li4uLlVTRAEAAABNVQ0AAgAAAAsyMTQzLjE3MTU5NQEIAAAABQAAAAExAQAAAAstMTk1NjE4MDUxNwMAAAADMTYw | AJ1: AgAAAAMyMTIEAAAAATAHAAAACTMvMjcvMjAyNQgAAAAKMTIvMzEvMjAyNAkAAAABMPwPA4ZVbd0IwhfkVFdt3QgrQ0lRLklRODczODA1LklRX0lOVF9JTkNfTE9BTlMuRlkyMDIzLi4uLlVTRAEAAABNVQ0AAgAAAAsyMDQyLjc4ODQ3NQEIAAAABQAAAAExAQAAAAstMjAwNzY1MDM3MAMAAAADMTYwAgAAAAMyMTIEAAAAATAHAAAACTMvMjcvMjAyNQgAAAAKMTIvMzEvMjAyMwkAAAABMPwPA4ZVbd0IwhfkVFdt3QgrQ0lRLklRODczODA1LklRX0lOVF9JTkNfTE9BTlMuRlkyMDIyLi4uLlVTRAEAAABNVQ0AAgAAAAsxNTA2LjY5NzkwNQEIAAAABQAAAAExAQAAAAstMjAwNzY1MDM3MQMAAAADMTYwAgAAAAMyMTIEAAAAATAHAAAACTMvMjcvMjAyNQgAAAAKMTIvMzEvMjAyMgkAAAABMPwPA4ZVbd0IPLThVFdt3QggQ0lRLklRODczODA1LklRX05JLkZZMjAyNC4uLi5VU0QBAAAATVUNAAIAAAAKNDk5LjE5NzE1NwEIAAAABQAAAAExAQAAAAstMTk1NjE4MDUxNwMAAAADMTYwAgAAAAIxNQQAAAABMAcAAAAJMy8yNy8yMDI1CAAAAAoxMi8zMS8yMDI0CQAAAAEw/A8DhlVt3QjCF+RUV23dCCBDSVEuSVE4NzM4MDUuSVFfTkkuRlkyMDIzLi4uLlVTRAEAAABNVQ0AAgAAAAo1MDQuNTc0MTIyAQgAAAAFAAAAATEBAAAACy0yMDA3NjUwMzcwAwAAAAMxNjACAAAAAjE1BAAAAAEwBwAAAAkzLzI3LzIwMjUIAAAACjEy | AK1: LzMxLzIwMjMJAAAAATD8DwOGVW3dCMIX5FRXbd0IIENJUS5JUTg3MzgwNS5JUV9OSS5GWTIwMjIuLi4uVVNEAQAAAE1VDQACAAAACjUwNC41MTc4NjQBCAAAAAUAAAABMQEAAAALLTIwMDc2NTAzNzEDAAAAAzE2MAIAAAACMTUEAAAAATAHAAAACTMvMjcvMjAyNQgAAAAKMTIvMzEvMjAyMgkAAAABMPwPA4ZVbd0IPLThVFdt3QggQ0lRLklRODc3NDgyLklRX1RPVEFMX1JFVi5GWTIwMjIBAAAAqmMNAAIAAAAJMTUzOTIuNDAyAQgAAAAFAAAAATEBAAAACy0xOTkzNTk4MTczAwAAAAMxMjICAAAAAjI4BAAAAAEwBwAAAAkzLzI3LzIwMjUIAAAACjEyLzMxLzIwMjIJAAAAATD8DwOGVW3dCN+z4FRXbd0IKENJUS5JUTQ0OTM1MjYuSVFfVE9UQUxfUkVWLkZZMjAyNC4uLi5VU0QBAAAA1pBEAAIAAAAKMTkyLjg0MTIzNAEIAAAABQAAAAExAQAAAAstMTk1NjgyMjkzOQMAAAADMTYwAgAAAAIyOAQAAAABMAcAAAAJMy8yNy8yMDI1CAAAAAoxMi8zMS8yMDI0CQAAAAEw/A8DhlVt3QjCF+RUV23dCChDSVEuSVE0NDkzNTI2LklRX1RPVEFMX1JFVi5GWTIwMjMuLi4uVVNEAQAAANaQRAACAAAACjE5MC4wMTUzNDkBCAAAAAUAAAABMQEAAAALLTE5OTM4NjY5MzQDAAAAAzE2MAIAAAACMjgEAAAAATAHAAAACTMvMjcvMjAyNQgAAAAKMTIvMzEvMjAyMwkAAAABMPwPA4ZVbd0IPLThVFdt3QgoQ0lRLklRNDQ5MzUyNi5J | AL1: UV9UT1RBTF9SRVYuRlkyMDIyLi4uLlVTRAEAAADWkEQAAgAAAAoyMDkuMzc5MTE4AQgAAAAFAAAAATEBAAAACy0xOTkzODY2ODk1AwAAAAMxNjACAAAAAjI4BAAAAAEwBwAAAAkzLzI3LzIwMjUIAAAACjEyLzMxLzIwMjIJAAAAATD8DwOGVW3dCDy04VRXbd0IJUNJUS5JUTQ0OTM1MjYuSVFfRUJJVERBLkZZMjAyNC4uLi5VU0QBAAAA1pBEAAIAAAAJMTguNzUwOTI4AQgAAAAFAAAAATEBAAAACy0xOTU2ODIyOTM5AwAAAAMxNjACAAAABDQwNTEEAAAAATAHAAAACTMvMjcvMjAyNQgAAAAKMTIvMzEvMjAyNAkAAAABMPwPA4ZVbd0IwhfkVFdt3QglQ0lRLklRNDQ5MzUyNi5JUV9FQklUREEuRlkyMDIzLi4uLlVTRAEAAADWkEQAAgAAAAg2LjU1OTg0OQEIAAAABQAAAAExAQAAAAstMTk5Mzg2NjkzNAMAAAADMTYwAgAAAAQ0MDUxBAAAAAEwBwAAAAkzLzI3LzIwMjUIAAAACjEyLzMxLzIwMjMJAAAAATD8DwOGVW3dCDy04VRXbd0IJUNJUS5JUTQ0OTM1MjYuSVFfRUJJVERBLkZZMjAyMi4uLi5VU0QBAAAA1pBEAAIAAAAJMjkuNTcwNzY1AQgAAAAFAAAAATEBAAAACy0xOTkzODY2ODk1AwAAAAMxNjACAAAABDQwNTEEAAAAATAHAAAACTMvMjcvMjAyNQgAAAAKMTIvMzEvMjAyMgkAAAABMPwPA4ZVbd0IPLThVFdt3QghQ0lRLklRNDQ5MzUyNi5JUV9OSS5GWTIwMjQuLi4uVVNEAQAAANaQRAACAAAACS0zLjIz | AM1: MzExMQEIAAAABQAAAAExAQAAAAstMTk1NjgyMjkzOQMAAAADMTYwAgAAAAIxNQQAAAABMAcAAAAJMy8yNy8yMDI1CAAAAAoxMi8zMS8yMDI0CQAAAAEw/A8DhlVt3QjCF+RUV23dCCFDSVEuSVE0NDkzNTI2LklRX05JLkZZMjAyMy4uLi5VU0QBAAAA1pBEAAIAAAAKLTE5LjM0Njk3NwEIAAAABQAAAAExAQAAAAstMTk5Mzg2NjkzNAMAAAADMTYwAgAAAAIxNQQAAAABMAcAAAAJMy8yNy8yMDI1CAAAAAoxMi8zMS8yMDIzCQAAAAEw/A8DhlVt3QjCF+RUV23dCCFDSVEuSVE0NDkzNTI2LklRX05JLkZZMjAyMi4uLi5VU0QBAAAA1pBEAAIAAAAINC40MDg5MTUBCAAAAAUAAAABMQEAAAALLTE5OTM4NjY4OTUDAAAAAzE2MAIAAAACMTUEAAAAATAHAAAACTMvMjcvMjAyNQgAAAAKMTIvMzEvMjAyMgkAAAABMPwPA4ZVbd0IPLThVFdt3Qg=

Sheet Consolidado (usd)
Q2: IQ_INT_INC_LOANS | R2: IQ_TOTAL_REV
G3: Remuneracion Directorio (USD 000) | J3: # Directores | M3: Prom. Por Director | Q3: % Ingresos | T3: % EBITDA | W3: % Utilidad Neta
B4: IQ | E4: Empresa | F4: Moneda | G4: 2024 | H4: 2023 | I4: 2022 | J4: 2024 | K4: 2023 | L4: 2022 | M4: 2024 | N4: 2023 | O4: 2022 | Q4: 2024 | R4: 2023 | S4: 2022 | T4: 2024 | U4: 2023 | V4: 2022 | W4: 2024 | X4: 2023 | Y4: 2022 | AB4: 2024
E5: Mineras | AB5: 2023
B6: IQ392824 | E6: Buenaventura | F6: USD | G6: 3383 | H6: 999 | I6: 2873 | J6: 9 | K6: 7 | L6: 7 | M6: =IFERROR(G6/J6,"-") -> 375.88889 | N6: =IFERROR(H6/K6,"-") -> 142.71429 | O6: =I6/L6 -> 410.42857 | Q6: {=G6/(_xll.ciqfunctions.udf.CIQ($B6,$R$2,"FY"&Q$4, , , , "USD")*1000)} -> 0.0029300064 | R6: {=H6/(_xll.ciqfunctions.udf.CIQ($B6,$R$2,"FY"&R$4, , , , "USD")*1000)} -> 0.0012126067 | S6: {=I6/(_xll.ciqfunctions.udf.CIQ($B6,$R$2,"FY"&S$4, , , , "USD")*1000)} -> 0.0034832602 | T6: {=G6/(_xll.ciqfunctions.udf.CIQ($B6,"IQ_EBITDA","FY"&Q$4, , , , "USD")*1000)} -> 0.0086220079 | U6: {=H6/(_xll.ciqfunctions.udf.CIQ($B6,"IQ_EBITDA","FY"&R$4, , , , "USD")*1000)} -> 0.0061043421 | V6: {=I6/(_xll.ciqfunctions.udf.CIQ($B6,"IQ_EBITDA","FY"&S$4, , , , "USD")*1000)} -> 0.022570863 | W6: {=G6/(_xll.ciqfunctions.udf.CIQ($B6,"IQ_ni","FY"&Q$4, , , , "USD")*1000)} -> 0.0084010241 | X6: {=H6/(_xll.ciqfunctions.udf.CIQ($B6,"IQ_ni","FY"&R$4, , , , "USD")*1000)} -> 0.050314782 | Y6: {=I6/(_xll.ciqfunctions.udf.CIQ($B6,"IQ_ni","FY"&S$4, , , , "USD")*1000)} -> 0.004768069 | AB6: 2022
B7: IQ6476057 | E7: Cerro Verde | F7: - | G7: - | H7: - | I7: - | J7: 5 | K7: 5 | L7: 5 | M7: =IFERROR(G7/J7,"-") -> - | N7: =IFERROR(H7/K7,"-") -> - | O7: - | Q7: - | R7: - | S7: - | T7: - | U7: - | V7: - | W7: - | X7: - | Y7: -
B8: IQ880120 | E8: Minsur | F8: USD | G8: 540 | H8: 538 | I8: 530 | J8: 8 | K8: 8 | L8: 8 | M8: =IFERROR(G8/J8,"-") -> 67.5 | N8: =IFERROR(H8/K8,"-") -> 67.25 | O8: =I8/L8 -> 66.25 | Q8: {=G8/(_xll.ciqfunctions.udf.CIQ($B8,$R$2,"FY"&Q$4, , , , "USD")*1000)} -> 0.00024880172 | R8: {=H8/(_xll.ciqfunctions.udf.CIQ($B8,$R$2,"FY"&R$4, , , , "USD")*1000)} -> 0.00026756186 | S8: {=I8/(_xll.ciqfunctions.udf.CIQ($B8,$R$2,"FY"&S$4, , , , "USD")*1000)} -> 0.00023296918 | T8: {=G8/(_xll.ciqfunctions.udf.CIQ($B8,"IQ_EBITDA","FY"&Q$4, , , , "USD")*1000)} -> 0.00038019682 | U8: {=H8/(_xll.ciqfunctions.udf.CIQ($B8,"IQ_EBITDA","FY"&R$4, , , , "USD")*1000)} -> 0.00044403324 | V8: {=I8/(_xll.ciqfunctions.udf.CIQ($B8,"IQ_EBITDA","FY"&S$4, , , , "USD")*1000)} -> 0.00040577953 | W8: {=G8/(_xll.ciqfunctions.udf.CIQ($B8,"IQ_ni","FY"&Q$4, , , , "USD")*1000)} -> 0.0011649329 | X8: {=H8/(_xll.ciqfunctions.udf.CIQ($B8,"IQ_ni","FY"&R$4, , , , "USD")*1000)} -> 0.0013609813 | Y8: {=I8/(_xll.ciqfunctions.udf.CIQ($B8,"IQ_ni","FY"&S$4, , , , "USD")*1000)} -> 0.0010680337
B9: IQ877515 | E9: Volcan | F9: USD | G9: 14433 | H9: 10571 | I9: 7573 | J9: 7 | K9: 7 | L9: 7 | M9: =IFERROR(G9/J9,"-") -> 2061.8571 | N9: =IFERROR(H9/K9,"-") -> 1510.1429 | O9: =I9/L9 -> 1081.8571 | Q9: {=G9/(_xll.ciqfunctions.udf.CIQ($B9,$R$2,"FY"&Q$4, , , , "USD")*1000)} -> 0.01502622 | R9: {=H9/(_xll.ciqfunctions.udf.CIQ($B9,$R$2,"FY"&R$4, , , , "USD")*1000)} -> 0.011970522 | S9: {=I9/(_xll.ciqfunctions.udf.CIQ($B9,$R$2,"FY"&S$4, , , , "USD")*1000)} -> 0.0079609699 | T9: {=G9/(_xll.ciqfunctions.udf.CIQ($B9,"IQ_EBITDA","FY"&Q$4, , , , "USD")*1000)} -> 0.031959062 | U9: {=H9/(_xll.ciqfunctions.udf.CIQ($B9,"IQ_EBITDA","FY"&R$4, , , , "USD")*1000)} -> 0.04104143 | V9: {=I9/(_xll.ciqfunctions.udf.CIQ($B9,"IQ_EBITDA","FY"&S$4, , , , "USD")*1000)} -> 0.026543617 | W9: {=G9/(_xll.ciqfunctions.udf.CIQ($B9,"IQ_ni","FY"&Q$4, , , , "USD")*1000)} -> 0.10524819 | X9: {=H9/(_xll.ciqfunctions.udf.CIQ($B9,"IQ_ni","FY"&R$4, , , , "USD")*1000)} -> -1.0589001 | Y9: {=I9/(_xll.ciqfunctions.udf.CIQ($B9,"IQ_ni","FY"&S$4, , , , "USD")*1000)} -> -0.093054975
B10: IQ877687 | E10: Nexa Perú | F10: - | G10: 11342 | H10: 13951 | I10: 5496 | J10: 5 | K10: 5 | L10: 5 | M10: =IFERROR(G10/J10,"-") -> 2268.4 | N10: =IFERROR(H10/K10,"-") -> 2790.2 | O10: =I10/L10 -> 1099.2 | Q10: {=G10/(_xll.ciqfunctions.udf.CIQ($B10,$R$2,"FY"&Q$4, , , , "USD")*1000)} -> 0.012872224 | R10: {=H10/(_xll.ciqfunctions.udf.CIQ($B10,$R$2,"FY"&R$4, , , , "USD")*1000)} -> 0.018972254 | S10: {=I10/(_xll.ciqfunctions.udf.CIQ($B10,$R$2,"FY"&S$4, , , , "USD")*1000)} -> 0.0061587492 | T10: {=G10/(_xll.ciqfunctions.udf.CIQ($B10,"IQ_EBITDA","FY"&Q$4, , , , "USD")*1000)} -> 0.038106565 | U10: {=H10/(_xll.ciqfunctions.udf.CIQ($B10,"IQ_EBITDA","FY"&R$4, , , , "USD")*1000)} -> 0.075530026 | V10: {=I10/(_xll.ciqfunctions.udf.CIQ($B10,"IQ_EBITDA","FY"&S$4, , , , "USD")*1000)} -> 0.017338962 | W10: {=G10/(_xll.ciqfunctions.udf.CIQ($B10,"IQ_ni","FY"&Q$4, , , , "USD")*1000)} -> 2.6959829 | X10: {=H10/(_xll.ciqfunctions.udf.CIQ($B10,"IQ_ni","FY"&R$4, , , , "USD")*1000)} -> 0.2972662 | Y10: {=I10/(_xll.ciqfunctions.udf.CIQ($B10,"IQ_ni","FY"&S$4, , , , "USD")*1000)} -> 0.057947177
B11: IQ284839929 | E11: Nexa US | F11: USD | G11: 7829 | H11: 7353 | I11: 7529 | J11: 9 | K11: 9 | L11: 9 | M11: =IFERROR(G11/J11,"-") -> 869.88889 | N11: =IFERROR(H11/K11,"-") -> 817 | O11: =I11/L11 -> 836.55556 | Q11: {=G11/(_xll.ciqfunctions.udf.CIQ($B11,$R$2,"FY"&Q$4, , , , "USD")*1000)} -> 0.0028299489 | R11: {=H11/(_xll.ciqfunctions.udf.CIQ($B11,$R$2,"FY"&R$4, , , , "USD")*1000)} -> 0.0028574948 | S11: {=I11/(_xll.ciqfunctions.udf.CIQ($B11,$R$2,"FY"&S$4, , , , "USD")*1000)} -> 0.0024815507 | T11: {=G11/(_xll.ciqfunctions.udf.CIQ($B11,"IQ_EBITDA","FY"&Q$4, , , , "USD")*1000)} -> 0.01286581 | U11: {=H11/(_xll.ciqfunctions.udf.CIQ($B11,"IQ_EBITDA","FY"&R$4, , , , "USD")*1000)} -> 0.02533927 | V11: {=I11/(_xll.ciqfunctions.udf.CIQ($B11,"IQ_EBITDA","FY"&S$4, , , , "USD")*1000)} -> 0.010850095 | W11: {=G11/(_xll.ciqfunctions.udf.CIQ($B11,"IQ_ni","FY"&Q$4, , , , "USD")*1000)} -> -0.038184656 | X11: {=H11/(_xll.ciqfunctions.udf.CIQ($B11,"IQ_ni","FY"&R$4, , , , "USD")*1000)} -> -0.025184267 | Y11: {=I11/(_xll.ciqfunctions.udf.CIQ($B11,"IQ_ni","FY"&S$4, , , , "USD")*1000)} -> 0.15150418
B12: IQ29666569 | E12: Hochschild | F12: USD | G12: 8284 | H12: 7416 | I12: 8295 | J12: 9 | K12: 9 | L12: 9 | M12: =IFERROR(G12/J12,"-") -> 920.44444 | N12: =IFERROR(H12/K12,"-") -> 824 | O12: =I12/L12 -> 921.66667 | Q12: {=G12/(_xll.ciqfunctions.udf.CIQ($B12,$R$2,"FY"&Q$4, , , , "USD")*1000)} -> 0.0087411997 | R12: {=H12/(_xll.ciqfunctions.udf.CIQ($B12,$R$2,"FY"&R$4, , , , "USD")*1000)} -> 0.010690254 | S12: {=I12/(_xll.ciqfunctions.udf.CIQ($B12,$R$2,"FY"&S$4, , , , "USD")*1000)} -> 0.01127585 | T12: {=G12/(_xll.ciqfunctions.udf.CIQ($B12,"IQ_EBITDA","FY"&Q$4, , , , "USD")*1000)} -> 0.020628209 | U12: {=H12/(_xll.ciqfunctions.udf.CIQ($B12,"IQ_EBITDA","FY"&R$4, , , , "USD")*1000)} -> 0.032382158 | V12: {=I12/(_xll.ciqfunctions.udf.CIQ($B12,"IQ_EBITDA","FY"&S$4, , , , "USD")*1000)} -> 0.043011589 | W12: {=G12/(_xll.ciqfunctions.udf.CIQ($B12,"IQ_ni","FY"&Q$4, , , , "USD")*1000)} -> 0.08539766 | X12: {=H12/(_xll.ciqfunctions.udf.CIQ($B12,"IQ_ni","FY"&R$4, , , , "USD")*1000)} -> -0.13482166 | Y12: {=I12/(_xll.ciqfunctions.udf.CIQ($B12,"IQ_ni","FY"&S$4, , , , "USD")*1000)} -> 2.8014184
E13: Utilities
B14: IQ883110 | E14: Orygen | F14: PEN | G14: =9339/H36 -> 2476.1374 | H14: =9008/I36 -> 2425.7439 | I14: 1589 | J14: 7 | K14: 7 | L14: 7 | M14: =IFERROR(G14/J14,"-") -> 353.73392 | N14: =IFERROR(H14/K14,"-") -> 346.53484 | O14: =I14/L14 -> 227 | Q14: {=G14/(_xll.ciqfunctions.udf.CIQ($B14,$R$2,"FY"&Q$4, , , , "USD")*1000)} -> 0.0033373202 | R14: {=H14/(_xll.ciqfunctions.udf.CIQ($B14,$R$2,"FY"&R$4, , , , "USD")*1000)} -> 0.0034348105 | S14: {=I14/(_xll.ciqfunctions.udf.CIQ($B14,$R$2,"FY"&S$4, , , , "USD")*1000)} -> 0.002548409 | T14: {=G14/(_xll.ciqfunctions.udf.CIQ($B14,"IQ_EBITDA","FY"&Q$4, , , , "USD")*1000)} -> 0.0057819179 | U14: {=H14/(_xll.ciqfunctions.udf.CIQ($B14,"IQ_EBITDA","FY"&R$4, , , , "USD")*1000)} -> 0.0068688116 | V14: {=I14/(_xll.ciqfunctions.udf.CIQ($B14,"IQ_EBITDA","FY"&S$4, , , , "USD")*1000)} -> 0.0048174626 | W14: {=G14/(_xll.ciqfunctions.udf.CIQ($B14,"IQ_ni","FY"&Q$4, , , , "USD")*1000)} -> 0.010053016 | X14: {=H14/(_xll.ciqfunctions.udf.CIQ($B14,"IQ_ni","FY"&R$4, , , , "USD")*1000)} -> 0.011296261 | Y14: {=I14/(_xll.ciqfunctions.udf.CIQ($B14,"IQ_ni","FY"&S$4, , , , "USD")*1000)} -> 0.0076730072
B15: IQ5885965 | E15: Pluzen | F15: PEN | G15: =9514/H36 -> 2522.5369 | H15: 130 | I15: 2311 | J15: 7 | K15: 7 | L15: 7 | M15: =IFERROR(G15/J15,"-") -> 360.36241 | N15: =IFERROR(H15/K15,"-") -> 18.571429 | O15: =I15/L15 -> 330.14286 | Q15: {=G15/(_xll.ciqfunctions.udf.CIQ($B15,$R$2,"FY"&Q$4, , , , "USD")*1000)} -> 0.0023208286 | R15: {=H15/(_xll.ciqfunctions.udf.CIQ($B15,$R$2,"FY"&R$4, , , , "USD")*1000)} -> 0.00011680066 | S15: {=I15/(_xll.ciqfunctions.udf.CIQ($B15,$R$2,"FY"&S$4, , , , "USD")*1000)} -> 0.0022449499 | T15: {=G15/(_xll.ciqfunctions.udf.CIQ($B15,"IQ_EBITDA","FY"&Q$4, , , , "USD")*1000)} -> 0.0095078864 | U15: {=H15/(_xll.ciqfunctions.udf.CIQ($B15,"IQ_EBITDA","FY"&R$4, , , , "USD")*1000)} -> 0.00050330598 | V15: {=I15/(_xll.ciqfunctions.udf.CIQ($B15,"IQ_EBITDA","FY"&S$4, , , , "USD")*1000)} -> 0.0090679216 | W15: {=G15/(_xll.ciqfunctions.udf.CIQ($B15,"IQ_ni","FY"&Q$4, , , , "USD")*1000)} -> 0.024799097 | X15: {=H15/(_xll.ciqfunctions.udf.CIQ($B15,"IQ_ni","FY"&R$4, , , , "USD")*1000)} -> 0.0011138709 | Y15: {=I15/(_xll.ciqfunctions.udf.CIQ($B15,"IQ_ni","FY"&S$4, , , , "USD")*1000)} -> 0.018375866
B16: IQ5704688 | E16: Engie | F16: USD | G16: 1974 | H16: 869 | I16: 45 | J16: 7 | K16: 7 | L16: 7 | M16: =IFERROR(G16/J16,"-") -> 282 | N16: =IFERROR(H16/K16,"-") -> 124.14286 | O16: =I16/L16 -> 6.4285714 | Q16: {=G16/(_xll.ciqfunctions.udf.CIQ($B16,$R$2,"FY"&Q$4, , , , "USD")*1000)} -> 0.0027257024 | R16: {=H16/(_xll.ciqfunctions.udf.CIQ($B16,$R$2,"FY"&R$4, , , , "USD")*1000)} -> 0.001293534 | S16: {=I16/(_xll.ciqfunctions.udf.CIQ($B16,$R$2,"FY"&S$4, , , , "USD")*1000)} -> 8.109467e-05 | T16: {=G16/(_xll.ciqfunctions.udf.CIQ($B16,"IQ_EBITDA","FY"&Q$4, , , , "USD")*1000)} -> 0.0075640009 | U16: {=H16/(_xll.ciqfunctions.udf.CIQ($B16,"IQ_EBITDA","FY"&R$4, , , , "USD")*1000)} -> 0.0053140747 | V16: {=I16/(_xll.ciqfunctions.udf.CIQ($B16,"IQ_EBITDA","FY"&S$4, , , , "USD")*1000)} -> 0.0002386483 | W16: {=G16/(_xll.ciqfunctions.udf.CIQ($B16,"IQ_ni","FY"&Q$4, , , , "USD")*1000)} -> 0.020024143 | X16: {=H16/(_xll.ciqfunctions.udf.CIQ($B16,"IQ_ni","FY"&R$4, , , , "USD")*1000)} -> 0.14483333 | Y16: {=I16/(_xll.ciqfunctions.udf.CIQ($B16,"IQ_ni","FY"&S$4, , , , "USD")*1000)} -> 0.00069071374
E17: Construcción
B18: IQ877414 | E18: Ferreycorp | F18: PEN | G18: =44340/H36 -> 11756.284 | H18: =42031/I36 -> 11318.433 | I18: 15183 | J18: 9 | K18: 9 | L18: 9 | M18: =IFERROR(G18/J18,"-") -> 1306.2538 | N18: =IFERROR(H18/K18,"-") -> 1257.6036 | O18: =I18/L18 -> 1687 | Q18: {=G18/(_xll.ciqfunctions.udf.CIQ($B18,$R$2,"FY"&Q$4, , , , "USD")*1000)} -> 0.0058478946 | R18: {=H18/(_xll.ciqfunctions.udf.CIQ($B18,$R$2,"FY"&R$4, , , , "USD")*1000)} -> 0.0060547217 | S18: {=I18/(_xll.ciqfunctions.udf.CIQ($B18,$R$2,"FY"&S$4, , , , "USD")*1000)} -> 0.0087941324 | T18: {=G18/(_xll.ciqfunctions.udf.CIQ($B18,"IQ_EBITDA","FY"&Q$4, , , , "USD")*1000)} -> 0.044382029 | U18: {=H18/(_xll.ciqfunctions.udf.CIQ($B18,"IQ_EBITDA","FY"&R$4, , , , "USD")*1000)} -> 0.051510977 | V18: {=I18/(_xll.ciqfunctions.udf.CIQ($B18,"IQ_EBITDA","FY"&S$4, , , , "USD")*1000)} -> 0.07777573 | W18: {=G18/(_xll.ciqfunctions.udf.CIQ($B18,"IQ_ni","FY"&Q$4, , , , "USD")*1000)} -> 0.090711388 | X18: {=H18/(_xll.ciqfunctions.udf.CIQ($B18,"IQ_ni","FY"&R$4, , , , "USD")*1000)} -> 0.096878885 | Y18: {=I18/(_xll.ciqfunctions.udf.CIQ($B18,"IQ_ni","FY"&S$4, , , , "USD")*1000)} -> 0.13806748
B19: IQ882917 | E19: Aenza | F19: PEN | G19: =32000/H36 -> 8484.4628 | H19: =36500/I36 -> 9829.0023 | I19: 438 | J19: 9 | K19: 9 | L19: 9 | M19: =IFERROR(G19/J19,"-") -> 942.71809 | N19: =IFERROR(H19/K19,"-") -> 1092.1114 | O19: =I19/L19 -> 48.666667 | Q19: {=G19/(_xll.ciqfunctions.udf.CIQ($B19,$R$2,"FY"&Q$4, , , , "USD")*1000)} -> 0.01824931 | R19: {=H19/(_xll.ciqfunctions.udf.CIQ($B19,$R$2,"FY"&R$4, , , , "USD")*1000)} -> 0.0084854614 | S19: {=I19/(_xll.ciqfunctions.udf.CIQ($B19,$R$2,"FY"&S$4, , , , "USD")*1000)} -> 0.00037873753 | T19: {=G19/(_xll.ciqfunctions.udf.CIQ($B19,"IQ_EBITDA","FY"&Q$4, , , , "USD")*1000)} -> 0.069362558 | U19: {=H19/(_xll.ciqfunctions.udf.CIQ($B19,"IQ_EBITDA","FY"&R$4, , , , "USD")*1000)} -> 0.061072634 | V19: {=I19/(_xll.ciqfunctions.udf.CIQ($B19,"IQ_EBITDA","FY"&S$4, , , , "USD")*1000)} -> 0.0042332784 | W19: {=G19/(_xll.ciqfunctions.udf.CIQ($B19,"IQ_ni","FY"&Q$4, , , , "USD")*1000)} -> -0.12929919 | X19: {=H19/(_xll.ciqfunctions.udf.CIQ($B19,"IQ_ni","FY"&R$4, , , , "USD")*1000)} -> 0.43144724 | Y19: {=I19/(_xll.ciqfunctions.udf.CIQ($B19,"IQ_ni","FY"&S$4, , , , "USD")*1000)} -> -0.0036980653
B20: IQ874008 | E20: UNACEM | F20: PEN | G20: =6724/H36 -> 1782.7978 | H20: =6323/I36 -> 1702.7063 | I20: 2122 | J20: 11 | K20: 11 | L20: 11 | M20: =IFERROR(G20/J20,"-") -> 162.07252 | N20: =IFERROR(H20/K20,"-") -> 154.79149 | O20: =I20/L20 -> 192.90909 | Q20: {=G20/(_xll.ciqfunctions.udf.CIQ($B20,$R$2,"FY"&Q$4, , , , "USD")*1000)} -> 0.00098089029 | R20: {=H20/(_xll.ciqfunctions.udf.CIQ($B20,$R$2,"FY"&R$4, , , , "USD")*1000)} -> 0.00099164496 | S20: {=I20/(_xll.ciqfunctions.udf.CIQ($B20,$R$2,"FY"&S$4, , , , "USD")*1000)} -> 0.0013519188 | T20: {=G20/(_xll.ciqfunctions.udf.CIQ($B20,"IQ_EBITDA","FY"&Q$4, , , , "USD")*1000)} -> 0.0042135553 | U20: {=H20/(_xll.ciqfunctions.udf.CIQ($B20,"IQ_EBITDA","FY"&R$4, , , , "USD")*1000)} -> 0.0043552321 | V20: {=I20/(_xll.ciqfunctions.udf.CIQ($B20,"IQ_EBITDA","FY"&S$4, , , , "USD")*1000)} -> 0.0052873574 | W20: {=G20/(_xll.ciqfunctions.udf.CIQ($B20,"IQ_ni","FY"&Q$4, , , , "USD")*1000)} -> 0.014937774 | X20: {=H20/(_xll.ciqfunctions.udf.CIQ($B20,"IQ_ni","FY"&R$4, , , , "USD")*1000)} -> 0.012409841 | Y20: {=I20/(_xll.ciqfunctions.udf.CIQ($B20,"IQ_ni","FY"&S$4, , , , "USD")*1000)} -> 0.014572914
B21: IQ877470 | E21: Pacasmayo | F21: PEN | G21: =6032/H36 -> 1599.3212 | H21: =5941/I36 -> 1599.8384 | I21: 1361 | J21: 7 | K21: 7 | L21: 7 | M21: =IFERROR(G21/J21,"-") -> 228.47446 | N21: =IFERROR(H21/K21,"-") -> 228.54835 | O21: =I21/L21 -> 194.42857 | Q21: {=G21/(_xll.ciqfunctions.udf.CIQ($B21,$R$2,"FY"&Q$4, , , , "USD")*1000)} -> 0.0030494356 | R21: {=H21/(_xll.ciqfunctions.udf.CIQ($B21,$R$2,"FY"&R$4, , , , "USD")*1000)} -> 0.0030465495 | S21: {=I21/(_xll.ciqfunctions.udf.CIQ($B21,$R$2,"FY"&S$4, , , , "USD")*1000)} -> 0.0024502871 | T21: {=G21/(_xll.ciqfunctions.udf.CIQ($B21,"IQ_EBITDA","FY"&Q$4, , , , "USD")*1000)} -> 0.011251569 | U21: {=H21/(_xll.ciqfunctions.udf.CIQ($B21,"IQ_EBITDA","FY"&R$4, , , , "USD")*1000)} -> 0.011502932 | V21: {=I21/(_xll.ciqfunctions.udf.CIQ($B21,"IQ_EBITDA","FY"&S$4, , , , "USD")*1000)} -> 0.01049734 | W21: {=G21/(_xll.ciqfunctions.udf.CIQ($B21,"IQ_ni","FY"&Q$4, , , , "USD")*1000)} -> 0.03033061 | X21: {=H21/(_xll.ciqfunctions.udf.CIQ($B21,"IQ_ni","FY"&R$4, , , , "USD")*1000)} -> 0.035174658 | Y21: {=I21/(_xll.ciqfunctions.udf.CIQ($B21,"IQ_ni","FY"&S$4, , , , "USD")*1000)} -> 0.029317674
E22: Consumo
B23: IQ216401988 | E23: Inretail | F23: PEN | G23: =72200/H36 -> 19143.069 | H23: =65609/I36 -> 17667.699 | I23: 15182 | J23: 6 | K23: 6 | L23: 6 | M23: =IFERROR(G23/J23,"-") -> 3190.5115 | N23: =IFERROR(H23/K23,"-") -> 2944.6165 | O23: =I23/L23 -> 2530.3333 | Q23: {=G23/(_xll.ciqfunctions.udf.CIQ($B23,$R$2,"FY"&Q$4, , , , "USD")*1000)} -> 0.003329742 | R23: {=H23/(_xll.ciqfunctions.udf.CIQ($B23,$R$2,"FY"&R$4, , , , "USD")*1000)} -> 0.0031447962 | S23: {=I23/(_xll.ciqfunctions.udf.CIQ($B23,$R$2,"FY"&S$4, , , , "USD")*1000)} -> 0.0029233346 | T23: {=G23/(_xll.ciqfunctions.udf.CIQ($B23,"IQ_EBITDA","FY"&Q$4, , , , "USD")*1000)} -> 0.028913505 | U23: {=H23/(_xll.ciqfunctions.udf.CIQ($B23,"IQ_EBITDA","FY"&R$4, , , , "USD")*1000)} -> 0.028010682 | V23: {=I23/(_xll.ciqfunctions.udf.CIQ($B23,"IQ_EBITDA","FY"&S$4, , , , "USD")*1000)} -> 0.027955501 | W23: {=G23/(_xll.ciqfunctions.udf.CIQ($B23,"IQ_ni","FY"&Q$4, , , , "USD")*1000)} -> 0.074329235 | X23: {=H23/(_xll.ciqfunctions.udf.CIQ($B23,"IQ_ni","FY"&R$4, , , , "USD")*1000)} -> 0.070112688 | Y23: {=I23/(_xll.ciqfunctions.udf.CIQ($B23,"IQ_ni","FY"&S$4, , , , "USD")*1000)} -> 0.078541132
B24: IQ877482 | E24: Alicorp | F24: - | G24: - | H24: =3474/I36 -> 935.50559 | I24: =3691/H36 -> 978.62976 | J24: 9 | K24: 9 | L24: 9 | M24: =IFERROR(G24/J24,"-") -> - | N24: =IFERROR(H24/K24,"-") -> 103.94507 | O24: =I24/L24 -> 108.73664 | Q24: - | R24: {=H24/(_xll.ciqfunctions.udf.CIQ($B24,$R$2,"FY"&R$4, , , , "USD")*1000)} -> 0.0003146992 | S24: {=I24/(_xll.ciqfunctions.udf.CIQ($B24,$R$2,"FY"&S$4, , , , "USD")*1000)} -> 0.00024217784 | T24: - | U24: {=H24/(_xll.ciqfunctions.udf.CIQ($B24,"IQ_EBITDA","FY"&R$4, , , , "USD")*1000)} -> 0.0031917914 | V24: {=I24/(_xll.ciqfunctions.udf.CIQ($B24,"IQ_EBITDA","FY"&S$4, , , , "USD")*1000)} -> 0.0023824214 | W24: - | X24: {=H24/(_xll.ciqfunctions.udf.CIQ($B24,"IQ_ni","FY"&R$4, , , , "USD")*1000)} -> 0.018442525 | Y24: {=I24/(_xll.ciqfunctions.udf.CIQ($B24,"IQ_ni","FY"&S$4, , , , "USD")*1000)} -> 0.0071119876
E25: Financieras
B26: IQ396812 | E26: BAP | F26: PEN | G26: - | H26: =7387/I36 -> 1989.2285 | I26: 2060 | J26: 9 | K26: 9 | L26: 9 | M26: =IFERROR(G26/J26,"-") -> - | N26: =IFERROR(H26/K26,"-") -> 221.02539 | O26: =I26/L26 -> 228.88889 | Q26: - | R26: {=H26/(_xll.ciqfunctions.udf.CIQ($B26,$Q$2,"FY"&R$4, , , , "USD")*1000)} -> 0.00039295699 | S26: {=I26/(_xll.ciqfunctions.udf.CIQ($B26,$Q$2,"FY"&S$4, , , , "USD")*1000)} -> 0.00052272324 | T26: - | U26: - | V26: - | W26: - | X26: {=H26/(_xll.ciqfunctions.udf.CIQ($B26,"IQ_ni","FY"&R$4, , , , "USD")*1000)} -> 0.0015182282 | Y26: {=I26/(_xll.ciqfunctions.udf.CIQ($B26,"IQ_ni","FY"&S$4, , , , "USD")*1000)} -> 0.0016882645
B27: IQ35196267 | E27: IFS | F27: PEN | G27: =2160/H36 -> 572.70124 | H27: =2104/I36 -> 566.58139 | I27: 1029 | J27: 7 | K27: 7 | L27: 7 | M27: =IFERROR(G27/J27,"-") -> 81.814463 | N27: =IFERROR(H27/K27,"-") -> 80.940199 | O27: =I27/L27 -> 147 | Q27: {=G27/(_xll.ciqfunctions.udf.CIQ($B27,$Q$2,"FY"&Q$4, , , , "USD")*1000)} -> 0.00030728124 | R27: {=H27/(_xll.ciqfunctions.udf.CIQ($B27,$Q$2,"FY"&R$4, , , , "USD")*1000)} -> 0.00029548856 | S27: {=I27/(_xll.ciqfunctions.udf.CIQ($B27,$Q$2,"FY"&S$4, , , , "USD")*1000)} -> 0.00066758002 | T27: - | U27: - | V27: - | W27: {=G27/(_xll.ciqfunctions.udf.CIQ($B27,"IQ_ni","FY"&Q$4, , , , "USD")*1000)} -> 0.0016614388 | X27: {=H27/(_xll.ciqfunctions.udf.CIQ($B27,"IQ_ni","FY"&R$4, , , , "USD")*1000)} -> 0.0019613546 | Y27: {=I27/(_xll.ciqfunctions.udf.CIQ($B27,"IQ_ni","FY"&S$4, , , , "USD")*1000)} -> 0.0023498218
B28: IQ873805 | E28: BBVA | F28: PEN | G28: =16000/H36 -> 4242.2314 | H28: =15000/I36 -> 4039.316 | I28: 4460 | J28: 11 | K28: 11 | L28: 11 | M28: =IFERROR(G28/J28,"-") -> 385.6574 | N28: =IFERROR(H28/K28,"-") -> 367.21055 | O28: =I28/L28 -> 405.45455 | Q28: {=G28/(_xll.ciqfunctions.udf.CIQ($B28,$Q$2,"FY"&Q$4, , , , "USD")*1000)} -> 0.0019794175 | R28: {=H28/(_xll.ciqfunctions.udf.CIQ($B28,$Q$2,"FY"&R$4, , , , "USD")*1000)} -> 0.001977354 | S28: {=I28/(_xll.ciqfunctions.udf.CIQ($B28,$Q$2,"FY"&S$4, , , , "USD")*1000)} -> 0.0029601156 | T28: - | U28: - | V28: - | W28: {=G28/(_xll.ciqfunctions.udf.CIQ($B28,"IQ_ni","FY"&Q$4, , , , "USD")*1000)} -> 0.0084981081 | X28: {=H28/(_xll.ciqfunctions.udf.CIQ($B28,"IQ_ni","FY"&R$4, , , , "USD")*1000)} -> 0.0080053967 | Y28: {=I28/(_xll.ciqfunctions.udf.CIQ($B28,"IQ_ni","FY"&S$4, , , , "USD")*1000)} -> 0.0088401231
E29: Servicios de Comunicación
B30: IQ4493526 | E30: EL Comercio | F30: PEN | G30: =3594/H36 -> 952.91123 | H30: =4326/I36 -> 1164.9387 | I30: =4942/J36 -> 1297.4193 | J30: 10 | K30: 10 | L30: 10 | M30: =IFERROR(G30/J30,"-") -> 95.291123 | N30: =IFERROR(H30/K30,"-") -> 116.49387 | O30: =I30/L30 -> 129.74193 | Q30: {=G30/(_xll.ciqfunctions.udf.CIQ($B30,$R$2,"FY"&Q$4, , , , "USD")*1000)} -> 0.0049414289 | R30: {=H30/(_xll.ciqfunctions.udf.CIQ($B30,$R$2,"FY"&R$4, , , , "USD")*1000)} -> 0.0061307612 | S30: {=I30/(_xll.ciqfunctions.udf.CIQ($B30,$R$2,"FY"&S$4, , , , "USD")*1000)} -> 0.0061965077 | T30: {=G30/(_xll.ciqfunctions.udf.CIQ($B30,"IQ_EBITDA","FY"&Q$4, , , , "USD")*1000)} -> 0.14304476 | U30: {=H30/(_xll.ciqfunctions.udf.CIQ($B30,"IQ_EBITDA","FY"&R$4, , , , "USD")*1000)} -> 0.068876593 | V30: {=I30/(_xll.ciqfunctions.udf.CIQ($B30,"IQ_EBITDA","FY"&S$4, , , , "USD")*1000)} -> 0.043875061 | W30: {=G30/(_xll.ciqfunctions.udf.CIQ($B30,"IQ_ni","FY"&Q$4, , , , "USD")*1000)} -> -0.29473517 | X30: {=H30/(_xll.ciqfunctions.udf.CIQ($B30,"IQ_ni","FY"&R$4, , , , "USD")*1000)} -> -0.06021295 | Y30: {=I30/(_xll.ciqfunctions.udf.CIQ($B30,"IQ_ni","FY"&S$4, , , , "USD")*1000)} -> 0.29427146
F31: TC
G32: No separan Key Management de Directores
H35: 2024 | I35: 2023 | J35: 2022
G36: TC | H36: =1/H37 -> 3.7716 | I36: =1/I37 -> 3.7135 | J36: =1/J37 -> 3.8091 | N36: ="$USDPEN" -> $USDPEN
H37: {=(_xll.ciqfunctions.udf.CIQ($B24,$R$2,"FY"&Q$4, , , ,"USD"))/(_xll.ciqfunctions.udf.CIQ($B24,$R$2,"FY"&Q$4, , , ,))} -> 0.26513946 | I37: {=(_xll.ciqfunctions.udf.CIQ($B24,$R$2,"FY"&R$4, , , ,"USD"))/(_xll.ciqfunctions.udf.CIQ($B24,$R$2,"FY"&R$4, , , ,))} -> 0.26928773 | J37: {=(_xll.ciqfunctions.udf.CIQ($B24,$R$2,"FY"&S$4, , , ,"USD"))/(_xll.ciqfunctions.udf.CIQ($B24,$R$2,"FY"&S$4, , , ,))} -> 0.26252921

Sheet Consolidado (usd) Power BI
A1: Año | B1: Empresa | C1: Remuneracion Directorio (USD 000) | D1: # Directores | E1: Prom. Por Director | F1: % Ingresos | G1: % EBITDA | H1: % Utilidad Neta
A2: 2022 | B2: Buenaventura | C2: =+INDEX('Consolidado (usd)'!$G$6:$I$30,MATCH('Consolidado (usd) Power BI'!$B2,'Consolidado (usd)'!$E$6:$E$30,0),MATCH($A2,'Consolidado (usd)'!$AB$4:$AB$6,0)) -> 2873 | D2: =+INDEX('Consolidado (usd)'!$J$6:$L$30,MATCH('Consolidado (usd) Power BI'!$B2,'Consolidado (usd)'!$E$6:$E$30,0),MATCH($A2,'Consolidado (usd)'!$AB$4:$AB$6,0)) -> 7 | E2: =+INDEX('Consolidado (usd)'!$M$6:$O$30,MATCH('Consolidado (usd) Power BI'!$B2,'Consolidado (usd)'!$E$6:$E$30,0),MATCH($A2,'Consolidado (usd)'!$AB$4:$AB$6,0)) -> 410.42857 | F2: =+INDEX('Consolidado (usd)'!$Q$6:$S$30,MATCH('Consolidado (usd) Power BI'!$B2,'Consolidado (usd)'!$E$6:$E$30,0),MATCH($A2,'Consolidado (usd)'!$AB$4:$AB$6,0)) -> 0.0034832602 | G2: =+INDEX('Consolidado (usd)'!$T$6:$V$30,MATCH('Consolidado (usd) Power BI'!$B2,'Consolidado (usd)'!$E$6:$E$30,0),MATCH($A2,'Consolidado (usd)'!$AB$4:$AB$6,0)) -> 0.022570863 | H2: =+INDEX('Consolidado (usd)'!$W$6:$Y$30,MATCH('Consolidado (usd) Power BI'!$B2,'Consolidado (usd)'!$E$6:$E$30,0),MATCH($A2,'Consolidado (usd)'!$AB$4:$AB$6,0)) -> 0.004768069
A3: 2022 | B3: Cerro Verde | C3: =+INDEX('Consolidado (usd)'!$G$6:$I$30,MATCH('Consolidado (usd) Power BI'!B3,'Consolidado (usd)'!$E$6:$E$30,0),MATCH(A3,'Consolidado (usd)'!$AB$4:$AB$6,0)) -> - | D3: =+INDEX('Consolidado (usd)'!$J$6:$L$30,MATCH('Consolidado (usd) Power BI'!$B3,'Consolidado (usd)'!$E$6:$E$30,0),MATCH($A3,'Consolidado (usd)'!$AB$4:$AB$6,0)) -> 5 | E3: =+INDEX('Consolidado (usd)'!$M$6:$O$30,MATCH('Consolidado (usd) Power BI'!$B3,'Consolidado (usd)'!$E$6:$E$30,0),MATCH($A3,'Consolidado (usd)'!$AB$4:$AB$6,0)) -> - | F3: =+INDEX('Consolidado (usd)'!$Q$6:$S$30,MATCH('Consolidado (usd) Power BI'!$B3,'Consolidado (usd)'!$E$6:$E$30,0),MATCH($A3,'Consolidado (usd)'!$AB$4:$AB$6,0)) -> - | G3: =+INDEX('Consolidado (usd)'!$T$6:$V$30,MATCH('Consolidado (usd) Power BI'!$B3,'Consolidado (usd)'!$E$6:$E$30,0),MATCH($A3,'Consolidado (usd)'!$AB$4:$AB$6,0)) -> - | H3: =+INDEX('Consolidado (usd)'!$W$6:$Y$30,MATCH('Consolidado (usd) Power BI'!$B3,'Consolidado (usd)'!$E$6:$E$30,0),MATCH($A3,'Consolidado (usd)'!$AB$4:$AB$6,0)) -> -
A4: 2022 | B4: Minsur | C4: =+INDEX('Consolidado (usd)'!$G$6:$I$30,MATCH('Consolidado (usd) Power BI'!B4,'Consolidado (usd)'!$E$6:$E$30,0),MATCH(A4,'Consolidado (usd)'!$AB$4:$AB$6,0)) -> 530 | D4: =+INDEX('Consolidado (usd)'!$J$6:$L$30,MATCH('Consolidado (usd) Power BI'!$B4,'Consolidado (usd)'!$E$6:$E$30,0),MATCH($A4,'Consolidado (usd)'!$AB$4:$AB$6,0)) -> 8 | E4: =+INDEX('Consolidado (usd)'!$M$6:$O$30,MATCH('Consolidado (usd) Power BI'!$B4,'Consolidado (usd)'!$E$6:$E$30,0),MATCH($A4,'Consolidado (usd)'!$AB$4:$AB$6,0)) -> 66.25 | F4: =+INDEX('Consolidado (usd)'!$Q$6:$S$30,MATCH('Consolidado (usd) Power BI'!$B4,'Consolidado (usd)'!$E$6:$E$30,0),MATCH($A4,'Consolidado (usd)'!$AB$4:$AB$6,0)) -> 0.00023296918 | G4: =+INDEX('Consolidado (usd)'!$T$6:$V$30,MATCH('Consolidado (usd) Power BI'!$B4,'Consolidado (usd)'!$E$6:$E$30,0),MATCH($A4,'Consolidado (usd)'!$AB$4:$AB$6,0)) -> 0.00040577953 | H4: =+INDEX('Consolidado (usd)'!$W$6:$Y$30,MATCH('Consolidado (usd) Power BI'!$B4,'Consolidado (usd)'!$E$6:$E$30,0),MATCH($A4,'Consolidado (usd)'!$AB$4:$AB$6,0)) -> 0.0010680337
A5: 2022 | B5: Volcan | C5: =+INDEX('Consolidado (usd)'!$G$6:$I$30,MATCH('Consolidado (usd) Power BI'!B5,'Consolidado (usd)'!$E$6:$E$30,0),MATCH(A5,'Consolidado (usd)'!$AB$4:$AB$6,0)) -> 7573 | D5: =+INDEX('Consolidado (usd)'!$J$6:$L$30,MATCH('Consolidado (usd) Power BI'!$B5,'Consolidado (usd)'!$E$6:$E$30,0),MATCH($A5,'Consolidado (usd)'!$AB$4:$AB$6,0)) -> 7 | E5: =+INDEX('Consolidado (usd)'!$M$6:$O$30,MATCH('Consolidado (usd) Power BI'!$B5,'Consolidado (usd)'!$E$6:$E$30,0),MATCH($A5,'Consolidado (usd)'!$AB$4:$AB$6,0)) -> 1081.8571 | F5: =+INDEX('Consolidado (usd)'!$Q$6:$S$30,MATCH('Consolidado (usd) Power BI'!$B5,'Consolidado (usd)'!$E$6:$E$30,0),MATCH($A5,'Consolidado (usd)'!$AB$4:$AB$6,0)) -> 0.0079609699 | G5: =+INDEX('Consolidado (usd)'!$T$6:$V$30,MATCH('Consolidado (usd) Power BI'!$B5,'Consolidado (usd)'!$E$6:$E$30,0),MATCH($A5,'Consolidado (usd)'!$AB$4:$AB$6,0)) -> 0.026543617 | H5: =+INDEX('Consolidado (usd)'!$W$6:$Y$30,MATCH('Consolidado (usd) Power BI'!$B5,'Consolidado (usd)'!$E$6:$E$30,0),MATCH($A5,'Consolidado (usd)'!$AB$4:$AB$6,0)) -> -0.093054975
A6: 2022 | B6: Nexa Perú | C6: =+INDEX('Consolidado (usd)'!$G$6:$I$30,MATCH('Consolidado (usd) Power BI'!B6,'Consolidado (usd)'!$E$6:$E$30,0),MATCH(A6,'Consolidado (usd)'!$AB$4:$AB$6,0)) -> 5496 | D6: =+INDEX('Consolidado (usd)'!$J$6:$L$30,MATCH('Consolidado (usd) Power BI'!$B6,'Consolidado (usd)'!$E$6:$E$30,0),MATCH($A6,'Consolidado (usd)'!$AB$4:$AB$6,0)) -> 5 | E6: =+INDEX('Consolidado (usd)'!$M$6:$O$30,MATCH('Consolidado (usd) Power BI'!$B6,'Consolidado (usd)'!$E$6:$E$30,0),MATCH($A6,'Consolidado (usd)'!$AB$4:$AB$6,0)) -> 1099.2 | F6: =+INDEX('Consolidado (usd)'!$Q$6:$S$30,MATCH('Consolidado (usd) Power BI'!$B6,'Consolidado (usd)'!$E$6:$E$30,0),MATCH($A6,'Consolidado (usd)'!$AB$4:$AB$6,0)) -> 0.0061587492 | G6: =+INDEX('Consolidado (usd)'!$T$6:$V$30,MATCH('Consolidado (usd) Power BI'!$B6,'Consolidado (usd)'!$E$6:$E$30,0),MATCH($A6,'Consolidado (usd)'!$AB$4:$AB$6,0)) -> 0.017338962 | H6: =+INDEX('Consolidado (usd)'!$W$6:$Y$30,MATCH('Consolidado (usd) Power BI'!$B6,'Consolidado (usd)'!$E$6:$E$30,0),MATCH($A6,'Consolidado (usd)'!$AB$4:$AB$6,0)) -> 0.057947177
A7: 2022 | B7: Nexa Atacocha | C7: 7529 | D7: 9 | E7: 836.55556 | F7: 0.0024815507 | G7: 0.010850095 | H7: 0.15150418
A8: 2022 | B8: Hochschild | C8: =+INDEX('Consolidado (usd)'!$G$6:$I$30,MATCH('Consolidado (usd) Power BI'!B8,'Consolidado (usd)'!$E$6:$E$30,0),MATCH(A8,'Consolidado (usd)'!$AB$4:$AB$6,0)) -> 8295 | D8: =+INDEX('Consolidado (usd)'!$J$6:$L$30,MATCH('Consolidado (usd) Power BI'!$B8,'Consolidado (usd)'!$E$6:$E$30,0),MATCH($A8,'Consolidado (usd)'!$AB$4:$AB$6,0)) -> 9 | E8: =+INDEX('Consolidado (usd)'!$M$6:$O$30,MATCH('Consolidado (usd) Power BI'!$B8,'Consolidado (usd)'!$E$6:$E$30,0),MATCH($A8,'Consolidado (usd)'!$AB$4:$AB$6,0)) -> 921.66667 | F8: =+INDEX('Consolidado (usd)'!$Q$6:$S$30,MATCH('Consolidado (usd) Power BI'!$B8,'Consolidado (usd)'!$E$6:$E$30,0),MATCH($A8,'Consolidado (usd)'!$AB$4:$AB$6,0)) -> 0.01127585 | G8: =+INDEX('Consolidado (usd)'!$T$6:$V$30,MATCH('Consolidado (usd) Power BI'!$B8,'Consolidado (usd)'!$E$6:$E$30,0),MATCH($A8,'Consolidado (usd)'!$AB$4:$AB$6,0)) -> 0.043011589 | H8: =+INDEX('Consolidado (usd)'!$W$6:$Y$30,MATCH('Consolidado (usd) Power BI'!$B8,'Consolidado (usd)'!$E$6:$E$30,0),MATCH($A8,'Consolidado (usd)'!$AB$4:$AB$6,0)) -> 2.8014184
A9: 2022 | B9: Orygen | C9: =+INDEX('Consolidado (usd)'!$G$6:$I$30,MATCH('Consolidado (usd) Power BI'!B9,'Consolidado (usd)'!$E$6:$E$30,0),MATCH(A9,'Consolidado (usd)'!$AB$4:$AB$6,0)) -> 1589 | D9: =+INDEX('Consolidado (usd)'!$J$6:$L$30,MATCH('Consolidado (usd) Power BI'!$B9,'Consolidado (usd)'!$E$6:$E$30,0),MATCH($A9,'Consolidado (usd)'!$AB$4:$AB$6,0)) -> 7 | E9: =+INDEX('Consolidado (usd)'!$M$6:$O$30,MATCH('Consolidado (usd) Power BI'!$B9,'Consolidado (usd)'!$E$6:$E$30,0),MATCH($A9,'Consolidado (usd)'!$AB$4:$AB$6,0)) -> 227 | F9: =+INDEX('Consolidado (usd)'!$Q$6:$S$30,MATCH('Consolidado (usd) Power BI'!$B9,'Consolidado (usd)'!$E$6:$E$30,0),MATCH($A9,'Consolidado (usd)'!$AB$4:$AB$6,0)) -> 0.002548409 | G9: =+INDEX('Consolidado (usd)'!$T$6:$V$30,MATCH('Consolidado (usd) Power BI'!$B9,'Consolidado (usd)'!$E$6:$E$30,0),MATCH($A9,'Consolidado (usd)'!$AB$4:$AB$6,0)) -> 0.0048174626 | H9: =+INDEX('Consolidado (usd)'!$W$6:$Y$30,MATCH('Consolidado (usd) Power BI'!$B9,'Consolidado (usd)'!$E$6:$E$30,0),MATCH($A9,'Consolidado (usd)'!$AB$4:$AB$6,0)) -> 0.0076730072
A10: 2022 | B10: Pluzen | C10: =+INDEX('Consolidado (usd)'!$G$6:$I$30,MATCH('Consolidado (usd) Power BI'!B10,'Consolidado (usd)'!$E$6:$E$30,0),MATCH(A10,'Consolidado (usd)'!$AB$4:$AB$6,0)) -> 2311 | D10: =+INDEX('Consolidado (usd)'!$J$6:$L$30,MATCH('Consolidado (usd) Power BI'!$B10,'Consolidado (usd)'!$E$6:$E$30,0),MATCH($A10,'Consolidado (usd)'!$AB$4:$AB$6,0)) -> 7 | E10: =+INDEX('Consolidado (usd)'!$M$6:$O$30,MATCH('Consolidado (usd) Power BI'!$B10,'Consolidado (usd)'!$E$6:$E$30,0),MATCH($A10,'Consolidado (usd)'!$AB$4:$AB$6,0)) -> 330.14286 | F10: =+INDEX('Consolidado (usd)'!$Q$6:$S$30,MATCH('Consolidado (usd) Power BI'!$B10,'Consolidado (usd)'!$E$6:$E$30,0),MATCH($A10,'Consolidado (usd)'!$AB$4:$AB$6,0)) -> 0.0022449499 | G10: =+INDEX('Consolidado (usd)'!$T$6:$V$30,MATCH('Consolidado (usd) Power BI'!$B10,'Consolidado (usd)'!$E$6:$E$30,0),MATCH($A10,'Consolidado (usd)'!$AB$4:$AB$6,0)) -> 0.0090679216 | H10: =+INDEX('Consolidado (usd)'!$W$6:$Y$30,MATCH('Consolidado (usd) Power BI'!$B10,'Consolidado (usd)'!$E$6:$E$30,0),MATCH($A10,'Consolidado (usd)'!$AB$4:$AB$6,0)) -> 0.018375866
A11: 2022 | B11: Engie | C11: =+INDEX('Consolidado (usd)'!$G$6:$I$30,MATCH('Consolidado (usd) Power BI'!B11,'Consolidado (usd)'!$E$6:$E$30,0),MATCH(A11,'Consolidado (usd)'!$AB$4:$AB$6,0)) -> 45 | D11: =+INDEX('Consolidado (usd)'!$J$6:$L$30,MATCH('Consolidado (usd) Power BI'!$B11,'Consolidado (usd)'!$E$6:$E$30,0),MATCH($A11,'Consolidado (usd)'!$AB$4:$AB$6,0)) -> 7 | E11: =+INDEX('Consolidado (usd)'!$M$6:$O$30,MATCH('Consolidado (usd) Power BI'!$B11,'Consolidado (usd)'!$E$6:$E$30,0),MATCH($A11,'Consolidado (usd)'!$AB$4:$AB$6,0)) -> 6.4285714 | F11: =+INDEX('Consolidado (usd)'!$Q$6:$S$30,MATCH('Consolidado (usd) Power BI'!$B11,'Consolidado (usd)'!$E$6:$E$30,0),MATCH($A11,'Consolidado (usd)'!$AB$4:$AB$6,0)) -> 8.109467e-05 | G11: =+INDEX('Consolidado (usd)'!$T$6:$V$30,MATCH('Consolidado (usd) Power BI'!$B11,'Consolidado (usd)'!$E$6:$E$30,0),MATCH($A11,'Consolidado (usd)'!$AB$4:$AB$6,0)) -> 0.0002386483 | H11: =+INDEX('Consolidado (usd)'!$W$6:$Y$30,MATCH('Consolidado (usd) Power BI'!$B11,'Consolidado (usd)'!$E$6:$E$30,0),MATCH($A11,'Consolidado (usd)'!$AB$4:$AB$6,0)) -> 0.00069071374
A12: 2022 | B12: Ferreycorp | C12: =+INDEX('Consolidado (usd)'!$G$6:$I$30,MATCH('Consolidado (usd) Power BI'!B12,'Consolidado (usd)'!$E$6:$E$30,0),MATCH(A12,'Consolidado (usd)'!$AB$4:$AB$6,0)) -> 15183 | D12: =+INDEX('Consolidado (usd)'!$J$6:$L$30,MATCH('Consolidado (usd) Power BI'!$B12,'Consolidado (usd)'!$E$6:$E$30,0),MATCH($A12,'Consolidado (usd)'!$AB$4:$AB$6,0)) -> 9 | E12: =+INDEX('Consolidado (usd)'!$M$6:$O$30,MATCH('Consolidado (usd) Power BI'!$B12,'Consolidado (usd)'!$E$6:$E$30,0),MATCH($A12,'Consolidado (usd)'!$AB$4:$AB$6,0)) -> 1687 | F12: =+INDEX('Consolidado (usd)'!$Q$6:$S$30,MATCH('Consolidado (usd) Power BI'!$B12,'Consolidado (usd)'!$E$6:$E$30,0),MATCH($A12,'Consolidado (usd)'!$AB$4:$AB$6,0)) -> 0.0087941324 | G12: =+INDEX('Consolidado (usd)'!$T$6:$V$30,MATCH('Consolidado (usd) Power BI'!$B12,'Consolidado (usd)'!$E$6:$E$30,0),MATCH($A12,'Consolidado (usd)'!$AB$4:$AB$6,0)) -> 0.07777573 | H12: =+INDEX('Consolidado (usd)'!$W$6:$Y$30,MATCH('Consolidado (usd) Power BI'!$B12,'Consolidado (usd)'!$E$6:$E$30,0),MATCH($A12,'Consolidado (usd)'!$AB$4:$AB$6,0)) -> 0.13806748
A13: 2022 | B13: AENZA | C13: =+INDEX('Consolidado (usd)'!$G$6:$I$30,MATCH('Consolidado (usd) Power BI'!B13,'Consolidado (usd)'!$E$6:$E$30,0),MATCH(A13,'Consolidado (usd)'!$AB$4:$AB$6,0)) -> 438 | D13: =+INDEX('Consolidado (usd)'!$J$6:$L$30,MATCH('Consolidado (usd) Power BI'!$B13,'Consolidado (usd)'!$E$6:$E$30,0),MATCH($A13,'Consolidado (usd)'!$AB$4:$AB$6,0)) -> 9 | E13: =+INDEX('Consolidado (usd)'!$M$6:$O$30,MATCH('Consolidado (usd) Power BI'!$B13,'Consolidado (usd)'!$E$6:$E$30,0),MATCH($A13,'Consolidado (usd)'!$AB$4:$AB$6,0)) -> 48.666667 | F13: =+INDEX('Consolidado (usd)'!$Q$6:$S$30,MATCH('Consolidado (usd) Power BI'!$B13,'Consolidado (usd)'!$E$6:$E$30,0),MATCH($A13,'Consolidado (usd)'!$AB$4:$AB$6,0)) -> 0.00037873753 | G13: =+INDEX('Consolidado (usd)'!$T$6:$V$30,MATCH('Consolidado (usd) Power BI'!$B13,'Consolidado (usd)'!$E$6:$E$30,0),MATCH($A13,'Consolidado (usd)'!$AB$4:$AB$6,0)) -> 0.0042332784 | H13: =+INDEX('Consolidado (usd)'!$W$6:$Y$30,MATCH('Consolidado (usd) Power BI'!$B13,'Consolidado (usd)'!$E$6:$E$30,0),MATCH($A13,'Consolidado (usd)'!$AB$4:$AB$6,0)) -> -0.0036980653
A14: 2022 | B14: UNACEM | C14: =+INDEX('Consolidado (usd)'!$G$6:$I$30,MATCH('Consolidado (usd) Power BI'!B14,'Consolidado (usd)'!$E$6:$E$30,0),MATCH(A14,'Consolidado (usd)'!$AB$4:$AB$6,0)) -> 2122 | D14: =+INDEX('Consolidado (usd)'!$J$6:$L$30,MATCH('Consolidado (usd) Power BI'!$B14,'Consolidado (usd)'!$E$6:$E$30,0),MATCH($A14,'Consolidado (usd)'!$AB$4:$AB$6,0)) -> 11 | E14: =+INDEX('Consolidado (usd)'!$M$6:$O$30,MATCH('Consolidado (usd) Power BI'!$B14,'Consolidado (usd)'!$E$6:$E$30,0),MATCH($A14,'Consolidado (usd)'!$AB$4:$AB$6,0)) -> 192.90909 | F14: =+INDEX('Consolidado (usd)'!$Q$6:$S$30,MATCH('Consolidado (usd) Power BI'!$B14,'Consolidado (usd)'!$E$6:$E$30,0),MATCH($A14,'Consolidado (usd)'!$AB$4:$AB$6,0)) -> 0.0013519188 | G14: =+INDEX('Consolidado (usd)'!$T$6:$V$30,MATCH('Consolidado (usd) Power BI'!$B14,'Consolidado (usd)'!$E$6:$E$30,0),MATCH($A14,'Consolidado (usd)'!$AB$4:$AB$6,0)) -> 0.0052873574 | H14: =+INDEX('Consolidado (usd)'!$W$6:$Y$30,MATCH('Consolidado (usd) Power BI'!$B14,'Consolidado (usd)'!$E$6:$E$30,0),MATCH($A14,'Consolidado (usd)'!$AB$4:$AB$6,0)) -> 0.014572914
A15: 2022 | B15: Pacasmayo | C15: =+INDEX('Consolidado (usd)'!$G$6:$I$30,MATCH('Consolidado (usd) Power BI'!B15,'Consolidado (usd)'!$E$6:$E$30,0),MATCH(A15,'Consolidado (usd)'!$AB$4:$AB$6,0)) -> 1361 | D15: =+INDEX('Consolidado (usd)'!$J$6:$L$30,MATCH('Consolidado (usd) Power BI'!$B15,'Consolidado (usd)'!$E$6:$E$30,0),MATCH($A15,'Consolidado (usd)'!$AB$4:$AB$6,0)) -> 7 | E15: =+INDEX('Consolidado (usd)'!$M$6:$O$30,MATCH('Consolidado (usd) Power BI'!$B15,'Consolidado (usd)'!$E$6:$E$30,0),MATCH($A15,'Consolidado (usd)'!$AB$4:$AB$6,0)) -> 194.42857 | F15: =+INDEX('Consolidado (usd)'!$Q$6:$S$30,MATCH('Consolidado (usd) Power BI'!$B15,'Consolidado (usd)'!$E$6:$E$30,0),MATCH($A15,'Consolidado (usd)'!$AB$4:$AB$6,0)) -> 0.0024502871 | G15: =+INDEX('Consolidado (usd)'!$T$6:$V$30,MATCH('Consolidado (usd) Power BI'!$B15,'Consolidado (usd)'!$E$6:$E$30,0),MATCH($A15,'Consolidado (usd)'!$AB$4:$AB$6,0)) -> 0.01049734 | H15: =+INDEX('Consolidado (usd)'!$W$6:$Y$30,MATCH('Consolidado (usd) Power BI'!$B15,'Consolidado (usd)'!$E$6:$E$30,0),MATCH($A15,'Consolidado (usd)'!$AB$4:$AB$6,0)) -> 0.029317674
A16: 2022 | B16: Inretail | C16: =+INDEX('Consolidado (usd)'!$G$6:$I$30,MATCH('Consolidado (usd) Power BI'!B16,'Consolidado (usd)'!$E$6:$E$30,0),MATCH(A16,'Consolidado (usd)'!$AB$4:$AB$6,0)) -> 15182 | D16: =+INDEX('Consolidado (usd)'!$J$6:$L$30,MATCH('Consolidado (usd) Power BI'!$B16,'Consolidado (usd)'!$E$6:$E$30,0),MATCH($A16,'Consolidado (usd)'!$AB$4:$AB$6,0)) -> 6 | E16: =+INDEX('Consolidado (usd)'!$M$6:$O$30,MATCH('Consolidado (usd) Power BI'!$B16,'Consolidado (usd)'!$E$6:$E$30,0),MATCH($A16,'Consolidado (usd)'!$AB$4:$AB$6,0)) -> 2530.3333 | F16: =+INDEX('Consolidado (usd)'!$Q$6:$S$30,MATCH('Consolidado (usd) Power BI'!$B16,'Consolidado (usd)'!$E$6:$E$30,0),MATCH($A16,'Consolidado (usd)'!$AB$4:$AB$6,0)) -> 0.0029233346 | G16: =+INDEX('Consolidado (usd)'!$T$6:$V$30,MATCH('Consolidado (usd) Power BI'!$B16,'Consolidado (usd)'!$E$6:$E$30,0),MATCH($A16,'Consolidado (usd)'!$AB$4:$AB$6,0)) -> 0.027955501 | H16: =+INDEX('Consolidado (usd)'!$W$6:$Y$30,MATCH('Consolidado (usd) Power BI'!$B16,'Consolidado (usd)'!$E$6:$E$30,0),MATCH($A16,'Consolidado (usd)'!$AB$4:$AB$6,0)) -> 0.078541132
A17: 2022 | B17: Alicorp | C17: =+INDEX('Consolidado (usd)'!$G$6:$I$30,MATCH('Consolidado (usd) Power BI'!B17,'Consolidado (usd)'!$E$6:$E$30,0),MATCH(A17,'Consolidado (usd)'!$AB$4:$AB$6,0)) -> 978.62976 | D17: =+INDEX('Consolidado (usd)'!$J$6:$L$30,MATCH('Consolidado (usd) Power BI'!$B17,'Consolidado (usd)'!$E$6:$E$30,0),MATCH($A17,'Consolidado (usd)'!$AB$4:$AB$6,0)) -> 9 | E17: =+INDEX('Consolidado (usd)'!$M$6:$O$30,MATCH('Consolidado (usd) Power BI'!$B17,'Consolidado (usd)'!$E$6:$E$30,0),MATCH($A17,'Consolidado (usd)'!$AB$4:$AB$6,0)) -> 108.73664 | F17: =+INDEX('Consolidado (usd)'!$Q$6:$S$30,MATCH('Consolidado (usd) Power BI'!$B17,'Consolidado (usd)'!$E$6:$E$30,0),MATCH($A17,'Consolidado (usd)'!$AB$4:$AB$6,0)) -> 0.00024217784 | G17: =+INDEX('Consolidado (usd)'!$T$6:$V$30,MATCH('Consolidado (usd) Power BI'!$B17,'Consolidado (usd)'!$E$6:$E$30,0),MATCH($A17,'Consolidado (usd)'!$AB$4:$AB$6,0)) -> 0.0023824214 | H17: =+INDEX('Consolidado (usd)'!$W$6:$Y$30,MATCH('Consolidado (usd) Power BI'!$B17,'Consolidado (usd)'!$E$6:$E$30,0),MATCH($A17,'Consolidado (usd)'!$AB$4:$AB$6,0)) -> 0.0071119876
A18: 2022 | B18: BAP | C18: =+INDEX('Consolidado (usd)'!$G$6:$I$30,MATCH('Consolidado (usd) Power BI'!B18,'Consolidado (usd)'!$E$6:$E$30,0),MATCH(A18,'Consolidado (usd)'!$AB$4:$AB$6,0)) -> 2060 | D18: =+INDEX('Consolidado (usd)'!$J$6:$L$30,MATCH('Consolidado (usd) Power BI'!$B18,'Consolidado (usd)'!$E$6:$E$30,0),MATCH($A18,'Consolidado (usd)'!$AB$4:$AB$6,0)) -> 9 | E18: =+INDEX('Consolidado (usd)'!$M$6:$O$30,MATCH('Consolidado (usd) Power BI'!$B18,'Consolidado (usd)'!$E$6:$E$30,0),MATCH($A18,'Consolidado (usd)'!$AB$4:$AB$6,0)) -> 228.88889 | F18: =+INDEX('Consolidado (usd)'!$Q$6:$S$30,MATCH('Consolidado (usd) Power BI'!$B18,'Consolidado (usd)'!$E$6:$E$30,0),MATCH($A18,'Consolidado (usd)'!$AB$4:$AB$6,0)) -> 0.00052272324 | G18: =+INDEX('Consolidado (usd)'!$T$6:$V$30,MATCH('Consolidado (usd) Power BI'!$B18,'Consolidado (usd)'!$E$6:$E$30,0),MATCH($A18,'Consolidado (usd)'!$AB$4:$AB$6,0)) -> - | H18: =+INDEX('Consolidado (usd)'!$W$6:$Y$30,MATCH('Consolidado (usd) Power BI'!$B18,'Consolidado (usd)'!$E$6:$E$30,0),MATCH($A18,'Consolidado (usd)'!$AB$4:$AB$6,0)) -> 0.0016882645
A19: 2022 | B19: IFS | C19: =+INDEX('Consolidado (usd)'!$G$6:$I$30,MATCH('Consolidado (usd) Power BI'!B19,'Consolidado (usd)'!$E$6:$E$30,0),MATCH(A19,'Consolidado (usd)'!$AB$4:$AB$6,0)) -> 1029 | D19: =+INDEX('Consolidado (usd)'!$J$6:$L$30,MATCH('Consolidado (usd) Power BI'!$B19,'Consolidado (usd)'!$E$6:$E$30,0),MATCH($A19,'Consolidado (usd)'!$AB$4:$AB$6,0)) -> 7 | E19: =+INDEX('Consolidado (usd)'!$M$6:$O$30,MATCH('Consolidado (usd) Power BI'!$B19,'Consolidado (usd)'!$E$6:$E$30,0),MATCH($A19,'Consolidado (usd)'!$AB$4:$AB$6,0)) -> 147 | F19: =+INDEX('Consolidado (usd)'!$Q$6:$S$30,MATCH('Consolidado (usd) Power BI'!$B19,'Consolidado (usd)'!$E$6:$E$30,0),MATCH($A19,'Consolidado (usd)'!$AB$4:$AB$6,0)) -> 0.00066758002 | G19: =+INDEX('Consolidado (usd)'!$T$6:$V$30,MATCH('Consolidado (usd) Power BI'!$B19,'Consolidado (usd)'!$E$6:$E$30,0),MATCH($A19,'Consolidado (usd)'!$AB$4:$AB$6,0)) -> - | H19: =+INDEX('Consolidado (usd)'!$W$6:$Y$30,MATCH('Consolidado (usd) Power BI'!$B19,'Consolidado (usd)'!$E$6:$E$30,0),MATCH($A19,'Consolidado (usd)'!$AB$4:$AB$6,0)) -> 0.0023498218
... A26: 2023 | B26: Nexa Perú | C26: =+INDEX('Consolidado (usd)'!$G$6:$I$30,MATCH('Consolidado (usd) Power BI'!B26,'Consolidado (usd)'!$E$6:$E$30,0),MATCH(A26,'Consolidado (usd)'!$AB$4:$AB$6,0)) -> 13951 | D26: =+INDEX('Consolidado (usd)'!$J$6:$L$30,MATCH('Consolidado (usd) Power BI'!$B26,'Consolidado (usd)'!$E$6:$E$30,0),MATCH($A26,'Consolidado (usd)'!$AB$4:$AB$6,0)) -> 5 | E26: =+INDEX('Consolidado (usd)'!$M$6:$O$30,MATCH('Consolidado (usd) Power BI'!$B26,'Consolidado (usd)'!$E$6:$E$30,0),MATCH($A26,'Consolidado (usd)'!$AB$4:$AB$6,0)) -> 2790.2 | F26: =+INDEX('Consolidado (usd)'!$Q$6:$S$30,MATCH('Consolidado (usd) Power BI'!$B26,'Consolidado (usd)'!$E$6:$E$30,0),MATCH($A26,'Consolidado (usd)'!$AB$4:$AB$6,0)) -> 0.018972254 | G26: =+INDEX('Consolidado (usd)'!$T$6:$V$30,MATCH('Consolidado (usd) Power BI'!$B26,'Consolidado (usd)'!$E$6:$E$30,0),MATCH($A26,'Consolidado (usd)'!$AB$4:$AB$6,0)) -> 0.075530026 | H26: =+INDEX('Consolidado (usd)'!$W$6:$Y$30,MATCH('Consolidado (usd) Power BI'!$B26,'Consolidado (usd)'!$E$6:$E$30,0),MATCH($A26,'Consolidado (usd)'!$AB$4:$AB$6,0)) -> 0.2972662
A27: 2023 | B27: Nexa Atacocha | C27: 7353 | D27: 9 | E27: 817 | F27: 0.0028574948 | G27: 0.026909719 | H27: -0.025184267
A28: 2023 | B28: Hochschild | C28: =+INDEX('Consolidado (usd)'!$G$6:$I$30,MATCH('Consolidado (usd) Power BI'!B28,'Consolidado (usd)'!$E$6:$E$30,0),MATCH(A28,'Consolidado (usd)'!$AB$4:$AB$6,0)) -> 7416 | D28: =+INDEX('Consolidado (usd)'!$J$6:$L$30,MATCH('Consolidado (usd) Power BI'!$B28,'Consolidado (usd)'!$E$6:$E$30,0),MATCH($A28,'Consolidado (usd)'!$AB$4:$AB$6,0)) -> 9 | E28: =+INDEX('Consolidado (usd)'!$M$6:$O$30,MATCH('Consolidado (usd) Power BI'!$B28,'Consolidado (usd)'!$E$6:$E$30,0),MATCH($A28,'Consolidado (usd)'!$AB$4:$AB$6,0)) -> 824 | F28: =+INDEX('Consolidado (usd)'!$Q$6:$S$30,MATCH('Consolidado (usd) Power BI'!$B28,'Consolidado (usd)'!$E$6:$E$30,0),MATCH($A28,'Consolidado (usd)'!$AB$4:$AB$6,0)) -> 0.010690254 | G28: =+INDEX('Consolidado (usd)'!$T$6:$V$30,MATCH('Consolidado (usd) Power BI'!$B28,'Consolidado (usd)'!$E$6:$E$30,0),MATCH($A28,'Consolidado (usd)'!$AB$4:$AB$6,0)) -> 0.032382158 | H28: =+INDEX('Consolidado (usd)'!$W$6:$Y$30,MATCH('Consolidado (usd) Power BI'!$B28,'Consolidado (usd)'!$E$6:$E$30,0),MATCH($A28,'Consolidado (usd)'!$AB$4:$AB$6,0)) -> -0.13482166
A29: 2023 | B29: Orygen | C29: =+INDEX('Consolidado (usd)'!$G$6:$I$30,MATCH('Consolidado (usd) Power BI'!B29,'Consolidado (usd)'!$E$6:$E$30,0),MATCH(A29,'Consolidado (usd)'!$AB$4:$AB$6,0)) -> 2425.7439 | D29: =+INDEX('Consolidado (usd)'!$J$6:$L$30,MATCH('Consolidado (usd) Power BI'!$B29,'Consolidado (usd)'!$E$6:$E$30,0),MATCH($A29,'Consolidado (usd)'!$AB$4:$AB$6,0)) -> 7 | E29: =+INDEX('Consolidado (usd)'!$M$6:$O$30,MATCH('Consolidado (usd) Power BI'!$B29,'Consolidado (usd)'!$E$6:$E$30,0),MATCH($A29,'Consolidado (usd)'!$AB$4:$AB$6,0)) -> 346.53484 | F29: =+INDEX('Consolidado (usd)'!$Q$6:$S$30,MATCH('Consolidado (usd) Power BI'!$B29,'Consolidado (usd)'!$E$6:$E$30,0),MATCH($A29,'Consolidado (usd)'!$AB$4:$AB$6,0)) -> 0.0034348105 | G29: =+INDEX('Consolidado (usd)'!$T$6:$V$30,MATCH('Consolidado (usd) Power BI'!$B29,'Consolidado (usd)'!$E$6:$E$30,0),MATCH($A29,'Consolidado (usd)'!$AB$4:$AB$6,0)) -> 0.0068688116 | H29: =+INDEX('Consolidado (usd)'!$W$6:$Y$30,MATCH('Consolidado (usd) Power BI'!$B29,'Consolidado (usd)'!$E$6:$E$30,0),MATCH($A29,'Consolidado (usd)'!$AB$4:$AB$6,0)) -> 0.011296261
A30: 2023 | B30: Pluzen | C30: =+INDEX('Consolidado (usd)'!$G$6:$I$30,MATCH('Consolidado (usd) Power BI'!B30,'Consolidado (usd)'!$E$6:$E$30,0),MATCH(A30,'Consolidado (usd)'!$AB$4:$AB$6,0)) -> 130 | D30: =+INDEX('Consolidado (usd)'!$J$6:$L$30,MATCH('Consolidado (usd) Power BI'!$B30,'Consolidado (usd)'!$E$6:$E$30,0),MATCH($A30,'Consolidado (usd)'!$AB$4:$AB$6,0)) -> 7 | E30: =+INDEX('Consolidado (usd)'!$M$6:$O$30,MATCH('Consolidado (usd) Power BI'!$B30,'Consolidado (usd)'!$E$6:$E$30,0),MATCH($A30,'Consolidado (usd)'!$AB$4:$AB$6,0)) -> 18.571429 | F30: =+INDEX('Consolidado (usd)'!$Q$6:$S$30,MATCH('Consolidado (usd) Power BI'!$B30,'Consolidado (usd)'!$E$6:$E$30,0),MATCH($A30,'Consolidado (usd)'!$AB$4:$AB$6,0)) -> 0.00011680066 | G30: =+INDEX('Consolidado (usd)'!$T$6:$V$30,MATCH('Consolidado (usd) Power BI'!$B30,'Consolidado (usd)'!$E$6:$E$30,0),MATCH($A30,'Consolidado (usd)'!$AB$4:$AB$6,0)) -> 0.00050330598 | H30: =+INDEX('Consolidado (usd)'!$W$6:$Y$30,MATCH('Consolidado (usd) Power BI'!$B30,'Consolidado (usd)'!$E$6:$E$30,0),MATCH($A30,'Consolidado (usd)'!$AB$4:$AB$6,0)) -> 0.0011138709
A31: 2023 | B31: Engie | C31: =+INDEX('Consolidado (usd)'!$G$6:$I$30,MATCH('Consolidado (usd) Power BI'!B31,'Consolidado (usd)'!$E$6:$E$30,0),MATCH(A31,'Consolidado (usd)'!$AB$4:$AB$6,0)) -> 869 | D31: =+INDEX('Consolidado (usd)'!$J$6:$L$30,MATCH('Consolidado (usd) Power BI'!$B31,'Consolidado (usd)'!$E$6:$E$30,0),MATCH($A31,'Consolidado (usd)'!$AB$4:$AB$6,0)) -> 7 | E31: =+INDEX('Consolidado (usd)'!$M$6:$O$30,MATCH('Consolidado (usd) Power BI'!$B31,'Consolidado (usd)'!$E$6:$E$30,0),MATCH($A31,'Consolidado (usd)'!$AB$4:$AB$6,0)) -> 124.14286 | F31: =+INDEX('Consolidado (usd)'!$Q$6:$S$30,MATCH('Consolidado (usd) Power BI'!$B31,'Consolidado (usd)'!$E$6:$E$30,0),MATCH($A31,'Consolidado (usd)'!$AB$4:$AB$6,0)) -> 0.001293534 | G31: =+INDEX('Consolidado (usd)'!$T$6:$V$30,MATCH('Consolidado (usd) Power BI'!$B31,'Consolidado (usd)'!$E$6:$E$30,0),MATCH($A31,'Consolidado (usd)'!$AB$4:$AB$6,0)) -> 0.0053140747 | H31: =+INDEX('Consolidado (usd)'!$W$6:$Y$30,MATCH('Consolidado (usd) Power BI'!$B31,'Consolidado (usd)'!$E$6:$E$30,0),MATCH($A31,'Consolidado (usd)'!$AB$4:$AB$6,0)) -> 0.14483333
A32: 2023 | B32: Ferreycorp | C32: =+INDEX('Consolidado (usd)'!$G$6:$I$30,MATCH('Consolidado (usd) Power BI'!B32,'Consolidado (usd)'!$E$6:$E$30,0),MATCH(A32,'Consolidado (usd)'!$AB$4:$AB$6,0)) -> 11318.433 | D32: =+INDEX('Consolidado (usd)'!$J$6:$L$30,MATCH('Consolidado (usd) Power BI'!$B32,'Consolidado (usd)'!$E$6:$E$30,0),MATCH($A32,'Consolidado (usd)'!$AB$4:$AB$6,0)) -> 9 | E32: =+INDEX('Consolidado (usd)'!$M$6:$O$30,MATCH('Consolidado (usd) Power BI'!$B32,'Consolidado (usd)'!$E$6:$E$30,0),MATCH($A32,'Consolidado (usd)'!$AB$4:$AB$6,0)) -> 1257.6036 | F32: =+INDEX('Consolidado (usd)'!$Q$6:$S$30,MATCH('Consolidado (usd) Power BI'!$B32,'Consolidado (usd)'!$E$6:$E$30,0),MATCH($A32,'Consolidado (usd)'!$AB$4:$AB$6,0)) -> 0.0060547217 | G32: =+INDEX('Consolidado (usd)'!$T$6:$V$30,MATCH('Consolidado (usd) Power BI'!$B32,'Consolidado (usd)'!$E$6:$E$30,0),MATCH($A32,'Consolidado (usd)'!$AB$4:$AB$6,0)) -> 0.051510977 | H32: =+INDEX('Consolidado (usd)'!$W$6:$Y$30,MATCH('Consolidado (usd) Power BI'!$B32,'Consolidado (usd)'!$E$6:$E$30,0),MATCH($A32,'Consolidado (usd)'!$AB$4:$AB$6,0)) -> 0.096878885
A33: 2023 | B33: AENZA | C33: =+INDEX('Consolidado (usd)'!$G$6:$I$30,MATCH('Consolidado (usd) Power BI'!B33,'Consolidado (usd)'!$E$6:$E$30,0),MATCH(A33,'Consolidado (usd)'!$AB$4:$AB$6,0)) -> 9829.0023 | D33: =+INDEX('Consolidado (usd)'!$J$6:$L$30,MATCH('Consolidado (usd) Power BI'!$B33,'Consolidado (usd)'!$E$6:$E$30,0),MATCH($A33,'Consolidado (usd)'!$AB$4:$AB$6,0)) -> 9 | E33: =+INDEX('Consolidado (usd)'!$M$6:$O$30,MATCH('Consolidado (usd) Power BI'!$B33,'Consolidado (usd)'!$E$6:$E$30,0),MATCH($A33,'Consolidado (usd)'!$AB$4:$AB$6,0)) -> 1092.1114 | F33: =+INDEX('Consolidado (usd)'!$Q$6:$S$30,MATCH('Consolidado (usd) Power BI'!$B33,'Consolidado (usd)'!$E$6:$E$30,0),MATCH($A33,'Consolidado (usd)'!$AB$4:$AB$6,0)) -> 0.0084854614 | G33: =+INDEX('Consolidado (usd)'!$T$6:$V$30,MATCH('Consolidado (usd) Power BI'!$B33,'Consolidado (usd)'!$E$6:$E$30,0),MATCH($A33,'Consolidado (usd)'!$AB$4:$AB$6,0)) -> 0.061072634 | H33: =+INDEX('Consolidado (usd)'!$W$6:$Y$30,MATCH('Consolidado (usd) Power BI'!$B33,'Consolidado (usd)'!$E$6:$E$30,0),MATCH($A33,'Consolidado (usd)'!$AB$4:$AB$6,0)) -> 0.43144724
A34: 2023 | B34: UNACEM | C34: =+INDEX('Consolidado (usd)'!$G$6:$I$30,MATCH('Consolidado (usd) Power BI'!B34,'Consolidado (usd)'!$E$6:$E$30,0),MATCH(A34,'Consolidado (usd)'!$AB$4:$AB$6,0)) -> 1702.7063 | D34: =+INDEX('Consolidado (usd)'!$J$6:$L$30,MATCH('Consolidado (usd) Power BI'!$B34,'Consolidado (usd)'!$E$6:$E$30,0),MATCH($A34,'Consolidado (usd)'!$AB$4:$AB$6,0)) -> 11 | E34: =+INDEX('Consolidado (usd)'!$M$6:$O$30,MATCH('Consolidado (usd) Power BI'!$B34,'Consolidado (usd)'!$E$6:$E$30,0),MATCH($A34,'Consolidado (usd)'!$AB$4:$AB$6,0)) -> 154.79149 | F34: =+INDEX('Consolidado (usd)'!$Q$6:$S$30,MATCH('Consolidado (usd) Power BI'!$B34,'Consolidado (usd)'!$E$6:$E$30,0),MATCH($A34,'Consolidado (usd)'!$AB$4:$AB$6,0)) -> 0.00099164496 | G34: =+INDEX('Consolidado (usd)'!$T$6:$V$30,MATCH('Consolidado (usd) Power BI'!$B34,'Consolidado (usd)'!$E$6:$E$30,0),MATCH($A34,'Consolidado (usd)'!$AB$4:$AB$6,0)) -> 0.0043552321 | H34: =+INDEX('Consolidado (usd)'!$W$6:$Y$30,MATCH('Consolidado (usd) Power BI'!$B34,'Consolidado (usd)'!$E$6:$E$30,0),MATCH($A34,'Consolidado (usd)'!$AB$4:$AB$6,0)) -> 0.012409841
A35: 2023 | B35: Pacasmayo | C35: =+INDEX('Consolidado (usd)'!$G$6:$I$30,MATCH('Consolidado (usd) Power BI'!B35,'Consolidado (usd)'!$E$6:$E$30,0),MATCH(A35,'Consolidado (usd)'!$AB$4:$AB$6,0)) -> 1599.8384 | D35: =+INDEX('Consolidado (usd)'!$J$6:$L$30,MATCH('Consolidado (usd) Power BI'!$B35,'Consolidado (usd)'!$E$6:$E$30,0),MATCH($A35,'Consolidado (usd)'!$AB$4:$AB$6,0)) -> 7 | E35: =+INDEX('Consolidado (usd)'!$M$6:$O$30,MATCH('Consolidado (usd) Power BI'!$B35,'Consolidado (usd)'!$E$6:$E$30,0),MATCH($A35,'Consolidado (usd)'!$AB$4:$AB$6,0)) -> 228.54835 | F35: =+INDEX('Consolidado (usd)'!$Q$6:$S$30,MATCH('Consolidado (usd) Power BI'!$B35,'Consolidado (usd)'!$E$6:$E$30,0),MATCH($A35,'Consolidado (usd)'!$AB$4:$AB$6,0)) -> 0.0030465495 | G35: =+INDEX('Consolidado (usd)'!$T$6:$V$30,MATCH('Consolidado (usd) Power BI'!$B35,'Consolidado (usd)'!$E$6:$E$30,0),MATCH($A35,'Consolidado (usd)'!$AB$4:$AB$6,0)) -> 0.011502932 | H35: =+INDEX('Consolidado (usd)'!$W$6:$Y$30,MATCH('Consolidado (usd) Power BI'!$B35,'Consolidado (usd)'!$E$6:$E$30,0),MATCH($A35,'Consolidado (usd)'!$AB$4:$AB$6,0)) -> 0.035174658
A36: 2023 | B36: Inretail | C36: =+INDEX('Consolidado (usd)'!$G$6:$I$30,MATCH('Consolidado (usd) Power BI'!B36,'Consolidado (usd)'!$E$6:$E$30,0),MATCH(A36,'Consolidado (usd)'!$AB$4:$AB$6,0)) -> 17667.699 | D36: =+INDEX('Consolidado (usd)'!$J$6:$L$30,MATCH('Consolidado (usd) Power BI'!$B36,'Consolidado (usd)'!$E$6:$E$30,0),MATCH($A36,'Consolidado (usd)'!$AB$4:$AB$6,0)) -> 6 | E36: =+INDEX('Consolidado (usd)'!$M$6:$O$30,MATCH('Consolidado (usd) Power BI'!$B36,'Consolidado (usd)'!$E$6:$E$30,0),MATCH($A36,'Consolidado (usd)'!$AB$4:$AB$6,0)) -> 2944.6165 | F36: =+INDEX('Consolidado (usd)'!$Q$6:$S$30,MATCH('Consolidado (usd) Power BI'!$B36,'Consolidado (usd)'!$E$6:$E$30,0),MATCH($A36,'Consolidado (usd)'!$AB$4:$AB$6,0)) -> 0.0031447962 | G36: =+INDEX('Consolidado (usd)'!$T$6:$V$30,MATCH('Consolidado (usd) Power BI'!$B36,'Consolidado (usd)'!$E$6:$E$30,0),MATCH($A36,'Consolidado (usd)'!$AB$4:$AB$6,0)) -> 0.028010682 | H36: =+INDEX('Consolidado (usd)'!$W$6:$Y$30,MATCH('Consolidado (usd) Power BI'!$B36,'Consolidado (usd)'!$E$6:$E$30,0),MATCH($A36,'Consolidado (usd)'!$AB$4:$AB$6,0)) -> 0.070112688
A37: 2023 | B37: Alicorp | C37: =+INDEX('Consolidado (usd)'!$G$6:$I$30,MATCH('Consolidado (usd) Power BI'!B37,'Consolidado (usd)'!$E$6:$E$30,0),MATCH(A37,'Consolidado (usd)'!$AB$4:$AB$6,0)) -> 935.50559 | D37: =+INDEX('Consolidado (usd)'!$J$6:$L$30,MATCH('Consolidado (usd) Power BI'!$B37,'Consolidado (usd)'!$E$6:$E$30,0),MATCH($A37,'Consolidado (usd)'!$AB$4:$AB$6,0)) -> 9 | E37: =+INDEX('Consolidado (usd)'!$M$6:$O$30,MATCH('Consolidado (usd) Power BI'!$B37,'Consolidado (usd)'!$E$6:$E$30,0),MATCH($A37,'Consolidado (usd)'!$AB$4:$AB$6,0)) -> 103.94507 | F37: =+INDEX('Consolidado (usd)'!$Q$6:$S$30,MATCH('Consolidado (usd) Power BI'!$B37,'Consolidado (usd)'!$E$6:$E$30,0),MATCH($A37,'Consolidado (usd)'!$AB$4:$AB$6,0)) -> 0.0003146992 | G37: =+INDEX('Consolidado (usd)'!$T$6:$V$30,MATCH('Consolidado (usd) Power BI'!$B37,'Consolidado (usd)'!$E$6:$E$30,0),MATCH($A37,'Consolidado (usd)'!$AB$4:$AB$6,0)) -> 0.0031917914 | H37: =+INDEX('Consolidado (usd)'!$W$6:$Y$30,MATCH('Consolidado (usd) Power BI'!$B37,'Consolidado (usd)'!$E$6:$E$30,0),MATCH($A37,'Consolidado (usd)'!$AB$4:$AB$6,0)) -> 0.018442525
A38: 2023 | B38: BAP | C38: =+INDEX('Consolidado (usd)'!$G$6:$I$30,MATCH('Consolidado (usd) Power BI'!B38,'Consolidado (usd)'!$E$6:$E$30,0),MATCH(A38,'Consolidado (usd)'!$AB$4:$AB$6,0)) -> 1989.2285 | D38: =+INDEX('Consolidado (usd)'!$J$6:$L$30,MATCH('Consolidado (usd) Power BI'!$B38,'Consolidado (usd)'!$E$6:$E$30,0),MATCH($A38,'Consolidado (usd)'!$AB$4:$AB$6,0)) -> 9 | E38: =+INDEX('Consolidado (usd)'!$M$6:$O$30,MATCH('Consolidado (usd) Power BI'!$B38,'Consolidado (usd)'!$E$6:$E$30,0),MATCH($A38,'Consolidado (usd)'!$AB$4:$AB$6,0)) -> 221.02539 | F38: =+INDEX('Consolidado (usd)'!$Q$6:$S$30,MATCH('Consolidado (usd) Power BI'!$B38,'Consolidado (usd)'!$E$6:$E$30,0),MATCH($A38,'Consolidado (usd)'!$AB$4:$AB$6,0)) -> 0.00039295699 | G38: =+INDEX('Consolidado (usd)'!$T$6:$V$30,MATCH('Consolidado (usd) Power BI'!$B38,'Consolidado (usd)'!$E$6:$E$30,0),MATCH($A38,'Consolidado (usd)'!$AB$4:$AB$6,0)) -> - | H38: =+INDEX('Consolidado (usd)'!$W$6:$Y$30,MATCH('Consolidado (usd) Power BI'!$B38,'Consolidado (usd)'!$E$6:$E$30,0),MATCH($A38,'Consolidado (usd)'!$AB$4:$AB$6,0)) -> 0.0015182282
A39: 2023 | B39: IFS | C39: =+INDEX('Consolidado (usd)'!$G$6:$I$30,MATCH('Consolidado (usd) Power BI'!B39,'Consolidado (usd)'!$E$6:$E$30,0),MATCH(A39,'Consolidado (usd)'!$AB$4:$AB$6,0)) -> 566.58139 | D39: =+INDEX('Consolidado (usd)'!$J$6:$L$30,MATCH('Consolidado (usd) Power BI'!$B39,'Consolidado (usd)'!$E$6:$E$30,0),MATCH($A39,'Consolidado (usd)'!$AB$4:$AB$6,0)) -> 7 | E39: =+INDEX('Consolidado (usd)'!$M$6:$O$30,MATCH('Consolidado (usd) Power BI'!$B39,'Consolidado (usd)'!$E$6:$E$30,0),MATCH($A39,'Consolidado (usd)'!$AB$4:$AB$6,0)) -> 80.940199 | F39: =+INDEX('Consolidado (usd)'!$Q$6:$S$30,MATCH('Consolidado (usd) Power BI'!$B39,'Consolidado (usd)'!$E$6:$E$30,0),MATCH($A39,'Consolidado (usd)'!$AB$4:$AB$6,0)) -> 0.00029548856 | G39: =+INDEX('Consolidado (usd)'!$T$6:$V$30,MATCH('Consolidado (usd) Power BI'!$B39,'Consolidado (usd)'!$E$6:$E$30,0),MATCH($A39,'Consolidado (usd)'!$AB$4:$AB$6,0)) -> - | H39: =+INDEX('Consolidado (usd)'!$W$6:$Y$30,MATCH('Consolidado (usd) Power BI'!$B39,'Consolidado (usd)'!$E$6:$E$30,0),MATCH($A39,'Consolidado (usd)'!$AB$4:$AB$6,0)) -> 0.0019613546
... A46: 2024 | B46: Nexa Perú | C46: =+INDEX('Consolidado (usd)'!$G$6:$I$30,MATCH('Consolidado (usd) Power BI'!B46,'Consolidado (usd)'!$E$6:$E$30,0),MATCH(A46,'Consolidado (usd)'!$AB$4:$AB$6,0)) -> 11342 | D46: =+INDEX('Consolidado (usd)'!$J$6:$L$30,MATCH('Consolidado (usd) Power BI'!$B46,'Consolidado (usd)'!$E$6:$E$30,0),MATCH($A46,'Consolidado (usd)'!$AB$4:$AB$6,0)) -> 5 | E46: =+INDEX('Consolidado (usd)'!$M$6:$O$30,MATCH('Consolidado (usd) Power BI'!$B46,'Consolidado (usd)'!$E$6:$E$30,0),MATCH($A46,'Consolidado (usd)'!$AB$4:$AB$6,0)) -> 2268.4 | F46: =+INDEX('Consolidado (usd)'!$Q$6:$S$30,MATCH('Consolidado (usd) Power BI'!$B46,'Consolidado (usd)'!$E$6:$E$30,0),MATCH($A46,'Consolidado (usd)'!$AB$4:$AB$6,0)) -> 0.012872224 | G46: =+INDEX('Consolidado (usd)'!$T$6:$V$30,MATCH('Consolidado (usd) Power BI'!$B46,'Consolidado (usd)'!$E$6:$E$30,0),MATCH($A46,'Consolidado (usd)'!$AB$4:$AB$6,0)) -> 0.038106565 | H46: =+INDEX('Consolidado (usd)'!$W$6:$Y$30,MATCH('Consolidado (usd) Power BI'!$B46,'Consolidado (usd)'!$E$6:$E$30,0),MATCH($A46,'Consolidado (usd)'!$AB$4:$AB$6,0)) -> 2.6959829
A47: 2024 | B47: Nexa Atacocha | C47: 7829 | D47: 9 | E47: 869.88889 | F47: 0.0028299489 | G47: 0.01286581 | H47: -0.038184656
A48: 2024 | B48: Hochschild | C48: =+INDEX('Consolidado (usd)'!$G$6:$I$30,MATCH('Consolidado (usd) Power BI'!B48,'Consolidado (usd)'!$E$6:$E$30,0),MATCH(A48,'Consolidado (usd)'!$AB$4:$AB$6,0)) -> 8284 | D48: =+INDEX('Consolidado (usd)'!$J$6:$L$30,MATCH('Consolidado (usd) Power BI'!$B48,'Consolidado (usd)'!$E$6:$E$30,0),MATCH($A48,'Consolidado (usd)'!$AB$4:$AB$6,0)) -> 9 | E48: =+INDEX('Consolidado (usd)'!$M$6:$O$30,MATCH('Consolidado (usd) Power BI'!$B48,'Consolidado (usd)'!$E$6:$E$30,0),MATCH($A48,'Consolidado (usd)'!$AB$4:$AB$6,0)) -> 920.44444 | F48: =+INDEX('Consolidado (usd)'!$Q$6:$S$30,MATCH('Consolidado (usd) Power BI'!$B48,'Consolidado (usd)'!$E$6:$E$30,0),MATCH($A48,'Consolidado (usd)'!$AB$4:$AB$6,0)) -> 0.0087411997 | G48: =+INDEX('Consolidado (usd)'!$T$6:$V$30,MATCH('Consolidado (usd) Power BI'!$B48,'Consolidado (usd)'!$E$6:$E$30,0),MATCH($A48,'Consolidado (usd)'!$AB$4:$AB$6,0)) -> 0.020628209 | H48: =+INDEX('Consolidado (usd)'!$W$6:$Y$30,MATCH('Consolidado (usd) Power BI'!$B48,'Consolidado (usd)'!$E$6:$E$30,0),MATCH($A48,'Consolidado (usd)'!$AB$4:$AB$6,0)) -> 0.08539766
A49: 2024 | B49: Orygen | C49: =+INDEX('Consolidado (usd)'!$G$6:$I$30,MATCH('Consolidado (usd) Power BI'!B49,'Consolidado (usd)'!$E$6:$E$30,0),MATCH(A49,'Consolidado (usd)'!$AB$4:$AB$6,0)) -> 2476.1374 | D49: =+INDEX('Consolidado (usd)'!$J$6:$L$30,MATCH('Consolidado (usd) Power BI'!$B49,'Consolidado (usd)'!$E$6:$E$30,0),MATCH($A49,'Consolidado (usd)'!$AB$4:$AB$6,0)) -> 7 | E49: =+INDEX('Consolidado (usd)'!$M$6:$O$30,MATCH('Consolidado (usd) Power BI'!$B49,'Consolidado (usd)'!$E$6:$E$30,0),MATCH($A49,'Consolidado (usd)'!$AB$4:$AB$6,0)) -> 353.73392 | F49: =+INDEX('Consolidado (usd)'!$Q$6:$S$30,MATCH('Consolidado (usd) Power BI'!$B49,'Consolidado (usd)'!$E$6:$E$30,0),MATCH($A49,'Consolidado (usd)'!$AB$4:$AB$6,0)) -> 0.0033373202 | G49: =+INDEX('Consolidado (usd)'!$T$6:$V$30,MATCH('Consolidado (usd) Power BI'!$B49,'Consolidado (usd)'!$E$6:$E$30,0),MATCH($A49,'Consolidado (usd)'!$AB$4:$AB$6,0)) -> 0.0057819179 | H49: =+INDEX('Consolidado (usd)'!$W$6:$Y$30,MATCH('Consolidado (usd) Power BI'!$B49,'Consolidado (usd)'!$E$6:$E$30,0),MATCH($A49,'Consolidado (usd)'!$AB$4:$AB$6,0)) -> 0.010053016
A50: 2024 | B50: Pluzen | C50: =+INDEX('Consolidado (usd)'!$G$6:$I$30,MATCH('Consolidado (usd) Power BI'!B50,'Consolidado (usd)'!$E$6:$E$30,0),MATCH(A50,'Consolidado (usd)'!$AB$4:$AB$6,0)) -> 2522.5369 | D50: =+INDEX('Consolidado (usd)'!$J$6:$L$30,MATCH('Consolidado (usd) Power BI'!$B50,'Consolidado (usd)'!$E$6:$E$30,0),MATCH($A50,'Consolidado (usd)'!$AB$4:$AB$6,0)) -> 7 | E50: =+INDEX('Consolidado (usd)'!$M$6:$O$30,MATCH('Consolidado (usd) Power BI'!$B50,'Consolidado (usd)'!$E$6:$E$30,0),MATCH($A50,'Consolidado (usd)'!$AB$4:$AB$6,0)) -> 360.36241 | F50: =+INDEX('Consolidado (usd)'!$Q$6:$S$30,MATCH('Consolidado (usd) Power BI'!$B50,'Consolidado (usd)'!$E$6:$E$30,0),MATCH($A50,'Consolidado (usd)'!$AB$4:$AB$6,0)) -> 0.0023208286 | G50: =+INDEX('Consolidado (usd)'!$T$6:$V$30,MATCH('Consolidado (usd) Power BI'!$B50,'Consolidado (usd)'!$E$6:$E$30,0),MATCH($A50,'Consolidado (usd)'!$AB$4:$AB$6,0)) -> 0.0095078864 | H50: =+INDEX('Consolidado (usd)'!$W$6:$Y$30,MATCH('Consolidado (usd) Power BI'!$B50,'Consolidado (usd)'!$E$6:$E$30,0),MATCH($A50,'Consolidado (usd)'!$AB$4:$AB$6,0)) -> 0.024799097
A51: 2024 | B51: Engie | C51: =+INDEX('Consolidado (usd)'!$G$6:$I$30,MATCH('Consolidado (usd) Power BI'!B51,'Consolidado (usd)'!$E$6:$E$30,0),MATCH(A51,'Consolidado (usd)'!$AB$4:$AB$6,0)) -> 1974 | D51: =+INDEX('Consolidado (usd)'!$J$6:$L$30,MATCH('Consolidado (usd) Power BI'!$B51,'Consolidado (usd)'!$E$6:$E$30,0),MATCH($A51,'Consolidado (usd)'!$AB$4:$AB$6,0)) -> 7 | E51: =+INDEX('Consolidado (usd)'!$M$6:$O$30,MATCH('Consolidado (usd) Power BI'!$B51,'Consolidado (usd)'!$E$6:$E$30,0),MATCH($A51,'Consolidado (usd)'!$AB$4:$AB$6,0)) -> 282 | F51: =+INDEX('Consolidado (usd)'!$Q$6:$S$30,MATCH('Consolidado (usd) Power BI'!$B51,'Consolidado (usd)'!$E$6:$E$30,0),MATCH($A51,'Consolidado (usd)'!$AB$4:$AB$6,0)) -> 0.0027257024 | G51: =+INDEX('Consolidado (usd)'!$T$6:$V$30,MATCH('Consolidado (usd) Power BI'!$B51,'Consolidado (usd)'!$E$6:$E$30,0),MATCH($A51,'Consolidado (usd)'!$AB$4:$AB$6,0)) -> 0.0075640009 | H51: =+INDEX('Consolidado (usd)'!$W$6:$Y$30,MATCH('Consolidado (usd) Power BI'!$B51,'Consolidado (usd)'!$E$6:$E$30,0),MATCH($A51,'Consolidado (usd)'!$AB$4:$AB$6,0)) -> 0.020024143
A52: 2024 | B52: Ferreycorp | C52: =+INDEX('Consolidado (usd)'!$G$6:$I$30,MATCH('Consolidado (usd) Power BI'!B52,'Consolidado (usd)'!$E$6:$E$30,0),MATCH(A52,'Consolidado (usd)'!$AB$4:$AB$6,0)) -> 11756.284 | D52: =+INDEX('Consolidado (usd)'!$J$6:$L$30,MATCH('Consolidado (usd) Power BI'!$B52,'Consolidado (usd)'!$E$6:$E$30,0),MATCH($A52,'Consolidado (usd)'!$AB$4:$AB$6,0)) -> 9 | E52: =+INDEX('Consolidado (usd)'!$M$6:$O$30,MATCH('Consolidado (usd) Power BI'!$B52,'Consolidado (usd)'!$E$6:$E$30,0),MATCH($A52,'Consolidado (usd)'!$AB$4:$AB$6,0)) -> 1306.2538 | F52: =+INDEX('Consolidado (usd)'!$Q$6:$S$30,MATCH('Consolidado (usd) Power BI'!$B52,'Consolidado (usd)'!$E$6:$E$30,0),MATCH($A52,'Consolidado (usd)'!$AB$4:$AB$6,0)) -> 0.0058478946 | G52: =+INDEX('Consolidado (usd)'!$T$6:$V$30,MATCH('Consolidado (usd) Power BI'!$B52,'Consolidado (usd)'!$E$6:$E$30,0),MATCH($A52,'Consolidado (usd)'!$AB$4:$AB$6,0)) -> 0.044382029 | H52: =+INDEX('Consolidado (usd)'!$W$6:$Y$30,MATCH('Consolidado (usd) Power BI'!$B52,'Consolidado (usd)'!$E$6:$E$30,0),MATCH($A52,'Consolidado (usd)'!$AB$4:$AB$6,0)) -> 0.090711388
A53: 2024 | B53: AENZA | C53: =+INDEX('Consolidado (usd)'!$G$6:$I$30,MATCH('Consolidado (usd) Power BI'!B53,'Consolidado (usd)'!$E$6:$E$30,0),MATCH(A53,'Consolidado (usd)'!$AB$4:$AB$6,0)) -> 8484.4628 | D53: =+INDEX('Consolidado (usd)'!$J$6:$L$30,MATCH('Consolidado (usd) Power BI'!$B53,'Consolidado (usd)'!$E$6:$E$30,0),MATCH($A53,'Consolidado (usd)'!$AB$4:$AB$6,0)) -> 9 | E53: =+INDEX('Consolidado (usd)'!$M$6:$O$30,MATCH('Consolidado (usd) Power BI'!$B53,'Consolidado (usd)'!$E$6:$E$30,0),MATCH($A53,'Consolidado (usd)'!$AB$4:$AB$6,0)) -> 942.71809 | F53: =+INDEX('Consolidado (usd)'!$Q$6:$S$30,MATCH('Consolidado (usd) Power BI'!$B53,'Consolidado (usd)'!$E$6:$E$30,0),MATCH($A53,'Consolidado (usd)'!$AB$4:$AB$6,0)) -> 0.01824931 | G53: =+INDEX('Consolidado (usd)'!$T$6:$V$30,MATCH('Consolidado (usd) Power BI'!$B53,'Consolidado (usd)'!$E$6:$E$30,0),MATCH($A53,'Consolidado (usd)'!$AB$4:$AB$6,0)) -> 0.069362558 | H53: =+INDEX('Consolidado (usd)'!$W$6:$Y$30,MATCH('Consolidado (usd) Power BI'!$B53,'Consolidado (usd)'!$E$6:$E$30,0),MATCH($A53,'Consolidado (usd)'!$AB$4:$AB$6,0)) -> -0.12929919
A54: 2024 | B54: UNACEM | C54: =+INDEX('Consolidado (usd)'!$G$6:$I$30,MATCH('Consolidado (usd) Power BI'!B54,'Consolidado (usd)'!$E$6:$E$30,0),MATCH(A54,'Consolidado (usd)'!$AB$4:$AB$6,0)) -> 1782.7978 | D54: =+INDEX('Consolidado (usd)'!$J$6:$L$30,MATCH('Consolidado (usd) Power BI'!$B54,'Consolidado (usd)'!$E$6:$E$30,0),MATCH($A54,'Consolidado (usd)'!$AB$4:$AB$6,0)) -> 11 | E54: =+INDEX('Consolidado (usd)'!$M$6:$O$30,MATCH('Consolidado (usd) Power BI'!$B54,'Consolidado (usd)'!$E$6:$E$30,0),MATCH($A54,'Consolidado (usd)'!$AB$4:$AB$6,0)) -> 162.07252 | F54: =+INDEX('Consolidado (usd)'!$Q$6:$S$30,MATCH('Consolidado (usd) Power BI'!$B54,'Consolidado (usd)'!$E$6:$E$30,0),MATCH($A54,'Consolidado (usd)'!$AB$4:$AB$6,0)) -> 0.00098089029 | G54: =+INDEX('Consolidado (usd)'!$T$6:$V$30,MATCH('Consolidado (usd) Power BI'!$B54,'Consolidado (usd)'!$E$6:$E$30,0),MATCH($A54,'Consolidado (usd)'!$AB$4:$AB$6,0)) -> 0.0042135553 | H54: =+INDEX('Consolidado (usd)'!$W$6:$Y$30,MATCH('Consolidado (usd) Power BI'!$B54,'Consolidado (usd)'!$E$6:$E$30,0),MATCH($A54,'Consolidado (usd)'!$AB$4:$AB$6,0)) -> 0.014937774
A55: 2024 | B55: Pacasmayo | C55: =+INDEX('Consolidado (usd)'!$G$6:$I$30,MATCH('Consolidado (usd) Power BI'!B55,'Consolidado (usd)'!$E$6:$E$30,0),MATCH(A55,'Consolidado (usd)'!$AB$4:$AB$6,0)) -> 1599.3212 | D55: =+INDEX('Consolidado (usd)'!$J$6:$L$30,MATCH('Consolidado (usd) Power BI'!$B55,'Consolidado (usd)'!$E$6:$E$30,0),MATCH($A55,'Consolidado (usd)'!$AB$4:$AB$6,0)) -> 7 | E55: =+INDEX('Consolidado (usd)'!$M$6:$O$30,MATCH('Consolidado (usd) Power BI'!$B55,'Consolidado (usd)'!$E$6:$E$30,0),MATCH($A55,'Consolidado (usd)'!$AB$4:$AB$6,0)) -> 228.47446 | F55: =+INDEX('Consolidado (usd)'!$Q$6:$S$30,MATCH('Consolidado (usd) Power BI'!$B55,'Consolidado (usd)'!$E$6:$E$30,0),MATCH($A55,'Consolidado (usd)'!$AB$4:$AB$6,0)) -> 0.0030494356 | G55: =+INDEX('Consolidado (usd)'!$T$6:$V$30,MATCH('Consolidado (usd) Power BI'!$B55,'Consolidado (usd)'!$E$6:$E$30,0),MATCH($A55,'Consolidado (usd)'!$AB$4:$AB$6,0)) -> 0.011251569 | H55: =+INDEX('Consolidado (usd)'!$W$6:$Y$30,MATCH('Consolidado (usd) Power BI'!$B55,'Consolidado (usd)'!$E$6:$E$30,0),MATCH($A55,'Consolidado (usd)'!$AB$4:$AB$6,0)) -> 0.03033061
A56: 2024 | B56: Inretail | C56: =+INDEX('Consolidado (usd)'!$G$6:$I$30,MATCH('Consolidado (usd) Power BI'!B56,'Consolidado (usd)'!$E$6:$E$30,0),MATCH(A56,'Consolidado (usd)'!$AB$4:$AB$6,0)) -> 19143.069 | D56: =+INDEX('Consolidado (usd)'!$J$6:$L$30,MATCH('Consolidado (usd) Power BI'!$B56,'Consolidado (usd)'!$E$6:$E$30,0),MATCH($A56,'Consolidado (usd)'!$AB$4:$AB$6,0)) -> 6 | E56: =+INDEX('Consolidado (usd)'!$M$6:$O$30,MATCH('Consolidado (usd) Power BI'!$B56,'Consolidado (usd)'!$E$6:$E$30,0),MATCH($A56,'Consolidado (usd)'!$AB$4:$AB$6,0)) -> 3190.5115 | F56: =+INDEX('Consolidado (usd)'!$Q$6:$S$30,MATCH('Consolidado (usd) Power BI'!$B56,'Consolidado (usd)'!$E$6:$E$30,0),MATCH($A56,'Consolidado (usd)'!$AB$4:$AB$6,0)) -> 0.003329742 | G56: =+INDEX('Consolidado (usd)'!$T$6:$V$30,MATCH('Consolidado (usd) Power BI'!$B56,'Consolidado (usd)'!$E$6:$E$30,0),MATCH($A56,'Consolidado (usd)'!$AB$4:$AB$6,0)) -> 0.028913505 | H56: =+INDEX('Consolidado (usd)'!$W$6:$Y$30,MATCH('Consolidado (usd) Power BI'!$B56,'Consolidado (usd)'!$E$6:$E$30,0),MATCH($A56,'Consolidado (usd)'!$AB$4:$AB$6,0)) -> 0.074329235
A57: 2024 | B57: Alicorp | C57: =+INDEX('Consolidado (usd)'!$G$6:$I$30,MATCH('Consolidado (usd) Power BI'!B57,'Consolidado (usd)'!$E$6:$E$30,0),MATCH(A57,'Consolidado (usd)'!$AB$4:$AB$6,0)) -> - | D57: =+INDEX('Consolidado (usd)'!$J$6:$L$30,MATCH('Consolidado (usd) Power BI'!$B57,'Consolidado (usd)'!$E$6:$E$30,0),MATCH($A57,'Consolidado (usd)'!$AB$4:$AB$6,0)) -> 9 | E57: =+INDEX('Consolidado (usd)'!$M$6:$O$30,MATCH('Consolidado (usd) Power BI'!$B57,'Consolidado (usd)'!$E$6:$E$30,0),MATCH($A57,'Consolidado (usd)'!$AB$4:$AB$6,0)) -> - | F57: =+INDEX('Consolidado (usd)'!$Q$6:$S$30,MATCH('Consolidado (usd) Power BI'!$B57,'Consolidado (usd)'!$E$6:$E$30,0),MATCH($A57,'Consolidado (usd)'!$AB$4:$AB$6,0)) -> - | G57: =+INDEX('Consolidado (usd)'!$T$6:$V$30,MATCH('Consolidado (usd) Power BI'!$B57,'Consolidado (usd)'!$E$6:$E$30,0),MATCH($A57,'Consolidado (usd)'!$AB$4:$AB$6,0)) -> - | H57: =+INDEX('Consolidado (usd)'!$W$6:$Y$30,MATCH('Consolidado (usd) Power BI'!$B57,'Consolidado (usd)'!$E$6:$E$30,0),MATCH($A57,'Consolidado (usd)'!$AB$4:$AB$6,0)) -> -
A58: 2024 | B58: BAP | C58: =+INDEX('Consolidado (usd)'!$G$6:$I$30,MATCH('Consolidado (usd) Power BI'!B58,'Consolidado (usd)'!$E$6:$E$30,0),MATCH(A58,'Consolidado (usd)'!$AB$4:$AB$6,0)) -> - | D58: =+INDEX('Consolidado (usd)'!$J$6:$L$30,MATCH('Consolidado (usd) Power BI'!$B58,'Consolidado (usd)'!$E$6:$E$30,0),MATCH($A58,'Consolidado (usd)'!$AB$4:$AB$6,0)) -> 9 | E58: =+INDEX('Consolidado (usd)'!$M$6:$O$30,MATCH('Consolidado (usd) Power BI'!$B58,'Consolidado (usd)'!$E$6:$E$30,0),MATCH($A58,'Consolidado (usd)'!$AB$4:$AB$6,0)) -> - | F58: =+INDEX('Consolidado (usd)'!$Q$6:$S$30,MATCH('Consolidado (usd) Power BI'!$B58,'Consolidado (usd)'!$E$6:$E$30,0),MATCH($A58,'Consolidado (usd)'!$AB$4:$AB$6,0)) -> - | G58: =+INDEX('Consolidado (usd)'!$T$6:$V$30,MATCH('Consolidado (usd) Power BI'!$B58,'Consolidado (usd)'!$E$6:$E$30,0),MATCH($A58,'Consolidado (usd)'!$AB$4:$AB$6,0)) -> - | H58: =+INDEX('Consolidado (usd)'!$W$6:$Y$30,MATCH('Consolidado (usd) Power BI'!$B58,'Consolidado (usd)'!$E$6:$E$30,0),MATCH($A58,'Consolidado (usd)'!$AB$4:$AB$6,0)) -> -
A59: 2024 | B59: IFS | C59: =+INDEX('Consolidado (usd)'!$G$6:$I$30,MATCH('Consolidado (usd) Power BI'!B59,'Consolidado (usd)'!$E$6:$E$30,0),MATCH(A59,'Consolidado (usd)'!$AB$4:$AB$6,0)) -> 572.70124 | D59: =+INDEX('Consolidado (usd)'!$J$6:$L$30,MATCH('Consolidado (usd) Power BI'!$B59,'Consolidado (usd)'!$E$6:$E$30,0),MATCH($A59,'Consolidado (usd)'!$AB$4:$AB$6,0)) -> 7 | E59: =+INDEX('Consolidado (usd)'!$M$6:$O$30,MATCH('Consolidado (usd) Power BI'!$B59,'Consolidado (usd)'!$E$6:$E$30,0),MATCH($A59,'Consolidado (usd)'!$AB$4:$AB$6,0)) -> 81.814463 | F59: =+INDEX('Consolidado (usd)'!$Q$6:$S$30,MATCH('Consolidado (usd) Power BI'!$B59,'Consolidado (usd)'!$E$6:$E$30,0),MATCH($A59,'Consolidado (usd)'!$AB$4:$AB$6,0)) -> 0.00030728124 | G59: =+INDEX('Consolidado (usd)'!$T$6:$V$30,MATCH('Consolidado (usd) Power BI'!$B59,'Consolidado (usd)'!$E$6:$E$30,0),MATCH($A59,'Consolidado (usd)'!$AB$4:$AB$6,0)) -> - | H59: =+INDEX('Consolidado (usd)'!$W$6:$Y$30,MATCH('Consolidado (usd) Power BI'!$B59,'Consolidado (usd)'!$E$6:$E$30,0),MATCH($A59,'Consolidado (usd)'!$AB$4:$AB$6,0)) -> 0.0016614388
... A61: 2024 | B61: EL Comercio | C61: =+INDEX('Consolidado (usd)'!$G$6:$I$30,MATCH('Consolidado (usd) Power BI'!B61,'Consolidado (usd)'!$E$6:$E$30,0),MATCH(A61,'Consolidado (usd)'!$AB$4:$AB$6,0)) -> 952.91123 | D61: =+INDEX('Consolidado (usd)'!$J$6:$L$30,MATCH('Consolidado (usd) Power BI'!$B61,'Consolidado (usd)'!$E$6:$E$30,0),MATCH($A61,'Consolidado (usd)'!$AB$4:$AB$6,0)) -> 10 | E61: =+INDEX('Consolidado (usd)'!$M$6:$O$30,MATCH('Consolidado (usd) Power BI'!$B61,'Consolidado (usd)'!$E$6:$E$30,0),MATCH($A61,'Consolidado (usd)'!$AB$4:$AB$6,0)) -> 95.291123 | F61: =+INDEX('Consolidado (usd)'!$Q$6:$S$30,MATCH('Consolidado (usd) Power BI'!$B61,'Consolidado (usd)'!$E$6:$E$30,0),MATCH($A61,'Consolidado (usd)'!$AB$4:$AB$6,0)) -> 0.0049414289 | G61: =+INDEX('Consolidado (usd)'!$T$6:$V$30,MATCH('Consolidado (usd) Power BI'!$B61,'Consolidado (usd)'!$E$6:$E$30,0),MATCH($A61,'Consolidado (usd)'!$AB$4:$AB$6,0)) -> 0.14304476 | H61: =+INDEX('Consolidado (usd)'!$W$6:$Y$30,MATCH('Consolidado (usd) Power BI'!$B61,'Consolidado (usd)'!$E$6:$E$30,0),MATCH($A61,'Consolidado (usd)'!$AB$4:$AB$6,0)) -> -0.29473517

Sheet Consolidado (usd) (Orygen)
Q2: IQ_INT_INC_LOANS | R2: IQ_TOTAL_REV
G3: Remuneracion Directorio (USD 000) | H3: Remuneracion Directorio (USD 000) | J3: # Directores | M3: Prom. Por Director | Q3: % Ingresos | T3: % EBITDA | W3: % Utilidad Neta
B4: IQ | E4: Empresa | F4: Moneda | G4: 2024 | H4: 2023 | I4: 2022 | J4: 2024 | K4: 2023 | L4: 2022 | M4: 2024 | N4: 2023 | O4: 2022 | Q4: 2024 | R4: 2023 | S4: 2022 | T4: 2024 | U4: 2023 | V4: 2022 | W4: 2024 | X4: 2023 | Y4: 2022 | AB4: 2024
E5: Mineras | AB5: 2023
B6: IQ392824 | E6: Buenaventura | F6: USD | G6: 3383 | H6: 999 | I6: 2873 | J6: 9 | K6: 7 | L6: 7 | M6: =IFERROR(G6/J6,"-") -> 375.88889 | N6: =IFERROR(H6/K6,"-") -> 142.71429 | O6: =I6/L6 -> 410.42857 | Q6: {=G6/(_xll.ciqfunctions.udf.CIQ($B6,$R$2,"FY"&Q$4, , , , "USD")*1000)} -> 0.0029300064 | R6: {=H6/(_xll.ciqfunctions.udf.CIQ($B6,$R$2,"FY"&R$4, , , , "USD")*1000)} -> 0.0012126067 | S6: {=I6/(_xll.ciqfunctions.udf.CIQ($B6,$R$2,"FY"&S$4, , , , "USD")*1000)} -> 0.0034832602 | T6: {=G6/(_xll.ciqfunctions.udf.CIQ($B6,"IQ_EBITDA","FY"&Q$4, , , , "USD")*1000)} -> 0.0086220079 | U6: {=H6/(_xll.ciqfunctions.udf.CIQ($B6,"IQ_EBITDA","FY"&R$4, , , , "USD")*1000)} -> 0.0061043421 | V6: {=I6/(_xll.ciqfunctions.udf.CIQ($B6,"IQ_EBITDA","FY"&S$4, , , , "USD")*1000)} -> 0.022570863 | W6: {=G6/(_xll.ciqfunctions.udf.CIQ($B6,"IQ_ni","FY"&Q$4, , , , "USD")*1000)} -> 0.0084010241 | X6: {=H6/(_xll.ciqfunctions.udf.CIQ($B6,"IQ_ni","FY"&R$4, , , , "USD")*1000)} -> 0.050314782 | Y6: {=I6/(_xll.ciqfunctions.udf.CIQ($B6,"IQ_ni","FY"&S$4, , , , "USD")*1000)} -> 0.004768069 | AB6: 2022
B7: IQ6476057 | E7: Cerro Verde | F7: - | G7: - | H7: - | I7: - | J7: 5 | K7: 5 | L7: 5 | M7: =IFERROR(G7/J7,"-") -> - | N7: =IFERROR(H7/K7,"-") -> - | O7: - | Q7: - | R7: - | S7: - | T7: - | U7: - | V7: - | W7: - | X7: - | Y7: -
B8: IQ880120 | E8: Minsur | F8: USD | G8: 540 | H8: 538 | I8: 530 | J8: 8 | K8: 8 | L8: 8 | M8: =IFERROR(G8/J8,"-") -> 67.5 | N8: =IFERROR(H8/K8,"-") -> 67.25 | O8: =I8/L8 -> 66.25 | Q8: {=G8/(_xll.ciqfunctions.udf.CIQ($B8,$R$2,"FY"&Q$4, , , , "USD")*1000)} -> 0.00024880172 | R8: {=H8/(_xll.ciqfunctions.udf.CIQ($B8,$R$2,"FY"&R$4, , , , "USD")*1000)} -> 0.00026756186 | S8: {=I8/(_xll.ciqfunctions.udf.CIQ($B8,$R$2,"FY"&S$4, , , , "USD")*1000)} -> 0.00023296918 | T8: {=G8/(_xll.ciqfunctions.udf.CIQ($B8,"IQ_EBITDA","FY"&Q$4, , , , "USD")*1000)} -> 0.00038019682 | U8: {=H8/(_xll.ciqfunctions.udf.CIQ($B8,"IQ_EBITDA","FY"&R$4, , , , "USD")*1000)} -> 0.00044403324 | V8: {=I8/(_xll.ciqfunctions.udf.CIQ($B8,"IQ_EBITDA","FY"&S$4, , , , "USD")*1000)} -> 0.00040577953 | W8: {=G8/(_xll.ciqfunctions.udf.CIQ($B8,"IQ_ni","FY"&Q$4, , , , "USD")*1000)} -> 0.0011649329 | X8: {=H8/(_xll.ciqfunctions.udf.CIQ($B8,"IQ_ni","FY"&R$4, , , , "USD")*1000)} -> 0.0013609813 | Y8: {=I8/(_xll.ciqfunctions.udf.CIQ($B8,"IQ_ni","FY"&S$4, , , , "USD")*1000)} -> 0.0010680337 | AC8: Desde el 2018, los directores de Orygen reciben una retribución del US$ 2,000 por sesión de Directorio o comité asistida. Pluz Energía de igual manera. Para Engie la retribución es de US$ 5,000 por sesión de Directorio asistida y solo aplicable a los directores independientes.
B9: IQ877515 | E9: Volcan | F9: USD | G9: 14433 | H9: 10571 | I9: 7573 | J9: 7 | K9: 7 | L9: 7 | M9: =IFERROR(G9/J9,"-") -> 2061.8571 | N9: =IFERROR(H9/K9,"-") -> 1510.1429 | O9: =I9/L9 -> 1081.8571 | Q9: {=G9/(_xll.ciqfunctions.udf.CIQ($B9,$R$2,"FY"&Q$4, , , , "USD")*1000)} -> 0.01502622 | R9: {=H9/(_xll.ciqfunctions.udf.CIQ($B9,$R$2,"FY"&R$4, , , , "USD")*1000)} -> 0.011970522 | S9: {=I9/(_xll.ciqfunctions.udf.CIQ($B9,$R$2,"FY"&S$4, , , , "USD")*1000)} -> 0.0079609699 | T9: {=G9/(_xll.ciqfunctions.udf.CIQ($B9,"IQ_EBITDA","FY"&Q$4, , , , "USD")*1000)} -> 0.031959062 | U9: {=H9/(_xll.ciqfunctions.udf.CIQ($B9,"IQ_EBITDA","FY"&R$4, , , , "USD")*1000)} -> 0.04104143 | V9: {=I9/(_xll.ciqfunctions.udf.CIQ($B9,"IQ_EBITDA","FY"&S$4, , , , "USD")*1000)} -> 0.026543617 | W9: {=G9/(_xll.ciqfunctions.udf.CIQ($B9,"IQ_ni","FY"&Q$4, , , , "USD")*1000)} -> 0.10524819 | X9: {=H9/(_xll.ciqfunctions.udf.CIQ($B9,"IQ_ni","FY"&R$4, , , , "USD")*1000)} -> -1.0589001 | Y9: {=I9/(_xll.ciqfunctions.udf.CIQ($B9,"IQ_ni","FY"&S$4, , , , "USD")*1000)} -> -0.093054975
B10: IQ877687 | E10: Nexa Perú | F10: - | G10: 11342 | H10: 13951 | I10: 5496 | J10: 5 | K10: 5 | L10: 5 | M10: =IFERROR(G10/J10,"-") -> 2268.4 | N10: =IFERROR(H10/K10,"-") -> 2790.2 | O10: =I10/L10 -> 1099.2 | Q10: {=G10/(_xll.ciqfunctions.udf.CIQ($B10,$R$2,"FY"&Q$4, , , , "USD")*1000)} -> 0.012872224 | R10: {=H10/(_xll.ciqfunctions.udf.CIQ($B10,$R$2,"FY"&R$4, , , , "USD")*1000)} -> 0.018972254 | S10: {=I10/(_xll.ciqfunctions.udf.CIQ($B10,$R$2,"FY"&S$4, , , , "USD")*1000)} -> 0.0061587492 | T10: {=G10/(_xll.ciqfunctions.udf.CIQ($B10,"IQ_EBITDA","FY"&Q$4, , , , "USD")*1000)} -> 0.038106565 | U10: {=H10/(_xll.ciqfunctions.udf.CIQ($B10,"IQ_EBITDA","FY"&R$4, , , , "USD")*1000)} -> 0.075530026 | V10: {=I10/(_xll.ciqfunctions.udf.CIQ($B10,"IQ_EBITDA","FY"&S$4, , , , "USD")*1000)} -> 0.017338962 | W10: {=G10/(_xll.ciqfunctions.udf.CIQ($B10,"IQ_ni","FY"&Q$4, , , , "USD")*1000)} -> 2.6959829 | X10: {=H10/(_xll.ciqfunctions.udf.CIQ($B10,"IQ_ni","FY"&R$4, , , , "USD")*1000)} -> 0.2972662 | Y10: {=I10/(_xll.ciqfunctions.udf.CIQ($B10,"IQ_ni","FY"&S$4, , , , "USD")*1000)} -> 0.057947177 | AD10: 3000 | AF10: 2023 | AG10: 2022
B11: IQ284839929 | E11: Nexa US | F11: USD | G11: 7829 | H11: 7353 | I11: 7529 | J11: 9 | K11: 9 | L11: 9 | M11: =IFERROR(G11/J11,"-") -> 869.88889 | N11: =IFERROR(H11/K11,"-") -> 817 | O11: =I11/L11 -> 836.55556 | Q11: {=G11/(_xll.ciqfunctions.udf.CIQ($B11,$R$2,"FY"&Q$4, , , , "USD")*1000)} -> 0.0028299489 | R11: {=H11/(_xll.ciqfunctions.udf.CIQ($B11,$R$2,"FY"&R$4, , , , "USD")*1000)} -> 0.0028574948 | S11: {=I11/(_xll.ciqfunctions.udf.CIQ($B11,$R$2,"FY"&S$4, , , , "USD")*1000)} -> 0.0024815507 | T11: {=G11/(_xll.ciqfunctions.udf.CIQ($B11,"IQ_EBITDA","FY"&Q$4, , , , "USD")*1000)} -> 0.01286581 | U11: {=H11/(_xll.ciqfunctions.udf.CIQ($B11,"IQ_EBITDA","FY"&R$4, , , , "USD")*1000)} -> 0.02533927 | V11: {=I11/(_xll.ciqfunctions.udf.CIQ($B11,"IQ_EBITDA","FY"&S$4, , , , "USD")*1000)} -> 0.010850095 | W11: {=G11/(_xll.ciqfunctions.udf.CIQ($B11,"IQ_ni","FY"&Q$4, , , , "USD")*1000)} -> -0.038184656 | X11: {=H11/(_xll.ciqfunctions.udf.CIQ($B11,"IQ_ni","FY"&R$4, , , , "USD")*1000)} -> -0.025184267 | Y11: {=I11/(_xll.ciqfunctions.udf.CIQ($B11,"IQ_ni","FY"&S$4, , , , "USD")*1000)} -> 0.15150418 | AD11: Orygen | AF11: =19*2000*3+1*2*2000+2*2*2000+2*1*2000 -> 130000 | AG11: =10*3*AD10+1*3*AD10+1*2*AD10+2*1*AD10 -> 111000 | AI11: =19*3000*3+1*2*3000+2*2*3000+2*1*3000 -> 195000
B12: IQ29666569 | E12: Hochschild | F12: USD | G12: 8284 | H12: 7416 | I12: 8295 | J12: 9 | K12: 9 | L12: 9 | M12: =IFERROR(G12/J12,"-") -> 920.44444 | N12: =IFERROR(H12/K12,"-") -> 824 | O12: =I12/L12 -> 921.66667 | Q12: {=G12/(_xll.ciqfunctions.udf.CIQ($B12,$R$2,"FY"&Q$4, , , , "USD")*1000)} -> 0.0087411997 | R12: {=H12/(_xll.ciqfunctions.udf.CIQ($B12,$R$2,"FY"&R$4, , , , "USD")*1000)} -> 0.010690254 | S12: {=I12/(_xll.ciqfunctions.udf.CIQ($B12,$R$2,"FY"&S$4, , , , "USD")*1000)} -> 0.01127585 | T12: {=G12/(_xll.ciqfunctions.udf.CIQ($B12,"IQ_EBITDA","FY"&Q$4, , , , "USD")*1000)} -> 0.020628209 | U12: {=H12/(_xll.ciqfunctions.udf.CIQ($B12,"IQ_EBITDA","FY"&R$4, , , , "USD")*1000)} -> 0.032382158 | V12: {=I12/(_xll.ciqfunctions.udf.CIQ($B12,"IQ_EBITDA","FY"&S$4, , , , "USD")*1000)} -> 0.043011589 | W12: {=G12/(_xll.ciqfunctions.udf.CIQ($B12,"IQ_ni","FY"&Q$4, , , , "USD")*1000)} -> 0.08539766 | X12: {=H12/(_xll.ciqfunctions.udf.CIQ($B12,"IQ_ni","FY"&R$4, , , , "USD")*1000)} -> -0.13482166 | Y12: {=I12/(_xll.ciqfunctions.udf.CIQ($B12,"IQ_ni","FY"&S$4, , , , "USD")*1000)} -> 2.8014184 | AD12: PLuzEn | AF12: =13*3*AD10+1*2*AD10+1*1*AD10 -> 126000 | AG12: =AD10*10*3+1*3*AD10+AD10 -> 102000
E13: Utilities
B14: IQ883110 | E14: Orygen | F14: PEN | G14: =9339/H36 -> 2476.1374 | H14: 195 | I14: 110 | J14: 3 | K14: 3 | L14: 3 | M14: =IFERROR(G14/J14,"-") -> 825.37915 | N14: =IFERROR(H14/K14,"-") -> 65 | O14: =I14/L14 -> 36.666667 | Q14: {=G14/(_xll.ciqfunctions.udf.CIQ($B14,$R$2,"FY"&Q$4, , , , "USD")*1000)} -> 0.0033373202 | R14: {=H14/(_xll.ciqfunctions.udf.CIQ($B14,$R$2,"FY"&R$4, , , , "USD")*1000)} -> 0.00027611655 | S14: {=I14/(_xll.ciqfunctions.udf.CIQ($B14,$R$2,"FY"&S$4, , , , "USD")*1000)} -> 0.00017641598 | T14: {=G14/(_xll.ciqfunctions.udf.CIQ($B14,"IQ_EBITDA","FY"&Q$4, , , , "USD")*1000)} -> 0.0057819179 | U14: {=H14/(_xll.ciqfunctions.udf.CIQ($B14,"IQ_EBITDA","FY"&R$4, , , , "USD")*1000)} -> 0.00055216804 | V14: {=I14/(_xll.ciqfunctions.udf.CIQ($B14,"IQ_EBITDA","FY"&S$4, , , , "USD")*1000)} -> 0.00033349332 | W14: {=G14/(_xll.ciqfunctions.udf.CIQ($B14,"IQ_ni","FY"&Q$4, , , , "USD")*1000)} -> 0.010053016 | X14: {=H14/(_xll.ciqfunctions.udf.CIQ($B14,"IQ_ni","FY"&R$4, , , , "USD")*1000)} -> 0.00090808055 | Y14: {=I14/(_xll.ciqfunctions.udf.CIQ($B14,"IQ_ni","FY"&S$4, , , , "USD")*1000)} -> 0.00053117105 | AD14: Engie | AE14: =5000*2*10 -> 100000 | AF14: =11*2*5000 -> 110000
B15: IQ5885965 | E15: Pluzen | F15: PEN | G15: =9514/H36 -> 2522.5369 | H15: 84 | I15: 68 | J15: 7 | K15: 3 | L15: 3 | M15: =IFERROR(G15/J15,"-") -> 360.36241 | N15: =IFERROR(H15/K15,"-") -> 28 | O15: =I15/L15 -> 22.666667 | Q15: {=G15/(_xll.ciqfunctions.udf.CIQ($B15,$R$2,"FY"&Q$4, , , , "USD")*1000)} -> 0.0023208286 | R15: {=H15/(_xll.ciqfunctions.udf.CIQ($B15,$R$2,"FY"&R$4, , , , "USD")*1000)} -> 7.5471196e-05 | S15: {=I15/(_xll.ciqfunctions.udf.CIQ($B15,$R$2,"FY"&S$4, , , , "USD")*1000)} -> 6.6056509e-05 | T15: {=G15/(_xll.ciqfunctions.udf.CIQ($B15,"IQ_EBITDA","FY"&Q$4, , , , "USD")*1000)} -> 0.0095078864 | U15: {=H15/(_xll.ciqfunctions.udf.CIQ($B15,"IQ_EBITDA","FY"&R$4, , , , "USD")*1000)} -> 0.0003252131 | V15: {=I15/(_xll.ciqfunctions.udf.CIQ($B15,"IQ_EBITDA","FY"&S$4, , , , "USD")*1000)} -> 0.00026681898 | W15: {=G15/(_xll.ciqfunctions.udf.CIQ($B15,"IQ_ni","FY"&Q$4, , , , "USD")*1000)} -> 0.024799097 | X15: {=H15/(_xll.ciqfunctions.udf.CIQ($B15,"IQ_ni","FY"&R$4, , , , "USD")*1000)} -> 0.00071973199 | Y15: {=I15/(_xll.ciqfunctions.udf.CIQ($B15,"IQ_ni","FY"&S$4, , , , "USD")*1000)} -> 0.00054070052
B16: IQ5704688 | E16: Engie | F16: USD | G16: 1974 | H16: 100 | I16: 110 | J16: 7 | K16: 2 | L16: 2 | M16: =IFERROR(G16/J16,"-") -> 282 | N16: =IFERROR(H16/K16,"-") -> 50 | O16: =I16/L16 -> 55 | Q16: {=G16/(_xll.ciqfunctions.udf.CIQ($B16,$R$2,"FY"&Q$4, , , , "USD")*1000)} -> 0.0027257024 | R16: {=H16/(_xll.ciqfunctions.udf.CIQ($B16,$R$2,"FY"&R$4, , , , "USD")*1000)} -> 0.00014885316 | S16: {=I16/(_xll.ciqfunctions.udf.CIQ($B16,$R$2,"FY"&S$4, , , , "USD")*1000)} -> 0.00019823142 | T16: {=G16/(_xll.ciqfunctions.udf.CIQ($B16,"IQ_EBITDA","FY"&Q$4, , , , "USD")*1000)} -> 0.0075640009 | U16: {=H16/(_xll.ciqfunctions.udf.CIQ($B16,"IQ_EBITDA","FY"&R$4, , , , "USD")*1000)} -> 0.00061151607 | V16: {=I16/(_xll.ciqfunctions.udf.CIQ($B16,"IQ_EBITDA","FY"&S$4, , , , "USD")*1000)} -> 0.0005833625 | W16: {=G16/(_xll.ciqfunctions.udf.CIQ($B16,"IQ_ni","FY"&Q$4, , , , "USD")*1000)} -> 0.020024143 | X16: {=H16/(_xll.ciqfunctions.udf.CIQ($B16,"IQ_ni","FY"&R$4, , , , "USD")*1000)} -> 0.016666667 | Y16: {=I16/(_xll.ciqfunctions.udf.CIQ($B16,"IQ_ni","FY"&S$4, , , , "USD")*1000)} -> 0.0016884114
E17: Construcción
B18: IQ877414 | E18: Ferreycorp | F18: PEN | G18: =44340/H36 -> 11756.284 | H18: =42031/I36 -> 11318.433 | I18: 15183 | J18: 9 | K18: 9 | L18: 9 | M18: =IFERROR(G18/J18,"-") -> 1306.2538 | N18: =IFERROR(H18/K18,"-") -> 1257.6036 | O18: =I18/L18 -> 1687 | Q18: {=G18/(_xll.ciqfunctions.udf.CIQ($B18,$R$2,"FY"&Q$4, , , , "USD")*1000)} -> 0.0058478946 | R18: {=H18/(_xll.ciqfunctions.udf.CIQ($B18,$R$2,"FY"&R$4, , , , "USD")*1000)} -> 0.0060547217 | S18: {=I18/(_xll.ciqfunctions.udf.CIQ($B18,$R$2,"FY"&S$4, , , , "USD")*1000)} -> 0.0087941324 | T18: {=G18/(_xll.ciqfunctions.udf.CIQ($B18,"IQ_EBITDA","FY"&Q$4, , , , "USD")*1000)} -> 0.044382029 | U18: {=H18/(_xll.ciqfunctions.udf.CIQ($B18,"IQ_EBITDA","FY"&R$4, , , , "USD")*1000)} -> 0.051510977 | V18: {=I18/(_xll.ciqfunctions.udf.CIQ($B18,"IQ_EBITDA","FY"&S$4, , , , "USD")*1000)} -> 0.07777573 | W18: {=G18/(_xll.ciqfunctions.udf.CIQ($B18,"IQ_ni","FY"&Q$4, , , , "USD")*1000)} -> 0.090711388 | X18: {=H18/(_xll.ciqfunctions.udf.CIQ($B18,"IQ_ni","FY"&R$4, , , , "USD")*1000)} -> 0.096878885 | Y18: {=I18/(_xll.ciqfunctions.udf.CIQ($B18,"IQ_ni","FY"&S$4, , , , "USD")*1000)} -> 0.13806748
B19: IQ882917 | E19: Aenza | F19: PEN | G19: =32000/H36 -> 8484.4628 | H19: =36500/I36 -> 9829.0023 | I19: 438 | J19: 9 | K19: 9 | L19: 9 | M19: =IFERROR(G19/J19,"-") -> 942.71809 | N19: =IFERROR(H19/K19,"-") -> 1092.1114 | O19: =I19/L19 -> 48.666667 | Q19: {=G19/(_xll.ciqfunctions.udf.CIQ($B19,$R$2,"FY"&Q$4, , , , "USD")*1000)} -> 0.01824931 | R19: {=H19/(_xll.ciqfunctions.udf.CIQ($B19,$R$2,"FY"&R$4, , , , "USD")*1000)} -> 0.0084854614 | S19: {=I19/(_xll.ciqfunctions.udf.CIQ($B19,$R$2,"FY"&S$4, , , , "USD")*1000)} -> 0.00037873753 | T19: {=G19/(_xll.ciqfunctions.udf.CIQ($B19,"IQ_EBITDA","FY"&Q$4, , , , "USD")*1000)} -> 0.069362558 | U19: {=H19/(_xll.ciqfunctions.udf.CIQ($B19,"IQ_EBITDA","FY"&R$4, , , , "USD")*1000)} -> 0.061072634 | V19: {=I19/(_xll.ciqfunctions.udf.CIQ($B19,"IQ_EBITDA","FY"&S$4, , , , "USD")*1000)} -> 0.0042332784 | W19: {=G19/(_xll.ciqfunctions.udf.CIQ($B19,"IQ_ni","FY"&Q$4, , , , "USD")*1000)} -> -0.12929919 | X19: {=H19/(_xll.ciqfunctions.udf.CIQ($B19,"IQ_ni","FY"&R$4, , , , "USD")*1000)} -> 0.43144724 | Y19: {=I19/(_xll.ciqfunctions.udf.CIQ($B19,"IQ_ni","FY"&S$4, , , , "USD")*1000)} -> -0.0036980653
B20: IQ874008 | E20: UNACEM | F20: PEN | G20: =6724/H36 -> 1782.7978 | H20: =6323/I36 -> 1702.7063 | I20: 2122 | J20: 11 | K20: 11 | L20: 11 | M20: =IFERROR(G20/J20,"-") -> 162.07252 | N20: =IFERROR(H20/K20,"-") -> 154.79149 | O20: =I20/L20 -> 192.90909 | Q20: {=G20/(_xll.ciqfunctions.udf.CIQ($B20,$R$2,"FY"&Q$4, , , , "USD")*1000)} -> 0.00098089029 | R20: {=H20/(_xll.ciqfunctions.udf.CIQ($B20,$R$2,"FY"&R$4, , , , "USD")*1000)} -> 0.00099164496 | S20: {=I20/(_xll.ciqfunctions.udf.CIQ($B20,$R$2,"FY"&S$4, , , , "USD")*1000)} -> 0.0013519188 | T20: {=G20/(_xll.ciqfunctions.udf.CIQ($B20,"IQ_EBITDA","FY"&Q$4, , , , "USD")*1000)} -> 0.0042135553 | U20: {=H20/(_xll.ciqfunctions.udf.CIQ($B20,"IQ_EBITDA","FY"&R$4, , , , "USD")*1000)} -> 0.0043552321 | V20: {=I20/(_xll.ciqfunctions.udf.CIQ($B20,"IQ_EBITDA","FY"&S$4, , , , "USD")*1000)} -> 0.0052873574 | W20: {=G20/(_xll.ciqfunctions.udf.CIQ($B20,"IQ_ni","FY"&Q$4, , , , "USD")*1000)} -> 0.014937774 | X20: {=H20/(_xll.ciqfunctions.udf.CIQ($B20,"IQ_ni","FY"&R$4, , , , "USD")*1000)} -> 0.012409841 | Y20: {=I20/(_xll.ciqfunctions.udf.CIQ($B20,"IQ_ni","FY"&S$4, , , , "USD")*1000)} -> 0.014572914
B21: IQ877470 | E21: Pacasmayo | F21: PEN | G21: =6032/H36 -> 1599.3212 | H21: =5941/I36 -> 1599.8384 | I21: 1361 | J21: 7 | K21: 7 | L21: 7 | M21: =IFERROR(G21/J21,"-") -> 228.47446 | N21: =IFERROR(H21/K21,"-") -> 228.54835 | O21: =I21/L21 -> 194.42857 | Q21: {=G21/(_xll.ciqfunctions.udf.CIQ($B21,$R$2,"FY"&Q$4, , , , "USD")*1000)} -> 0.0030494356 | R21: {=H21/(_xll.ciqfunctions.udf.CIQ($B21,$R$2,"FY"&R$4, , , , "USD")*1000)} -> 0.0030465495 | S21: {=I21/(_xll.ciqfunctions.udf.CIQ($B21,$R$2,"FY"&S$4, , , , "USD")*1000)} -> 0.0024502871 | T21: {=G21/(_xll.ciqfunctions.udf.CIQ($B21,"IQ_EBITDA","FY"&Q$4, , , , "USD")*1000)} -> 0.011251569 | U21: {=H21/(_xll.ciqfunctions.udf.CIQ($B21,"IQ_EBITDA","FY"&R$4, , , , "USD")*1000)} -> 0.011502932 | V21: {=I21/(_xll.ciqfunctions.udf.CIQ($B21,"IQ_EBITDA","FY"&S$4, , , , "USD")*1000)} -> 0.01049734 | W21: {=G21/(_xll.ciqfunctions.udf.CIQ($B21,"IQ_ni","FY"&Q$4, , , , "USD")*1000)} -> 0.03033061 | X21: {=H21/(_xll.ciqfunctions.udf.CIQ($B21,"IQ_ni","FY"&R$4, , , , "USD")*1000)} -> 0.035174658 | Y21: {=I21/(_xll.ciqfunctions.udf.CIQ($B21,"IQ_ni","FY"&S$4, , , , "USD")*1000)} -> 0.029317674
E22: Consumo
B23: IQ216401988 | E23: Inretail | F23: PEN | G23: =72200/H36 -> 19143.069 | H23: =65609/I36 -> 17667.699 | I23: 15182 | J23: 6 | K23: 6 | L23: 6 | M23: =IFERROR(G23/J23,"-") -> 3190.5115 | N23: =IFERROR(H23/K23,"-") -> 2944.6165 | O23: =I23/L23 -> 2530.3333 | Q23: {=G23/(_xll.ciqfunctions.udf.CIQ($B23,$R$2,"FY"&Q$4, , , , "USD")*1000)} -> 0.003329742 | R23: {=H23/(_xll.ciqfunctions.udf.CIQ($B23,$R$2,"FY"&R$4, , , , "USD")*1000)} -> 0.0031447962 | S23: {=I23/(_xll.ciqfunctions.udf.CIQ($B23,$R$2,"FY"&S$4, , , , "USD")*1000)} -> 0.0029233346 | T23: {=G23/(_xll.ciqfunctions.udf.CIQ($B23,"IQ_EBITDA","FY"&Q$4, , , , "USD")*1000)} -> 0.028913505 | U23: {=H23/(_xll.ciqfunctions.udf.CIQ($B23,"IQ_EBITDA","FY"&R$4, , , , "USD")*1000)} -> 0.028010682 | V23: {=I23/(_xll.ciqfunctions.udf.CIQ($B23,"IQ_EBITDA","FY"&S$4, , , , "USD")*1000)} -> 0.027955501 | W23: {=G23/(_xll.ciqfunctions.udf.CIQ($B23,"IQ_ni","FY"&Q$4, , , , "USD")*1000)} -> 0.074329235 | X23: {=H23/(_xll.ciqfunctions.udf.CIQ($B23,"IQ_ni","FY"&R$4, , , , "USD")*1000)} -> 0.070112688 | Y23: {=I23/(_xll.ciqfunctions.udf.CIQ($B23,"IQ_ni","FY"&S$4, , , , "USD")*1000)} -> 0.078541132
B24: IQ877482 | E24: Alicorp | F24: - | G24: - | H24: =3474/I36 -> 935.50559 | I24: =3691/H36 -> 978.62976 | J24: 9 | K24: 9 | L24: 9 | M24: =IFERROR(G24/J24,"-") -> - | N24: =IFERROR(H24/K24,"-") -> 103.94507 | O24: =I24/L24 -> 108.73664 | Q24: - | R24: {=H24/(_xll.ciqfunctions.udf.CIQ($B24,$R$2,"FY"&R$4, , , , "USD")*1000)} -> 0.0003146992 | S24: {=I24/(_xll.ciqfunctions.udf.CIQ($B24,$R$2,"FY"&S$4, , , , "USD")*1000)} -> 0.00024217784 | T24: - | U24: {=H24/(_xll.ciqfunctions.udf.CIQ($B24,"IQ_EBITDA","FY"&R$4, , , , "USD")*1000)} -> 0.0031917914 | V24: {=I24/(_xll.ciqfunctions.udf.CIQ($B24,"IQ_EBITDA","FY"&S$4, , , , "USD")*1000)} -> 0.0023824214 | W24: - | X24: {=H24/(_xll.ciqfunctions.udf.CIQ($B24,"IQ_ni","FY"&R$4, , , , "USD")*1000)} -> 0.018442525 | Y24: {=I24/(_xll.ciqfunctions.udf.CIQ($B24,"IQ_ni","FY"&S$4, , , , "USD")*1000)} -> 0.0071119876
E25: Financieras
B26: IQ396812 | E26: BAP | F26: PEN | G26: - | H26: =7387/I36 -> 1989.2285 | I26: 2060 | J26: 9 | K26: 9 | L26: 9 | M26: =IFERROR(G26/J26,"-") -> - | N26: =IFERROR(H26/K26,"-") -> 221.02539 | O26: =I26/L26 -> 228.88889 | Q26: - | R26: {=H26/(_xll.ciqfunctions.udf.CIQ($B26,$Q$2,"FY"&R$4, , , , "USD")*1000)} -> 0.00039295699 | S26: {=I26/(_xll.ciqfunctions.udf.CIQ($B26,$Q$2,"FY"&S$4, , , , "USD")*1000)} -> 0.00052272324 | T26: - | U26: - | V26: - | W26: - | X26: {=H26/(_xll.ciqfunctions.udf.CIQ($B26,"IQ_ni","FY"&R$4, , , , "USD")*1000)} -> 0.0015182282 | Y26: {=I26/(_xll.ciqfunctions.udf.CIQ($B26,"IQ_ni","FY"&S$4, , , , "USD")*1000)} -> 0.0016882645
B27: IQ35196267 | E27: IFS | F27: PEN | G27: =2160/H36 -> 572.70124 | H27: =2104/I36 -> 566.58139 | I27: 1029 | J27: 7 | K27: 7 | L27: 7 | M27: =IFERROR(G27/J27,"-") -> 81.814463 | N27: =IFERROR(H27/K27,"-") -> 80.940199 | O27: =I27/L27 -> 147 | Q27: {=G27/(_xll.ciqfunctions.udf.CIQ($B27,$Q$2,"FY"&Q$4, , , , "USD")*1000)} -> 0.00030728124 | R27: {=H27/(_xll.ciqfunctions.udf.CIQ($B27,$Q$2,"FY"&R$4, , , , "USD")*1000)} -> 0.00029548856 | S27: {=I27/(_xll.ciqfunctions.udf.CIQ($B27,$Q$2,"FY"&S$4, , , , "USD")*1000)} -> 0.00066758002 | T27: - | U27: - | V27: - | W27: {=G27/(_xll.ciqfunctions.udf.CIQ($B27,"IQ_ni","FY"&Q$4, , , , "USD")*1000)} -> 0.0016614388 | X27: {=H27/(_xll.ciqfunctions.udf.CIQ($B27,"IQ_ni","FY"&R$4, , , , "USD")*1000)} -> 0.0019613546 | Y27: {=I27/(_xll.ciqfunctions.udf.CIQ($B27,"IQ_ni","FY"&S$4, , , , "USD")*1000)} -> 0.0023498218
B28: IQ873805 | E28: BBVA | F28: PEN | G28: =16000/H36 -> 4242.2314 | H28: =15000/I36 -> 4039.316 | I28: 4460 | J28: 11 | K28: 11 | L28: 11 | M28: =IFERROR(G28/J28,"-") -> 385.6574 | N28: =IFERROR(H28/K28,"-") -> 367.21055 | O28: =I28/L28 -> 405.45455 | Q28: {=G28/(_xll.ciqfunctions.udf.CIQ($B28,$Q$2,"FY"&Q$4, , , , "USD")*1000)} -> 0.0019794175 | R28: {=H28/(_xll.ciqfunctions.udf.CIQ($B28,$Q$2,"FY"&R$4, , , , "USD")*1000)} -> 0.001977354 | S28: {=I28/(_xll.ciqfunctions.udf.CIQ($B28,$Q$2,"FY"&S$4, , , , "USD")*1000)} -> 0.0029601156 | T28: - | U28: - | V28: - | W28: {=G28/(_xll.ciqfunctions.udf.CIQ($B28,"IQ_ni","FY"&Q$4, , , , "USD")*1000)} -> 0.0084981081 | X28: {=H28/(_xll.ciqfunctions.udf.CIQ($B28,"IQ_ni","FY"&R$4, , , , "USD")*1000)} -> 0.0080053967 | Y28: {=I28/(_xll.ciqfunctions.udf.CIQ($B28,"IQ_ni","FY"&S$4, , , , "USD")*1000)} -> 0.0088401231
E29: Servicios de Comunicación
B30: IQ4493526 | E30: EL Comercio | F30: PEN | G30: =3594/H36 -> 952.91123 | H30: =4326/I36 -> 1164.9387 | I30: =4942/J36 -> 1297.4193 | J30: 10 | K30: 10 | L30: 10 | M30: =IFERROR(G30/J30,"-") -> 95.291123 | N30: =IFERROR(H30/K30,"-") -> 116.49387 | O30: =I30/L30 -> 129.74193 | Q30: {=G30/(_xll.ciqfunctions.udf.CIQ($B30,$R$2,"FY"&Q$4, , , , "USD")*1000)} -> 0.0049414289 | R30: {=H30/(_xll.ciqfunctions.udf.CIQ($B30,$R$2,"FY"&R$4, , , , "USD")*1000)} -> 0.0061307612 | S30: {=I30/(_xll.ciqfunctions.udf.CIQ($B30,$R$2,"FY"&S$4, , , , "USD")*1000)} -> 0.0061965077 | T30: {=G30/(_xll.ciqfunctions.udf.CIQ($B30,"IQ_EBITDA","FY"&Q$4, , , , "USD")*1000)} -> 0.14304476 | U30: {=H30/(_xll.ciqfunctions.udf.CIQ($B30,"IQ_EBITDA","FY"&R$4, , , , "USD")*1000)} -> 0.068876593 | V30: {=I30/(_xll.ciqfunctions.udf.CIQ($B30,"IQ_EBITDA","FY"&S$4, , , , "USD")*1000)} -> 0.043875061 | W30: {=G30/(_xll.ciqfunctions.udf.CIQ($B30,"IQ_ni","FY"&Q$4, , , , "USD")*1000)} -> -0.29473517 | X30: {=H30/(_xll.ciqfunctions.udf.CIQ($B30,"IQ_ni","FY"&R$4, , , , "USD")*1000)} -> -0.06021295 | Y30: {=I30/(_xll.ciqfunctions.udf.CIQ($B30,"IQ_ni","FY"&S$4, , , , "USD")*1000)} -> 0.29427146
F31: TC
G32: No separan Key Management de Directores | H32: No separan Key Management de Directores
H35: 2024 | I35: 2023 | J35: 2022
G36: TC | H36: =1/H37 -> 3.7716 | I36: =1/I37 -> 3.7135 | J36: =1/J37 -> 3.8091 | N36: ="$USDPEN" -> $USDPEN
H37: {=(_xll.ciqfunctions.udf.CIQ($B24,$R$2,"FY"&Q$4, , , ,"USD"))/(_xll.ciqfunctions.udf.CIQ($B24,$R$2,"FY"&Q$4, , , ,))} -> 0.26513946 | I37: {=(_xll.ciqfunctions.udf.CIQ($B24,$R$2,"FY"&R$4, , , ,"USD"))/(_xll.ciqfunctions.udf.CIQ($B24,$R$2,"FY"&R$4, , , ,))} -> 0.26928773 | J37: {=(_xll.ciqfunctions.udf.CIQ($B24,$R$2,"FY"&S$4, , , ,"USD"))/(_xll.ciqfunctions.udf.CIQ($B24,$R$2,"FY"&S$4, , , ,))} -> 0.26252921

Sheet Sheet3
